Workbook
Name _Hlk107499372: 'Project Summaries'!$B$4
Name _Hlk125463371: 'Institute Background'!#REF!
Name _Hlk125463384: 'Institute Background'!#REF!
Name _Hlk125463491: 'Institute Background'!#REF!

Sheet Info
A1: Purpose | B1: The purpose of this workbook is to aggregate USGS fiscal-year reporting from a series of 5 years: 2016-2020. Whenever possible, this template format follows what was used for reporting in FY21. The USGS uses these data to demonstrate the value of the work accomplished by WRRI's. The USGS gets asked questions from different stakeholders - this is the reason for the multiple characterizations of each project. We suggest reviewing the entire spreadsheet before filling it out. While we tried to provide a list of what was accessible from the USGS database for these years, it is the responsibility each Institute to verify the completeness of the Project lists ("Project IDs" present in most tabs) and add whatever is missing.
A4: General Instructions | B4: A column heading in italics indicates that the field should be populated from a drop-down menu. Example entries are provided in blue text; you may overwrite them. We have worked to provide a complete list of options for each. To provide ample room for further details, most tabs have reserved the last column for "Additional Comments". Diversity, equity, inclusion, accessibility, and justice are included in multiple pages. Because of the variability in how this is addressed, please provide what information you can in the space provided. On several pages, specifics are asked about students, equipment, etc. These items were included because they are reported by many Institutes. Please put "NA" if this information was not tracked (e.g., not available) and it is a numeric answer. This will help distinguish from 0. For the science characterization on the "Significant Impact" and "Project Overview" tabs, we have provided drop-down menus of USGS research topics as well as those from the keywords list. We have also provided an "Additional Keywords" column so that you can provide specific terms that may be relatively new in terms of innovation, emerging contaminants, etc. For the "Significant Impact" tab, please describe three topics on which your Institute has focused, drawing from the general USGS priorities described in Circular 1488 (https://doi.org/10.3133/cir1488) and listed in the dropdown menu. In describing these impacts, please explain the relation to key water issues for the Institute and how they relate to your proposal process, outreach and education, research priorities, or other activities. Each of these descriptions must be limited to 300 words. Please remember to copy your Institute's 2019 evaluation action-items into the workbook and provide a response of how these were addressed.
A5: What to Report | B5: Responses to the "Project Overview," "Project Summaries," "Conference Presentations," "Education and Outreach," "Social Media", "USGS Collaboration", and "Other Activity" tabs should ONLY include activities supported by awards from THIS FIVE-YEAR AWARD CYCLE. Responses to the "doi Products", "other Products", and "Awards and Achievements" tabs may reference projects from this 5-year cycle or previous years, as long as they were published during this 5-year cycle (i.e., a citation date with years 2016-2020). Only report products and awards that were not included in previous 5-year evaluations. In the "Project Overview" tab, identifying the "acedemic Institution of the PI" supplements the information collected for "Congressional Districts" so that this can describe field area. For reporting numbers of funded students, please list WRRA federally funded students ONLY in columns J-L, and non-federal (matching) funded students ONLY in column M.
A6: Instructions for selecting the Project ID | B6: Project ID's have NOT been pre-populated, but a preliminary list needing verification is available in the Cover Sheet for the Institute. We anticipate that each Institute will have an Administration and/or Outreach budget, so these should be populated in column A and B on the "Project Overview" and column A on the "Project Summaries" tabs. Please use your own Institute-specific numbering scheme for the "Project ID" - these need to be differentiable so that they can be integrated with project summaries. If your Institute doesn't have a numbering scheme, please use "SS_YYYY_name" as the "Project ID," where SS is two-letter state abbreviation, YYYY is four digit award year, and name is last name of lead PI or the name of the activity (e.g., "Admin"). If you want to include figures, please paste an image in the space to the right of the project summary. Please use the original Project IDs for 2016-2020 if they existed. This may or may not be included in the pre-population.
A7: Report Submission | B7: Please email your completed report to gs-w.wrri.web.team@usgs.gov.

Sheet Institute Background
A1: Please provide background information about your institute
B2: Use Only This Column
A3: Name of Institute | B3: Illinois Water Resources Center
A4: University | B4: University of Illinois Urbana-Champaign
A5: Director | B5: Brian Miller (2016-2017) Yu-Feng Lin (2018-2020)
A6: Associate Director (NA if none) | B6: NA
A7: How many other science staff? [not administrative] | B7: 1
A8: How many administrative staff are in your institute? | B8: 3
A9: Do you employ students in institute? | B9: yes
A10: Is the WRRI integrated with other institutes? | B10: No
A11: Is there cost-sharing of administrative expenses? | B11: Yes
A12: Does Institute collect information that addresses questions of diversity, equity, inclusion, accessibility, and justice? | B12: No
A13: There are a range of approaches, so please explain. | B13: NA
A15: How much of individual postitions are funded by WRRA appropriated funds? (% [FTE] of total position) | B15: Average (automatically calculated) | C15: Year 1 | D15: Year 2 | E15: Year 3 | F15: Year 4 | G15: Year 5
A16: Director | B16: =AVERAGE(C16:G16) -> 8.6 | C16: 5 | D16: 0 | E16: 0 | F16: 0 | G16: 38
A17: Other Science Staff | B17: =AVERAGE(C17:G17) -> 13.2 | C17: 0 | D17: 0 | E17: 0 | F17: 33 | G17: 33
A18: Administrative Staff | B18: =AVERAGE(C18:G18) -> 32.266667 | C18: =SUM(41+25+7)/3 -> 24.333333 | D18: =SUM(12+20+8) -> 40 | E18: 0 | F18: 47 | G18: 50
A19: Students | B19: =AVERAGE(C19:G19) -> 10 | C19: 25 | D19: 25 | E19: 0 | F19: 0 | G19: 0
A20: Source(s) of additional funding for salary
A21: Director | B21: Office of the Vice Chancellor for Research
A22: Other Science Staff | B22: Department of Civil and Environmental Engineering
A23: Administrative Staff | B23: Office of the Vice Chancellor for Research
A24: Students | B24: NA
A26: Does host institution provide discretionary funds? | B26: Yes | C26: Year 1 | D26: Year 2 | E26: Year 3 | F26: Year 4 | G26: Year 5
A27: How much (by year)? How were these used? | B27: office supplies and refreshments for IWRC hosted events | C27: 10000 | D27: 10000 | E27: 10000 | F27: 10000 | G27: 10000
C28: Enter yearly breakdown below, or enter one response in column B if schedule does not vary year to year.
A29: Within-Institute base-award (104b) schedule | C29: Year 1 | D29: Year 2 | E29: Year 3 | F29: Year 4 | G29: Year 5
A30: When is the yearly call for proposals? | B30: September | C30: months | D30: months | E30: months | F30: months | G30: months
A31: When are proposals due? | B31: October | C31: months | D31: months | E31: months | F31: months | G31: months
A32: Does Institute plan for multi-year Awards? | B32: No | C32: yes/no | D32: yes/no | E32: yes/no | F32: yes/no | G32: yes/no
A33: How often does Institute have a symposium? (yr) | B33: 3 or more years | C33: 1,2,3 | D33: 1,2,3 | E33: 1,2,3 | F33: 1,2,3 | G33: 1,2,3
A34: When is symposium? | B34: November | C34: months | D34: months | E34: months | F34: months | G34: months
A35: Are there other Institutions that are symposium co-sponsors? | B35: No | C35: yes/no | D35: yes/no | E35: yes/no | F35: yes/no | G35: yes/no
A36: IF YES, list co-sponsors
A38: Advisory Board
A39: Frequency of meetings | B39: semi-annual
A40: Number of Members | B40: 4
A41: Does board review base-award (104b) proposals? | B41: No
A42: Does board guied base-award priorities? | B42: No
A43: Do board members have a term? (NA or years) | B43: No
A44: How else does board contribute? | B44: The board provides strategic guidance for IWRC
A45: Sponsorship of or coordination with Outside Advisory Groups? List | B45: NA

Sheet Advisory Board
A2: Advisory Board Members (name) | B2: Institution | C2: Beginning of Term | D2: End of Term (Actual/ Expected)
A3: Susan Martinis | B3: University of Illinois Urbana-Champaign | C3: 2016 | D3: NA
A4: Kimberlee Kidwell | B4: University of Illinois Urbana-Champaign | C4: 2016 | D4: 2020
A5: Evan Delucia | B5: University of Illinois Urbana-Champaign | C5: 2016 | D5: 2020
A6: Mark Ryan | B6: University of Illinois Urbana-Champaign | C6: 2016 | D6: 2021
A7: German A. Bollero | B7: University of Illinois Urbana-Champaign | C7: 2020 | D7: NA
A8: Madhu Khanna | B8: University of Illinois Urbana-Champaign | C8: 2020 | D8: NA
A9: Praveen Kumar | B9: University of Illinois Urbana-Champaign | C9: 2021 | D9: NA

Sheet Scientific Integrity
A1: Please provide information on how your Institute manages scientific integrity
B2: Use Only This Column
A3: Base-award process (104b)
A4: Are review criteria included in the proposal solicitation (RFP)? | B4: Yes
A5: Are proposals technically reviewed? | B5: Yes
A6: Who reviews base-award proposals? | B6: IWRC's Research Scientist identifies and recruits reviewers
A7: How many reviewers read each proposal? | B7: at least 3
A8: How is review process documented? | B8: Reviewers complete a Google form
A9: Who determines which proposals are selected for funding? | B9: IWRC's Research Scientist and Director
A10: Do all proposals receive comments from review process? | B10: Yes
A11: How are research priorities selected? | B11: Selected by the Director
A14: National competitive-grant process (104g)
A15: Does your institute require statements of interest? | B15: No
A16: How long before the deadline are proposals due to the Institute? | B16: 2 weeks
A17: Does the Institute interact with PIs who are preparing proposals? | B17: Yes
A18: If Institute interacts with PIs, is there requested statement of interest to initiate conversation? | B18: No
A19: If Institute interacts with PIs, is there training on proposal preparation? | B19: No
A20: If Institute interacts with PIs, is there fostering for collaboration for PIs with complementary ideas ? | B20: Yes
A21: If Institute interacts with PIs, is there Administrative Review of proposals? Review confirming completeness for rubric and required elements? | B21: Yes
A22: If Institute interact with PIs, is there support for budget development and review of budget? | B22: Yes
A23: How else does the Institute interact with PIs who are preparing proposals?
A24: Who submits the proposals? | B24: University Research Office
A27: Publications
A28: Does the Institute have a review process for publications funded by WRRA? | B28: No
A29: If papers are technically reviewed, who does this?
A30: How many base-award funded projects resulted in at least 1 peer-reviewed publication? | B30: 10
A31: How many base-award funded projects resulted in publically accessible (published) data? | B31: NA

Sheet By Year Summary
H1: Note: if this information wasn't tracked, enter "NA".
C2: 2016 | D2: 2017 | E2: 2018 | F2: 2019 | G2: 2020
B3: How many WRRI-involved students ended up working with USGS during WRRI project? | C3: NA | D3: NA | E3: NA | F3: NA | G3: NA
B4: How many WRRI-involved students ended up working at USGS sometime after WRRI project? | C4: NA | D4: NA | E4: NA | F4: NA | G4: NA
B5: Matching Funds by Source and Year | C5: 2016 | D5: 2017 | E5: 2018 | F5: 2019 | G5: 2020
B6: University | C6: 184670 | D6: 186237 | E6: 184670 | F6: 185377 | G6: 250290
B7: State Appropriations
B8: State Grants & Contracts
B9: Federal Grants & Contracts
B10: Foundation Grants & Contracts
B11: Private Sector Grants & Contracts
B12: Sales & Services
B13: Other:
B14: Other:
B15: Other:
B16: Other:
B17: Other:
B21: Prinicipal Investigators by Rank and Year (number) | C21: 2016 | D21: 2017 | E21: 2018 | F21: 2019 | G21: 2020
B22: Research Staff | C22: 0 | D22: 0 | E22: 1 | F22: 1 | G22: 2
B23: Assistant Professor and below | C23: 1 | D23: 3 | E23: 3 | F23: 3 | G23: 2
B24: Associate Professor | C24: 1 | D24: 0 | E24: 1 | F24: 0 | G24: 0
B25: Professor | C25: 2 | D25: 2 | E25: 0 | F25: 1 | G25: 2
B26: unknown | C26: 0 | D26: 0 | E26: 0 | F26: 0 | G26: 0
B27: Total
B29: Unspent Funds | C29: 2016 | D29: 2017 | E29: 2018 | F29: 2019 | G29: 2020
B30: Base Award Funds (104b) | C30: 0 | D30: 0 | E30: 0 | F30: 0 | G30: 0
B31: National Competitive Awards (104g) | C31: 0 | D31: 0 | E31: 0 | F31: 0 | G31: 0
B32: Coordination Awards | C32: 0 | D32: 0 | E32: 0 | F32: 0 | G32: 0
B34: Was an extension requested for the base award? (104b) | C34: no | D34: no | E34: yes | F34: yes | G34: yes

Sheet Significant Impact
A1: The Three Most Significant Impacts of WRRI Accomplishments for the 5-year Period | D1: Science Characterization
A2: Descriptive Phrase (about 15-word limit) | B2: Summary of Impact (Please describe three impacts on which your Institute has focused, drawing from the general USGS priorities described in Circular 1488 listed in the tab in column D, a dropdown menu. In describing these impacts, please relate to key science issues for the Institute and briefly explain how they relate to your proposal process, outreach and education, research priorities, or other activities. Each of these descriptions must be limited to 300 words. ) | C2: Relevant Project ID or IDs (for the 5-year reporting period, as needed to frame discussion) | D2: WRRI Science Priority that Best Aligns with this Issue, from Circular 1488. (Select one from the list) | E2: Keyword (Primary. Use supplied list) | F2: Additional Keywords (Separate keywords with a comma) | G2: USGS Cross-Discipline Science Topic (Select one) | H2: USGS Cross-Discipline Landscapes (Select one)
A3: Impact 1 : Nutrient Reduction | B3: Saturated buffer zones (SBZs) are considered a possible best management practice to intercept tile drainage water prior to discharge in streams; however, understanding the travel times (distances) that are needed for the SBZ systems to be effective has not been well documented. Results from a tracer test quantified the travel times for waters in SBZ situated in glacial materials. The initial calculations conducted prior to the test suggested a travel time of approximately 70 days. After injection of the tracer, the down-gradient wells reached their peak tracer concentrations in 13–15 days, which was the result of a higher than anticipated hydraulic gradient. Despite the shorter time, the data showed that between 38% and 100% of the nitrate introduced from the tile drainage system was removed along the travel path. Because the observation wells were different distances from the diversion tile, the results showed a linear relationship between distance (time) traveled and nitrate reduction. These data could be used to help develop SBZ systems that would provide the optimal reduction, given the limitations of the land available. Additionally, research was conducted to help the state of Illinois achieve its nutrient reduction targets of 20% by 2020 and 45% by 2040 to combat hypoxia in the Gulf of Mexico caused by the lack of denitrification in treatment wetlands. In 2016 and 2017 in Bureau County, Illinois, sediment organic matter concentrations were highest nearest the inlet and decreased to the wetland outlet, whereas NO3- decreased from the inlet to the outlet at the same locations. The outlet half of the wetland consistently had higher concentrations and more labile organic matter with a higher abundance of known denitrifying bacteria, resulting in higher removal efficiency as captured tile drainage moved through the wetland toward the outlet. | C3: 2016IL311B; 2017IL330B; 2017IL331B; 2018IL340B; 2018IL338B; 2020IL216B; 2020IL218B | D3: Watershed and Ecosystem Function
A4: Impact 2 : Critical Contaminant Monitoring and Solutions | B4: Seasonal trends were identified in the concentration of chloride (Cl-) from deicing agents in a watershed. Results showed elevated concentrations in the winter, whereas periodic spikes during the summer followed precipitation events. The spikes appeared to be associated with Cl- stored within the aquifer system and released in response to infiltration associated with the precipitation events. The continued use of road salts will continue to elevate the concentration of Cl- within the watershed. If the application of Cl- were to cease, the watershed would not fully recover within 50 years, and residual Cl- would remain in the system. A numerical modeling approach provided an initial evaluation, whereas incorporating transient flow revealed that areas around an urban setting were being impacted. More dilution occurred downstream because the waters discharging into downstream locations were agriculturally derived. Further, a comparison of the performance of a tripod-mounted large-scale particle image velocimeter (LSPIV) and an unmanned aerial system (UAS) LSPIV in relation to measurements of river discharge showed that results from the two methods were nearly identical. When the tripod was extended high enough to view the entire channel width, the camera would oscillate in the wind. Although the UAS was also not completely steady, after approximately 30, mean velocities were generally unaffected by camera movement. Even so, in many situations, the UAS was a more flexible option for obtaining the mean surface velocity and therefore the discharge. The UAS greatly increased the capability of obtaining LSPIV measurements over a large area, and mean flow velocities were relatively easy to obtain. Finally, the potential of floating gardens to improve the water quality of an urban stream, the Chicago River, was investigated. Results showed that concentrations of nitrate as nitrogen in water were lower after flowing past the floating garden. | C4: 2015IL298G; 2016IL313B; 2016IL314B; 2017IL332B; 2017IL333B; 2018IL340B; 2019IL092B; 2020IL103AIS | D4: Water Quality
A5: Impact 3 : Emerging Priorities | B5: The production of biofuels from contaminated soil and groundwater at the Crab Orchard National Wildlife Refuge, Illinois, was investigated. Grade A biosolids as a soil amendment provide nutrients to sunflowers (Helianthus annuus L.), were found to be better than low-nitrogen fertilizer in terms of plant growth, low concentrations of hexavalent chromium [Cr(VI)] were remediated, and biodiesel could be obtained from the seeds, making it a potential source of renewable fuel. Further, at the Energy Farm of the University of Illinois at Urbana-Champaign in a 97.5-meter-deep borehole, a thermal response test (TRT) and a distributed thermal response test (DTRT) were employed to analyze the homogeneous/heterogenous thermal properties, separately. The DTRT couples TRT with fiber-optic distributed temperature sensing (FO-DTS), allowing for analysis of the thermal properties along the subsurface layer by layer. Model simulations indicate the DTRT would improve the spatial resolution of thermal property prediction over the TRT, assuming the subsurface is a homogeneous solid. Application of this work to evaluate the working efficacy balance of the ground source heat pump is ongoing. Additionally, FO-DTS, installed vertically, was attached to PVC pipe in two adjacent boreholes (cased or sealed against the sidewall with bentonite grout). Thermal profiles were measured over a 2-year period (2015 – 2017). Heat transfer in the subsurface under both saturated and unsaturated conditions was numerically evaluated. This research shows how heterogeneities in the thermo-geology and well construction materials impact the natural geothermal gradient in the shallow subsurface. Finally, growth conditions of water-impermeable biological barriers using fungal mycelia were assessed in the presence of fly ash (known to inhibit fungal growth). Results showed that the fungi still produced massive mycelia and that when applied, they could effectively prevent water infiltration into the fly ash impoundment offering an innovative, sustainable, and cost-effective route to design and manage legacy sites. | C5: 2017IL329B; 2017IL337S; 2018IL341B; 2018IL342B-TRTDTRT; 2018IL342B-Rantoul; 2019IL090B; 2019IL091B; 2020IL214B; 2020IL217B | D5: Water Technology and Innovation

Sheet Project Overview
A1: Project Identifiers | C1: Project Information | I1: Funding | J1: Student Statistics (Please limit columns J-L to students supported using federal WRRA funds; please don't include students supported using matching funds. Please report students supported using matching funds in column M.) | O1: Science Characterization (Please help us characterize the studies both in terms of WRRI categories, but also those requested by Congress and other stakeholders.)
A2: Project ID | B2: Project Type (please include Admin as well as on-going individual research projects, 104g awards, and coordination agreements) | C2: Award Type | D2: Please indicate if an extension was granted for this project | E2: Project Title | F2: Project PI | G2: Academic Institution of PI | H2: Congressional District of project field site, or, if there is no field site, the congressional district where PI is located (please format as "[2-digit state abbreviation ]-[Congressional District]", e.g., "CO-1") | I2: Award Amount Allocated ($) this must be filled in for all lines | J2: Number of PhD Students Supported by WRRA $ | K2: Number of MS Students Supported by WRRA $ | L2: Number of Undergraduate Students Supported by WRRA $ | M2: Number of students supported by non-federal (matching) funds | N2: Diversity, Equity, Inclusion, Accessibility, & Justice (If the Institute collects information on number of students served, please include it. If the Institute does not collect that information, please respond "NA", not available. If these data are collected, but are unknown for this project, please respond "ND", not determined.) | O2: WRRI Science Priority that Best Aligns with this Project | P2: Water Resources Research Institute Region | Q2: USGS Cross-Discipline Landscapes (Primary) | R2: USGS Cross-Discipline Landscapes (Secondary, if applicable) | S2: Name of Geographic Study Area (if applicable) | T2: USGS Cross-Discipline Science Topic (Primary) | U2: USGS Cross-Discipline Science Topic (Secondary, if applicable) | V2: Keyword (Primary) | W2: Keyword (Secondary, if applicable) | X2: Keyword (Tertiary, if applicable) | Y2: Additional Keywords (if applicable; separate keywords with a comma)
A3: 2014IL292S | B3: Research | C3: Coordination Grant | D3: no | E3: Improving Morphodynamic Predictions in Rivers | F3: Gary Parker | G3: University of Illinois | H3: IL-015 | I3: 73030 | J3: ND | K3: ND | L3: ND | M3: ND | N3: NA | O3: Water Technology and Innovation | P3: Great Lakes | Q3: None of the Above | T3: Other | V3: MODELS | W3: GEOMORPOLOGICAL PROCESSES | X3: SOLUTE TRANSPORT
A4: 2015IL298G | B4: Research | C4: 104g - General | D4: no | E4: Using bioavailability to assess pyrethroid insecticide toxicity in urban sediments | F4: Michael Lydy, Amanda D Harwood, Kara Elizabeth Huff Hartz, Samuel A Nutile | G4: Southern Illinois University | H4: IL-012 | I4: 249329 | J4: 2 | K4: 2 | L4: 3 | M4: ND | N4: NA | O4: Water Quality | P4: Great Lakes | Q4: California Bay-Delta | R4: Great Lakes | T4: Natural Hazards | V4: MODELS | W4: SEDIMENTS | X4: TOXIC SUBSTANCES
A5: 2016IL311B | B5: Research | C5: Base Grant (104b) | D5: no | E5: Identifying wetland inundation extent and patterns in Illinois | F5: Michael W Eichholz | G5: Southern Illinois University | H5: IL-012 | I5: 1000 | J5: 1 | K5: 2 | L5: 5 | M5: ND | N5: NA | O5: Watershed and Ecosystem Function | P5: Great Lakes | Q5: None of the Above | T5: Natural Hazards | V5: WETLANDS | W5: FLOODS | X5: ECOLOGY
A6: 2016IL312B | B6: Research | C6: Base Grant (104b) | D6: no | E6: Under the Cover of Darkness: Nighttime water use by native, biofuel and agricultural crops of Illinois | F6: Max Benjamin Berkelhammer, Benjamin Alsip | G6: University of Illinois Chicago | H6: IL-007 | I6: 9853 | J6: 0 | K6: 1 | L6: 4 | M6: ND | N6: NA | O6: Water Scarcity and Availability | P6: Great Lakes | Q6: None of the Above | T6: Climate | V6: CLIMATOLOGICAL PROCESSES | W6: AGRICULTURE | X6: HYDROLOGY
A7: 2016IL313B | B7: Research | C7: Base Grant (104b) | D7: no | E7: Spatial and temporal modeling of road salts in a wateshed with mixed, urban and agricultural land use | F7: Eric Wade Peterson | G7: Illinois State University | H7: IL-103 | I7: 10000 | J7: 0 | K7: 2 | L7: 3 | M7: ND | N7: NA | O7: Water Quality | P7: Great Lakes | Q7: None of the Above | T7: Other | V7: NON POINT POLLUTION | W7: MODELS | X7: WATER QUALITY
A8: 2016IL314B | B8: Research | C8: Base Grant (104b) | D8: no | E8: Evaluating Water Quantity and Water Quality Issues in Illinois Streams Using Large-Scale Particle Image Velocimetry (LSPIV) | F8: Bruce L. Rhoads | G8: University of Illinois | H8: IL-015 | I8: 9915 | J8: 1 | K8: 0 | L8: 3 | M8: ND | N8: NA | O8: Water Quality | P8: Great Lakes | Q8: None of the Above | T8: Other | V8: HYDROLOGY | W8: SURFACE WATER | X8: WATER QUALITY
A9: 2016IL315B | B9: Outreach and Engagement | C9: Base Grant (104b) | D9: no | E9: Technology Transfer to the People of Illinois | F9: Lisa Merrifield | G9: University of Illinois | H9: IL-015 | I9: 46567 | J9: 0 | K9: 0 | L9: 0 | M9: ND | N9: NA | O9: Workforce Development and Water Literacy | P9: Great Lakes | Q9: None of the Above | T9: Other | V9: EDUCATION
A10: 2017IL329B | B10: Research | C10: Base Grant (104b) | D10: no | E10: Modeling the integration of green infrastructure into urban landscapes using a reliability-based framework | F10: Ashlynn S. Stillwell, Reshmina William | G10: University of Illinois | H10: IL-013 | I10: 10000 | J10: 1 | K10: 0 | L10: 0 | M10: 1 | N10: NA | O10: Water Policy, Planning, and Socioeconomics | P10: Great Lakes | Q10: None of the Above | T10: Other | V10: MANAGEMENT AND PLANNING | W10: CLIMATOLOGICAL PROCESSES | X10: FLOODS
A11: 2017IL330B | B11: Research | C11: Base Grant (104b) | D11: no | E11: Identifying nitrogen removal limitations in constructed wetlands treating agricultural tile drainage | F11: Karl John Rockne | G11: University of Illinois Chicago | H11: IL-016 | I11: 10000 | J11: 1 | K11: 0 | L11: 0 | M11: ND | N11: NA | O11: Watershed and Ecosystem Function | P11: Great Lakes | Q11: None of the Above | T11: Other | V11: AGRICULTURE | W11: NUTRIENTS | X11: WETLANDS
A12: 2017IL331B | B12: Research | C12: Base Grant (104b) | D12: no | E12: Evaluating the ability of wetland mitigation banks in the Chicago region to replace plant species lost to impacts to natural wetlands | F12: Jeffery Matthews | G12: University of Illinois | H12: IL-013 | I12: 4668 | J12: 0 | K12: 1 | L12: 0 | M12: ND | N12: NA | O12: Watershed and Ecosystem Function | P12: Great Lakes | Q12: None of the Above | T12: Water Challenges | V12: WETLANDS | W12: SURFACE WATER | X12: CONSERVATION
A13: 2017IL332B | B13: Research | C13: Base Grant (104b) | D13: no | E13: Impacts of stormwater-induced road salt runoff on soil and water quality in urban greenspaces | F13: Aaron Packman | G13: Northwestern University | H13: IL-009 | I13: 10000 | J13: 2 | K13: 1 | L13: 2 | M13: ND | N13: NA | O13: Water Quality | P13: Great Lakes | Q13: None of the Above | T13: Natural Hazards | V13: CLIMATOLOGICAL PROCESSES | W13: WATER QUALITY | X13: NON POINT POLLUTION
A14: 2017IL333B | B14: Research | C14: Base Grant (104b) | D14: no | E14: Diurnal and Seasonal Variation in Groundwater Nitrate-N Concentration in a Riparian Buffer Zone | F14: Eric Wade Peterson | G14: Illinois State University | H14: IL-105 | I14: 10000 | J14: 0 | K14: 1 | L14: 1 | M14: ND | N14: NA | O14: Water Quality | P14: Great Lakes | Q14: None of the Above | T14: Other | V14: AGRICULTURE | W14: NON POINT POLLUTION | X14: NUTRIENTS
A15: 2017IL337S | B15: Research | C15: Coordination Grant | D15: no | E15: Are Current Sediment Bioassays Being Biased by Collecting and Holding Time Procedures? | F15: Michael Lydy | G15: Southern Illinois University | H15: IL-012 | I15: 18915 | J15: 1 | K15: 0 | L15: 0 | M15: ND | N15: NA | O15: Water Technology and Innovation | P15: Great Lakes | Q15: None of the Above | T15: Other | V15: SEDIMENTS | W15: METHODS
A16: 2017IL334B | B16: Outreach and Engagement | C16: Base Grant (104b) | D16: no | E16: Transferring Water Resources Information to the People of Illinois | F16: Lisa Merrifield | G16: University of Illinois | H16: IL-013 | I16: 41608 | J16: 0 | K16: 0 | L16: 0 | M16: ND | N16: NA | O16: Workforce Development and Water Literacy | P16: Great Lakes | Q16: None of the Above | T16: Other | V16: EDUCATION
A17: 2018IL339B | B17: Research | C17: Base Grant (104b) | D17: yes | E17: Redefine Droughts in the U.S. Corn Belt: Stomatal conductance constraints attributable to atmospheric demand and/or soil water supply | F17: Kaiyu Guan, Hyungsuk Kim | G17: University of Illinois | H17: IL-013 | I17: 10000 | J17: 1 | K17: 0 | L17: 0 | M17: ND | N17: NA | O17: Water Scarcity and Availability | P17: Great Lakes | Q17: None of the Above | T17: Water Challenges | V17: AGRICULTURE | W17: DROUGHT | X17: WATER SUPPLY
A18: 2018IL340B | B18: Research | C18: Base Grant (104b) | D18: yes | E18: Characterization of harmful algal blooms using small unmanned aircraft systems and watershed analysis in southern Illinois | F18: Ruopu Li, Di Wu | G18: Southern Illinois University | H18: IL-012 | I18: 9982 | J18: 0 | K18: 0 | L18: 1 | M18: ND | N18: NA | O18: Water Quality | P18: Great Lakes | Q18: None of the Above | T18: HABs | V18: INVASIVE SPECIES | W18: MANAGEMENT AND PLANNING | X18: SURFACE WATER
A19: 2018IL341B | B19: Research | C19: Base Grant (104b) | D19: yes | E19: Groundwater phytoremediation and biofuels production for Crab Orchard Naional Wildlife Refuge | F19: Jia Liu, Md Hadiuzzaman | G19: Southern Illinois University | H19: IL-012 | I19: 9937 | J19: 1 | K19: 0 | L19: 0 | M19: ND | N19: NA | O19: Water Quality | P19: Great Lakes | Q19: None of the Above | T19: Energy | V19: GROUNDWATER | W19: AGRICULTURE | X19: TOXIC SUBSTANCES
A20: 2018IL338B | B20: Research | C20: Base Grant (104b) | D20: yes | E20: An experimental evaluation on the contribution of rain barrels to mosquito production | F20: Brian Allan, Allison Parker | G20: University of Illinois | H20: IL-013 | I20: 10000 | J20: 1 | K20: 0 | L20: 9 | M20: ND | N20: NA | O20: Workforce Development and Water Literacy | P20: Great Lakes | Q20: None of the Above | T20: Other | V20: WATER SUPPLY | W20: CONSERVATION
A21: 2018IL342B-Sangamon | B21: Research | C21: Base Grant (104b) | D21: yes | E21: Comprehensive multi-measurements of groundwater and surface water interaction survey in Sangamon River | F21: Yu-Feng Lin | G21: Univeristy of Illinois | H21: IL-013 | N21: NA | P21: Great Lakes
A22: 2018IL342B-TRTDTRT | B22: Research | C22: Base Grant (104b) | D22: yes | E22: TRT and DTRT in Energy Farm borehole site | F22: Yu-Feng Lin | G22: University of Illinois | H22: IL-013 | N22: NA | P22: Great Lakes
A23: 2018IL342B-Rantoul | B23: Research | C23: Base Grant (104b) | D23: yes | E23: Modeling Effects of Thermo-geology on Boreholes and on the Shallow Geothermal Gradient using Distributed Temperature Sensing in Rantoul, Illinois | F23: Yu-Feng Lin | G23: University of Illinois | H23: IL-013 | N23: NA | P23: Great Lakes
A24: 2019IL089B | B24: Research | C24: Base Grant (104b) | D24: yes | E24: Estimating Residential Hot Water Use from Smart Electricity Data | F24: Ashlynn S. Stillwell | G24: University of Illinois | H24: IL-013 | I24: 10000 | J24: 0 | K24: 1 | L24: 0 | M24: ND | N24: NA | O24: Water Technology and Innovation | P24: Great Lakes | Q24: None of the Above | T24: Energy | V24: WATER SUPPLY | W24: MANAGEMENT AND PLANNING
A25: 2019IL090B | B25: Research | C25: Base Grant (104b) | D25: yes | E25: Electrochemically-mediated Adsorption Systems for Selective Nitrate Recovery: Agriculture and the Water-energy Nexus | F25: Xiao Su | G25: University of Illinois | H25: IL-013 | I25: 10000 | J25: 1 | K25: 0 | L25: 0 | M25: ND | N25: NA | O25: Water Technology and Innovation | P25: Great Lakes | Q25: None of the Above | T25: Energy | V25: AGRICULTURE | W25: TREATMENT | X25: NUTRIENTS
A26: 2019IL091B | B26: Research | C26: Base Grant (104b) | D26: yes | E26: Improving Denitrifying Woodchip Bioreactor Design and Management through Denitrification Potential Testing | F26: Laura Christianson | G26: University of Illinois | H26: IL-013 | I26: 9968 | J26: 2 | K26: 0 | L26: 0 | M26: ND | N26: NA | O26: Water Technology and Innovation | P26: Great Lakes | Q26: None of the Above | T26: Energy | V26: AGRICULTURE | W26: NUTRIENTS
A27: 2019IL092B | B27: Research | C27: Base Grant (104b) | D27: yes | E27: Assessment of Floating Gardens to Improve the Water Quality of the Chicago River | F27: Eric Wade Peterson | G27: Illinois State University | H27: IL-013 | I27: 9998 | J27: 0 | K27: 2 | L27: 0 | M27: ND | N27: NA | O27: Water Quality | P27: Great Lakes | Q27: None of the Above | T27: Water Challenges | V27: NITRATE CONTAMINATION | W27: METHODS | X27: SURFACE WATER
A28: 2020IL216B | B28: Research | C28: Base Grant (104b) | D28: yes | E28: A Coupled Urban Spatial Simulation and Stormwater Runoff Model and Its Implications for Physrical Design: The Case of Chicago | F28: Brian Deal | G28: University of Illinois | H28: IL-013 | I28: 10000 | J28: 1 | K28: 0 | L28: 0 | M28: ND | N28: NA | O28: Water Policy, Planning, and Socioeconomics | P28: Great Lakes | Q28: None of the Above | T28: Natural Hazards | V28: CLIMATOLOGICAL PROCESSES | W28: MODELS | X28: HYDROLOGY
A29: 2020IL212B | B29: Research | C29: Base Grant (104b) | E29: Illinois Water Resources Center Research for Future Generations | F29: Maryam Ghadiri | G29: University of Illinois | H29: IL-013 | N29: NA | O29: Water Technology and Innovation | P29: Great Lakes | V29: HYDROLOGY | W29: SURFACE WATER | X29: GROUNDWATER
A30: 2020IL214B | B30: Research | C30: Base Grant (104b) | D30: yes | E30: Low Cost Mycelial Stabilization of Coal Combustion Products to Reduce as, and Contamination of Groundwater | F30: Linduo Zhao | G30: University of Illinois | H30: IL-013 | I30: 9988 | J30: 0 | K30: 0 | L30: 2 | M30: ND | N30: NA | O30: Water Technology and Innovation | P30: Great Lakes | Q30: None of the Above | T30: Energy | V30: GROUNDWATER | W30: WATER QUALITY
A31: 2020IL217B | B31: Research | C31: Base Grant (104b) | D31: yes | E31: Modeling the Effects of Green Stormwater Infrastructure Implementation on Urban Hydrology and Urban Heat Islands in Illinois | F31: Lei Zhao | G31: University of Illinois | H31: IL-013 | I31: 10000 | J31: 0 | K31: 1 | L31: 0 | M31: ND | N31: NA | O31: Water Technology and Innovation | P31: Great Lakes | Q31: None of the Above | T31: Water Challenges | V31: CLIMATOLOGICAL PROCESSES | W31: HYDROLOGY | X31: FLOODS
A32: 2020IL215B | B32: Research | C32: Base Grant (104b) | D32: yes | E32: Towards Better Agricultural Drought Assessment and Irrigation Management: Improving the Simulation and Understanding of Plant Water Stress for Crops in Noah-MP Surface Model | F32: Kaiyu Guan | G32: University of Illinois | H32: IL-013 | I32: 10000 | J32: 1 | K32: 0 | L32: 0 | M32: ND | N32: NA | O32: Water Scarcity and Availability | P32: Great Lakes | Q32: None of the Above | T32: Water Challenges | V32: CLIMATOLOGICAL PROCESSES | W32: AGRICULTURE | X32: MODELS
A33: 2020IL218B | B33: Research | C33: Base Grant (104b) | D33: yes | E33: Utilizing a Tracer Test to Calculate the Transport and Fate of Nitrate Withing a Saturated Budder Zone | F33: Eric Wade Peterson | G33: Illinois State University | H33: IL-013 | I33: 9887 | J33: 1 | K33: 0 | L33: 0 | M33: ND | N33: NA | O33: Water Quality | P33: Great Lakes | Q33: None of the Above | T33: Water Challenges | V33: WATER QUALITY | W33: NITRATE CONTAMINATION | X33: GROUNDWATER
A34: 2020IL103AIS | B34: Research | C34: 104g - AIS | D34: no | E34: Water Quality as a Detterent to the Movement of Invasive Fishes in the Illinois Waterway: Implications for the Upper Mississippi Basin | F34: Cory Suski | G34: University of Illinois | H34: IL-013 | I34: 240624 | N34: NA | P34: Great Lakes

Sheet Project Summaries
A1: Project ID (auto-populated form the "Project Overview" tab) | B1: Project Summary and/or Impact (There should be a project summary and/or impact for each project, note that this tab replaces the fillable "Project Details" PDF from previous years. Please use plain language [no technical terms], no acronyms, and limit to approximately 250 words. We recommend using this web app to evaluate the technical level of your text: https://hemingwayapp.com/, with a target of 5-6th grade level.)
A2: =IF(('Project Overview'!A3) <> 0, 'Project Overview'!A3, "") -> 2014IL292S | B2: In this paper we present numerical simulations of large-scale tracer particle advection-dispersion in alluvial rivers. We specifically focus on conditions for which bedload is the dominant mode of sediment transport, and for which the river is subject to the formation of free, migrating alternate bars. We apply two formulations of the Exner equation of sediment conservation; a standard flux form, in which bed elevation change is related to the divergence of the vector of sediment transport rate, and a stochastic entrainment form, in which bed elevation change is related to the net entrainment rate of particles into bedload. In modeling tracer advection-dispersion, we use a single grain size, as well as an active layer formulation in which active layer thickness scales with grain size. We specifically consider conditions so that no be aggradation or degradation occurs when averaged over the bars. We find that the presence of bars has a dramatic effect on streamwise advection-dispersion of tracer particles. When the flux form of Exner equation is used for the case of a flat bed (no bars), tracer particles advect without dispersing. When the entrainment formulation is applied to the same condition, the particles also disperse, in response to the stochasticity associated with the PDF of particle step length. The effect of bars is to substantially increase the streamwise dispersion rate. The statistics of the pattern of advection-dispersion seen in the presence of bars are to a large degree independent of whether the flux or entrainment forms of Exner equation are used, indicating that dispersion is dominated by the bars themselves. The simulated asymptotic pattern of streamwise tracer advection-dispersion under the influence of free bars is either normal or weakly superdiffusive. The numerical model self-generates stochasticity in bar properties, including wavelength, wave height, and celerity. This in turn imparts a randomness to tracer behavior, resulting in large-scale dispersion. More specifically, the randomness of the alternate bar dimensions renders local bed surface elevation a stochastic quantity. In some cases, the probability distribution of trough elevation is such that it results in a heavy-tailed waiting time distribution; a deeply-buried particle must wait an anomalously long time before it is re-entrained. Migrating bars strongly constrain the length-scale of tracer transport, likely causing a thin-tailed distribution of travel distance. The combination of thin-tailed travel distance and heavy-tailed waiting time may be the cause of the simulated superdiffusive dispersion when it occurs. The morphological evolution of bed surface we consider in the simulation is that of alternate bars only, in the absence of bed aggradation or degradation when averaged over the bars. However, the coexistence of several static and dynamic morphological elements might make the waiting time distribution more complex, perhaps causing other dispersion behavior (e.g., subdiffusive dispersion) and perhaps affecting advection (e.g., advective slowdown), which are not illustrated in this paper. The effects of different bed morphologies (e.g., multiple-row bars, braiding and 3D dunes) and channel planform (e.g., meandering, systematic width variation, and interacting channel and floodplain) on tracer advection-dispersion invite further investigation. In addition, model extensions including e.g. sediment size mixtures, and also describing the bed in terms of a continuous vertical structure rather than the active layer formulation so as to better simulate vertical mixing of tracers in the bed [e.g. Pelosi et al., 2014, 2016], are future challenges in the pursuit of a comprehensive understanding of bedload tracer advection-dispersion in nature. This study contributes to a better understanding of tracer advection-dispersion in the global regime [Nikora et al., 2002].
A3: =IF(('Project Overview'!A4) <> 0, 'Project Overview'!A4, "") -> 2015IL298G | B3: Pyrethroid insecticides were detected in 76% of the total, and 67% of the bioaccessible sites (n=49). Total average sum of pyrethroids was 259 ng/g organic carbon and 43.9 ng/g of bioaccessible pyrethroids. Bifenthrin was the most commonly detected pyrethroid. Only 28% and 15% of sediments caused a decrease in H. azteca biomass and survival. Using a temperature-based focused toxicity identification evaluation, confirmed that pyrethroids were a causual factor in the toxicity of 10 of the 12 sediments tested. Prevalence of bioaccessible and total pyrethroids detected in urban streambed sediments indicating that more cost-effective Tenax extraction methods can be used to survey pyrethroids. While a significant relationship existed between Tenax concentrations and toxicity, this relationship was complicated by several factors, including the paucity of toxicological parameters, uncertainties in standard bioassays, and more contaminants present in sediment, which all point to the need for more bioavailability-based studies. Pyrethroid-resistant H. azteca were not found, but, other amphipods present in the pyrethroud-contaminated urban stream were more tolerant to permethrin exposure than non-resistant H. azteca. Bioaccessible and bioaccumulated polychlorinated biphenyl (PCB) concentrations did not change significantly during the holding time, however, the bioaccessible pyrethroid concentrations were more varied, suggesting that holding time of the sediments prior to bioassay can potentially bias the bioassay tests.
A4: =IF(('Project Overview'!A5) <> 0, 'Project Overview'!A5, "") -> 2016IL311B | B4: Approximately 90 sites (~25 ha each) were sampled in 2015, and another 110 were sampled in 2016. Our recently completed spring 2017 samples covered 110 sites, and a similar number will be expected for repeat surveys in spring and autumn of this year. We are continuing to digitize the survey data into a GIS for analysis once field survey is completed. The first 50 free images have been downloaded from JAXA, spanning multiple seasons and years from 2014- 2016. We will acquire additional images for that period and will also obtain images for 2017 with our remaining allotment of 100 images. The multi-season, multi-year dataset will allow analyses of patterns of wetland inundation in Illinois during that period.
A5: =IF(('Project Overview'!A6) <> 0, 'Project Overview'!A6, "") -> 2016IL312B | B5: This contributed to a growing body of data on how carbonyl sulfide can be used as a proxy for plant photosynthesis and stomatal conductance (both night and day). We show very strong evidence that the carbonyl sulfide fluxes at this site track the seasonal and daily variability in photosynthesis and this is strongly controlled by soil moisture and relative humidity. This is one of the first comprehensive analyses of the nocturnal fluxes to be used in land surface models to place more realistic constraints on the processes controlling nighttime stomatal conductance. We provide a first high resolution analysis of carbon monoxide in the Chicago suburbs and show the strong effect that weekday traffic has on carbon monoxide concentrations.
A6: =IF(('Project Overview'!A7) <> 0, 'Project Overview'!A7, "") -> 2016IL313B | B6: Outcomes from these activities present spatial and temporal data for Cl - within a watershed impacted by deicing agents. Results identify seasonal trends in the concentration of Cl - in the LKC watershed, with elevated concentrations in the winter. However, periodic spikes during the summer follow precipitation events. The spikes appear to be associated with Cl - stored within the aquifer system that is released in response to infiltration associated with the precipitation events. The continued use of roads salts will continue to elevate the concentration of Cl - with in the waters. If the application of Cl - ceased, the watershed would not fully recover within 50 years. Residual Cl - would remain in the system. The numerical modeling approach provides an initial evaluation; additional modeling incorporating transient flow will be needed to support all future research activities and develop appropriate BMPs for Cl - applications. The Illinois State Geological Survey and the Illinois State Water Survey have examined the issue of road salts in the Chicago metropolitan area and the subsequent effects on the Illinois River watershed. A pilot GIS model developed to evaluate the transport and fate of Cl - within Illinois indicated that data are spatially and temporally too variable to accurately assess the problem. Our data suggest a balance between spatial resolution and temporal resolution exists. While our sampling points were closer together, the 2-week time period was to coarse to model accurately the pulse of Cl- moving through the system. A finer temporal resolution is needed to develop more adequate GIS and flow models. Increases in road salts use, leading to increases in stream/groundwater chloride concentrations, are fueling the need for useful tools to study chloride fate and transport. Linear regression modeling has been used many times to predict the movement of a contaminant and is used here to predict chloride concentrations downstream. Land cover, representing impervious surfaces, drainage area, and discharge are all controlling factors in chloride concentration downstream, however there must be other factors controlling chloride concentration other than the ones viewed in this study. This study also revealed that there is an impacted area around an urban setting. Chloride concentrations are less diluted upstream due to the chlorides stored and discharging into the upstream sites. More dilution occurs downstream due to the waters discharging into downstream locations are agriculturally derived.
A7: =IF(('Project Overview'!A8) <> 0, 'Project Overview'!A8, "") -> 2016IL314B | B7: First, in relation to measurements of river discharge, the performance of the tripod-mounted LSPIV and the UAS LSPIV was nearly identical in each case where both methods were used. We found that when the tripod is extended high enough to view the entire channel width, the camera oscillates in the wind. The UAS is also not completely steady, but after about 30 seconds (depending on wind speed and height above the water surface), mean velocities are generally unaffected by camera movement. While in certain situations, such as in narrow, tree-lined rivers, in restricted flight zones, or when nocertified UAS operator is present, it may be beneficial to use a tripod-mounted camera, in many situations the UAS is a more flexible option for obtaining mean surface velocity and therefore discharge. The UAS can more easily image wide rivers and the field of view can be adjusted on the fly in response to changing conditions. In addition, LSPIV discharge from both the tripod and UAS compared favorably with thepropeller and ADCP discharge and were often within a few percent of these reference values. Ourresults generally support the typical practice of relating depth-averaged velocity to surface velocity witha simple coefficient in the range of 0.85 – 0.9, but additional research into this is ongoing. Finally, wefound that in some low and high flow conditions, the LSPIV discharge was close to the referencedischarges measured by the research team but significantly (>25 %) different than the USGS gage.Overall, both the tripod and UAS methods resulted in rapid, accurate discharge calculations with respectto reference methods.Second, we found that LSPIV is an important complement to traditional velocity measurementsand can enrich our understanding of flow in complex hydrodynamic environments like confluences. Notonly can LSPIV be used for qualitative flow visualization, useful for comparison among field sites and flow events and with numerical modeling, but quantitative information can be obtained over a largespatial scale. UAS greatly increases the capability to obtain LSPIV over a large area, and mean flowvelocities are relatively easy to obtain. It is generally more difficult to obtain quasi-instantaneous flow“snapshots”, especially as camera height above the water and magnitude of cameramovement/oscillation increases. Under favorable circumstances, however, flow snapshots can beobtained from both tripod mounted and UAS LSPIV.
A8: =IF(('Project Overview'!A9) <> 0, 'Project Overview'!A9, "") -> 2016IL315B | B8: The Illinois Water Resources Center staff played a key role in writing, developing, filming,producing, and promoting a video series, “Planting for Pollinators” from inception tocompletion. The Planting for Pollinators series is a video series that contains seven shortepisodes that covers the basics of planting a pollinator friendly garden that is alsoenvironmentally friendly and promotes healthy water quality of the local rivers, lakes, andstreams.The IWRC staff coordinated and facilitated 30 meetings for the Illinois Nutrient Loss ReductionStrategy and was key in managing the various working groupsand gave a presentation on the Nutrient Loss Reduction Strategy at the Illinois StateFair.IWRC planned, facilitated, coordinated, and provided logistical support for the bi-annual IllinoisWater Conference in Urbana, IL.IWRC provided multimedia content for the Private Well Class, a flagship national 10-week educational email course for private well owners. Content provided includes the PrivateWell Podcast, well care videos, live webinars once a month with Q & A that feature a variety oftopics, social media via Facebook and Twitter, and other resources.IWRC staff from the Private Well Class presented 4-hour Environmental Health ProfessionalWorkshop trainings for Continuing Education Credits in Oregon, Virginia, Massachusetts,Connecticut, Illinois, Tennessee, and online (3). IWRC participates in multiple awareness weeks – including Groundwater Awareness Week,National Drinking Water Week, and more. We host a yearly Pledge to Test campaign where wellowners pledge to test their well water and one is randomly selected to receive the cost of wellwater testing paid for, up to $200.
A9: =IF(('Project Overview'!A10) <> 0, 'Project Overview'!A10, "") -> 2017IL329B | B9: Probabilistic approaches are needed to quantify and account for uncertainties in green infrastructure performance. One approach to quantifying performance reliability is through the use of fragility functions. Fragility is defined as the conditional probability of attaining or exceeding a specified standard of performance conditioned on different demand variables (i.e., loading intensity measures). Originally developed in the field of earthquake engineering, fragility functions have been used in multiple other applications, including flood control. This study developed a methodology to generate fragility curves for green stormwater infrastructure (GSI) to study the reliability of a green roof under different storm conditions. While the methodology was illustrated using a green roof case study, it is flexible enough to be extended to many other failure modes and types of green infrastructure.
A10: =IF(('Project Overview'!A11) <> 0, 'Project Overview'!A11, "") -> 2017IL330B | B10: - Denitrification-mediated nitrogen (N) removal has occurred at a limited rate in constructed wetland 1 (CW1) located in Bureau County, Illinois. - Sediment organic matter (OM) concentrations increased greatly within CW1 from nearest the inlet and decreasing to the wetland outlet during 2016 and 2017, while nitrate decreased from the inlet to the outlet at the same locations. - The outlet half of the wetland consistently had higher concentrations and more labile OM with a higher abundancy of known denitrifying bacteria that resulted in higher removal efficiency as captured tile drainage moved through the wetland towards the outlet.
A11: =IF(('Project Overview'!A12) <> 0, 'Project Overview'!A12, "") -> 2017IL331B | B11: - Of the native plant species affected by permitted impacts (developments), fewer than half are replaced in wetland mitigation banks. - Suggests that policies requiring greater equivalence between the wetland habitat types produced in banks and those present in impacted natural wetlands prioritize the replacement of the specific wetland resources lost.
A12: =IF(('Project Overview'!A13) <> 0, 'Project Overview'!A13, "") -> 2017IL332B | B12: This work constitutes a resource for TNC in managing GMP and the other prairies in the Indian Boundary Prairies to preserve biodiversity and maintain valuable ecosystem services. Continuing work at Gensburg Markham Prairie includes sampling of surface soils from the bottom of ditches during the dry season to evaluate deposition of metals and road salt constituents from water that infiltrates into the subsurface. Additional methods of estimating soil EC are also being explored to permit separation of intrinsic soil properties from anthropogenic effects on EC. As part of an ongoing partnership with Argonne National Laboratory, we are working to integrate the EC sensors installed as part of this research with larger-scale environmental sensing infrastructure via the Waggle platform (Beckman et al., 2016). This integration will permit open data dissemination in real time, allowing these measurements to inform site management decisions and be available to the public to facilitate discussion of alternative deicing strategies.
A13: =IF(('Project Overview'!A14) <> 0, 'Project Overview'!A14, "") -> 2017IL333B | B13: The most notable observations in this study are the 24-hour time series vegetation uptake and multi-process increase signals. Time of maximum and minimum NO3- -N concentration data indicate vegetation uptake generates the sinusoidal trend. Time of maximum and minimum NO 3- -N concentration occurs when it would be expected for a photosynthetically controlled process. Maximum NO3- -N concentration occurs during the dark period, while minimum NO3- -N concentration occurs at the end of the photoperiod. Vegetation uptake is observed under conditions where vegetation growth is possible and sufficiently isolated from competing processes by environmental conditions. The alternate explanation for the sinusoidal trend, denitrification, is not supported by these data. If denitrification were the process responsible for the time of maximum and time of minimum NO3- -N concentration, then the denitrification rate would need to change and would have to be driven by water temperature changes. No relationship exists between 24-hour water temperature difference and NO3--N concentration difference. Additionally, these data indicate multiple processes are responsible for the increase trend. Anoxic conditions in the saturated zone coupled with water column height drops from ET provide ideal conditions for conversion of accumulated NH4+ to NO3- in the unsaturated zone. NO3- produced by nitrification in the unsaturated zone was then transported to the saturated zone by unsaturated flow. NO3- transport from the upgradiant agricultural land use are best accounts for increases during the winter. As an area that is intensively farmed, Illinois fields receive a large amount of NO3- fertilizer yearly. Tile drains make many forms of NO3- management ineffective, exporting NO3- through soil into streams, bypassing riparian zones and making best management practices such as riparian buffers less effective. The results of this study reinforce the importance of vegetation NO3- uptake. The results presented here provide evidence for a measurable contribution of NO3- removal by vegetation. Seasons that have a significantly different μ daily [NO3--N] do not have a significantly different μdifference [NO3--N]. This means the amount of NO3- available does not influence the magnitude of change over 24-hours. If implemented, conservation practices that intercept and increase residence times of water will reduce NO3- loads. Future research could focus on quantification of total nitrogen captured by vegetation, NO3- flux in the unsaturated zone, and stable isotope methods for NO3- source and fate. This study focused on NO3- -N in the saturated zone, but other forms of nitrogen such as ammonium and nitrite in the unsaturated zone may be of interest.
... A33: =IF(('Project Overview'!A34) <> 0, 'Project Overview'!A34, "") -> 2020IL103AIS | B33: No project updates as the project didn't commence until September 1, 2021.
A34: =IF(('Project Overview'!A35) <> 0, 'Project Overview'!A35, "")
A35: =IF(('Project Overview'!A36) <> 0, 'Project Overview'!A36, "")
A36: =IF(('Project Overview'!A37) <> 0, 'Project Overview'!A37, "")
A37: =IF(('Project Overview'!A38) <> 0, 'Project Overview'!A38, "")
A38: =IF(('Project Overview'!A39) <> 0, 'Project Overview'!A39, "")
A39: =IF(('Project Overview'!A40) <> 0, 'Project Overview'!A40, "")
A40: =IF(('Project Overview'!A41) <> 0, 'Project Overview'!A41, "")
A41: =IF(('Project Overview'!A42) <> 0, 'Project Overview'!A42, "")
A42: =IF(('Project Overview'!A43) <> 0, 'Project Overview'!A43, "")
A43: =IF(('Project Overview'!A44) <> 0, 'Project Overview'!A44, "")
A44: =IF(('Project Overview'!A45) <> 0, 'Project Overview'!A45, "")
A45: =IF(('Project Overview'!A46) <> 0, 'Project Overview'!A46, "")
... A98: =IF(('Project Overview'!A99) <> 0, 'Project Overview'!A99, "")
A99: =IF(('Project Overview'!A102) <> 0, 'Project Overview'!A102, "")
A100: =IF(('Project Overview'!A103) <> 0, 'Project Overview'!A103, "")
A101: =IF(('Project Overview'!A104) <> 0, 'Project Overview'!A104, "")
A102: =IF(('Project Overview'!A105) <> 0, 'Project Overview'!A105, "")
A103: =IF(('Project Overview'!A106) <> 0, 'Project Overview'!A106, "")
A104: =IF(('Project Overview'!A107) <> 0, 'Project Overview'!A107, "")
A105: =IF(('Project Overview'!A108) <> 0, 'Project Overview'!A108, "")
A106: =IF(('Project Overview'!A109) <> 0, 'Project Overview'!A109, "")
A107: =IF(('Project Overview'!A110) <> 0, 'Project Overview'!A110, "")
A108: =IF(('Project Overview'!A111) <> 0, 'Project Overview'!A111, "")
A109: =IF(('Project Overview'!A112) <> 0, 'Project Overview'!A112, "")
A110: =IF(('Project Overview'!A113) <> 0, 'Project Overview'!A113, "")
... A232: =IF(('Project Overview'!A235) <> 0, 'Project Overview'!A235, "")

Sheet Equipment
A1: Project ID | B1: Award Type | C1: Description of Equipment (type and model) | D1: Cost of Equipment (>$5000 only) | E1: Number of students per year that use this equipment | F1: Additional Comments
A2: =IF(('Project Overview'!A3) <> 0, 'Project Overview'!A3, "") -> 2014IL292S | C2: 0
A3: =IF(('Project Overview'!A4) <> 0, 'Project Overview'!A4, "") -> 2015IL298G | C3: 0
A4: =IF(('Project Overview'!A5) <> 0, 'Project Overview'!A5, "") -> 2016IL311B | C4: 0
A5: =IF(('Project Overview'!A6) <> 0, 'Project Overview'!A6, "") -> 2016IL312B | C5: 0
A6: =IF(('Project Overview'!A7) <> 0, 'Project Overview'!A7, "") -> 2016IL313B | C6: 0
A7: =IF(('Project Overview'!A8) <> 0, 'Project Overview'!A8, "") -> 2016IL314B | C7: 0
A8: =IF(('Project Overview'!A9) <> 0, 'Project Overview'!A9, "") -> 2016IL315B | C8: 0
A9: =IF(('Project Overview'!A10) <> 0, 'Project Overview'!A10, "") -> 2017IL329B | C9: 0
A10: =IF(('Project Overview'!A11) <> 0, 'Project Overview'!A11, "") -> 2017IL330B | C10: 0
A11: =IF(('Project Overview'!A12) <> 0, 'Project Overview'!A12, "") -> 2017IL331B | C11: 0
A12: =IF(('Project Overview'!A13) <> 0, 'Project Overview'!A13, "") -> 2017IL332B | C12: 0
A13: =IF(('Project Overview'!A14) <> 0, 'Project Overview'!A14, "") -> 2017IL333B | C13: 0
... A32: =IF(('Project Overview'!A33) <> 0, 'Project Overview'!A33, "") -> 2020IL218B | C32: 0
A33: =IF(('Project Overview'!A34) <> 0, 'Project Overview'!A34, "") -> 2020IL103AIS | C33: Small shuttle box - a two chambered tank, connected by a narrow opening; fish can swim freely between the two chambers, but very little mixing occurs between the two chambers | D33: 16000 | E33: NA

Sheet doi_Products_ONLY
A1: Project ID | B1: Product Type (Journal article, report, dataset, with Digital Object Identifier) | C1: Product Citation (Indicate Digital Object Identifier and publication year in appropriate adjoining columns. If none available, go to "Other Products" Tab, and list product type and stage of completion. Provide further details about the doi product in the Additional Comments column. This list may include citations for projects from this 5-year period and one previous year, so long as the citation was not already included in previous year's report) | D1: Digital Object Identifier (DOI) | E1: Year of Publication | F1: How many USGS staff were co-authors of this product? | G1: How many students were co-authors of this product? | H1: Additional Comments (if publication was associated with a series of awards, please only report it once, but include other relevant award IDs here)
A2: 2016IL313B | B2: Journal Article | C2: Chabela, L. P., & Peterson, E. W. (2019). Relationship between Peak Stage, Storm Duration, and Bank Storage along a Meandering Stream. Water, 11(8). | D2: https://doi.org/10.3390/w11081688 | E2: 2019 | F2: 0 | G2: 1
A3: 2016IL314B | B3: Journal Article | C3: Lewis, Q. W., Lindroth, E. M., & Rhoads, B. L. (2018). Integrating unmanned aerial systems and LSPIV for rapid, cost-effective stream gauging. JOURNAL OF HYDROLOGY, 560, 230-246. | D3: https://doi.org/10.1016/j.jhydrol.2018.03.008 | E3: 2018 | F3: 0 | G3: 2
A4: 2016IL314B | B4: Journal Article | C4: Lewis, Q. W., & Rhoads, B. L. (2018a). LSPIV Measurements of Two-Dimensional Flow Structure in Streams Using Small Unmanned Aerial Systems: 1. Accuracy Assessment Based on Comparison With Stationary Camera Platforms and In-Stream Velocity Measurements. WATER RESOURCES RESEARCH, 54(10), 8000-8018. | D4: https://doi.org/10.1029/2018WR022550 | E4: 2018 | F4: 0 | G4: 1
A5: 2016IL312B | B5: Journal Article | C5: Berkelhammer, M., Alsip, B., Matamala, R., Cook, D., Whelan, M. E., Joo, E., Bernacchi, C., Miller, J., & Meyers, T. (2020). Seasonal Evolution of Canopy Stomatal Conductance for a Prairie and Maize Field in the Midwestern United States from Continuous Carbonyl Sulfide Fluxes. Geophysical Research Letters, 47(6). | D5: https://doi.org/10.1029/2019gl085652 | E5: 2020 | F5: 0 | G5: 1
A6: 2019IL090B | B6: Journal Article | C6: Candeago, R., Kim, K., Vapnik, H., Cotty, S., Aubin, M., Berensmeier, S., Kushima, A., & Su, X. (2020). Semiconducting Polymer Interfaces for Electrochemically Assisted Mercury Remediation. ACS APPLIED MATERIALS & INTERFACES, 12(44), 49713-49722. | D6: https://doi.org/10.1021/acsami.0c15570 | E6: 2020 | F6: 0 | G6: 3
A7: 2015IL293B | B7: Journal Article | C7: Favata, C. A., Maia, A., Pant, M., Nepal, V., & Colombo, R. E. (2018). Fish assemblage change following the structural restoration of a degraded stream. RIVER RESEARCH AND APPLICATIONS, 34(8), 927-936. | D7: https://doi.org/10.1002/rra.3336 | E7: 2018 | F7: 0 | G7: 2
A8: 2017IL332B | B8: Journal Article | C8: Gonzalez, L. M. H., Rivera, V. A., Phillips, C. B., Haug, L. A., Hatch, S. L., Yeager, L. E., Chang, H. B., Alvarez, J., Gnaedinger, K. J., Miller, W. M., & Packman, A. I. (2019). Characterization of soil profiles and elemental concentrations reveals deposition of heavy metals and phosphorus in a Chicago-area nature preserve, Gensburg Markham Prairie. JOURNAL OF SOILS AND SEDIMENTS, 19(11), 3817-3831. | D8: https://doi.org/10.1007/s11368-019-02315-5 | E8: 2019 | F8: 0 | G8: 2
A9: 2017IL332B | B9: Journal Article | C9: Griffin, J. S., Haug, L. A., Rivera, V. A., Gonzalez, L. M. H., Kelly, J. J., Miller, W. M., Wells, G. F., & Packman, A. I. (2020). Soil hydrology drives ecological niche differentiation in a native prairie microbiome. FEMS MICROBIOLOGY ECOLOGY, 96(1), Article fiz163. | D9: https://doi.org/10.1093/femsec/fiz163 | E9: 2020 | F9: 0 | G9: 2
A10: 2017IL332B | B10: Journal Article | C10: Hernandez Gonzalez, L. M., Rivera, V. A., Phillips, C. B., Haug, L. A., Hatch, S. L., Yeager, L. E., Chang, H., Alvarez, J., Gnaedinger, K. J., Miller, W. M., & Packman, A. I. (2019). Characterization of soil profiles and elemental concentrations reveals deposition of heavy metals and phosphorus in a Chicago-area nature preserve, Gensburg Markham Prairie. JOURNAL OF SOILS AND SEDIMENTS, 19(11), 3817-3831. | D10: https://doi.org/10.1007/s11368-019-02315-5 | E10: 2019 | F10: 0 | G10: 2
A11: 2019IL090B | B11: Journal Article | C11: Kim, K., Medina, P. B., Elbert, J., Kayiwa, E., Cusick, R. D., Men, Y. J., & Su, X. (2020). Molecular Tuning of Redox-Copolymers for Selective Electrochemical Remediation. ADVANCED FUNCTIONAL MATERIALS, 30(52), Article 2004635. | D11: https://doi.org/10.1002/adfm.202004635 | E11: 2020 | F11: 0 | G11: 1
A12: 2018IL339B | B12: Journal Article | C12: Kimm, H., Guan, K. Y., Gentine, P., Wu, J., Bernacchi, C. J., Sulman, B. N., Griffis, T. J., & Lin, C. J. (2020). Redefining droughts for the US Corn Belt: The dominant role of atmospheric vapor pressure deficit over soil moisture in regulating stomatal behavior of Maize and Soybean. AGRICULTURAL AND FOREST METEOROLOGY, 287, Article 107930. | D12: https://doi.org/10.1016/j.agrformet.2020.107930 | E12: 2020 | F12: 0 | G12: 1
A13: 2016IL314B | B13: Journal Article | C13: Lewis, Q., Rhoads, B., Sukhodolov, A., & Constantinescu, G. (2020). Advective Lateral Transport of Streamwise Momentum Governs Mixing at Small River Confluences. WATER RESOURCES RESEARCH, 56(9), Article e2019WR026817. | D13: https://doi.org/10.1029/2019WR026817 | E13: 2020 | F13: 0 | G13: 1
... A16: 2015IL293B | B16: Journal Article | C16: Smith, S. C. F., Colombo, R. E., Thomas, T., & Keeney, D. B. (2019). Dissimilar effects of low-head dams on the genetic structure of riverine fishes. FRESHWATER SCIENCE, 38(1), 92-102. | D16: https://doi.org/10.1086/701598 | E16: 2019 | F16: 0 | G16: 0
A17: 2014IA252B | B17: Journal Article | C17: Vanloocke, A., Twine, T. E., Kucharik, C. J., & Bernacchi, C. J. (2017). Assessing the potential to decrease the Gulf of Mexico hypoxic zone with Midwest US perennial cellulosic feedstock production. GLOBAL CHANGE BIOLOGY BIOENERGY, 9(5), 858-875. | D17: https://doi.org/10.1111/gcbb.12385 | E17: 2017 | F17: NA | G17: NA
A18: 2011IL222B | B18: Journal Article | C18: Waterman, D. M., & Garcia, M. H. (2019). Nonlinear Bedload Transport Trajectory Angle Expressed in a Traditional Form: Derivation and Application. JOURNAL OF HYDRAULIC ENGINEERING, 145(8), Article 04019028. | D18: https://doi.org/10.1061/(ASCE)HY.1943-7900.0001619 | E18: 2019 | F18: 0 | G18: 1
A19: 2017IL329B | B19: Journal Article | C19: William, R., Gardoni, P., & Stillwell, A. S. (2019). Reliability-Based Approach to Investigating Long-Term Clogging in Green Stormwater Infrastructure. JOURNAL OF SUSTAINABLE WATER IN THE BUILT ENVIRONMENT, 5(1), Article 04018015. | D19: https://doi.org/10.1061/JSWBAY.0000875 | E19: 2019 | F19: 0 | G19: 1
A20: 2015IL296B | B20: Journal Article | C20: Barker, Z. A., & Stillwell, A. S. (2016). Implications of Transitioning from De Facto to Engineered Water Reuse for Power Plant Cooling. ENVIRONMENTAL SCIENCE & TECHNOLOGY, 50(10), 5379-5388. | D20: https://doi.org/10.1021/acs.est.5b05753 | E20: 2016 | F20: 0 | G20: 1
A21: 2015IL298G | B21: Journal Article | C21: Huff Hartz, K. E., Nutile, S. A., Fung, C. Y., Sinche, F. L., Moran, P. W., Van Metre, P. C., Nowell, L. H., & Lydy, M. J. (2019). Survey of bioaccessible pyrethroid insecticides and sediment toxicity in urban streams of the northeast United States. Environmental Pollution, 254, 112931. | D21: https://doi.org/https://doi.org/10.1016/j.envpol.2019.07.099 | E21: 2019 | F21: 3 | G21: 3
A22: 2015IL298G | B22: Journal Article | C22: Huff Hartz, K. E., Sinche, F. L., Nutile, S. A., Fung, C. Y., Moran, P. W., Van Metre, P. C., Nowell, L. H., Mills, M., & Lydy, M. J. (2018). Effect of sample holding time on bioaccessibility and sediment ecotoxicological assessments. Environmental Pollution, 242, 2078-2087. | D22: https://doi.org/https://doi.org/10.1016/j.envpol.2018.06.065 | E22: 2018 | F22: 3 | G22: 3
A23: 2018IL341B | B23: Journal Article | C23: Wu, D., Li, R. P., Zhang, F. Y., & Liu, J. (2019). A review on drone-based harmful algae blooms monitoring. ENVIRONMENTAL MONITORING AND ASSESSMENT, 191(4), Article 211. | D23: https://doi.org/10.1007/s10661-019-7365-8 | E23: 2019 | F23: 0 | G23: 1
E24: .

Sheet otherProducts
A1: Project ID | B1: Product Type (select from product categories) | C1: Product Citation (Indicate Web-page or other identifier in adjacent column; if none available, provide further detail in the"Stage of Product" and/or "Additional Comments" column. This list may include citations for projects from the previous year before this 5-year cycle, so long as the citation was not already included in the previous year's report) | D1: Web-page, ISBN, or other identifier | E1: Stage of Product, if not complete (inProgress, submitted/inReview, inRevision, inProofs, complete but no weblink established) | F1: Year of Publication | G1: How many students were co-authors of this product? | H1: How many USGS staff were co-authors of this product? | I1: Additional Comments
A2: 2017IL331B | B2: Thesis/Dissertation | C2: Cohen, D. B. (2018). MICROBIAL COMMUNITY ASSEMBLY AND HYDROLOGIC VARIABILITY AS CONTROLS ON POTENTIAL DENITRIFICATION RATES IN RESTORED FRESHWATER WETLANDS | D2: https://hdl.handle.net/2142/101669 | F2: 2018 | G2: 1 | H2: 0
A3: 2017IL330B | B3: Conference Proceedings Paper (not abstract) | C3: Izadmehr, M., & Rockne, K. (2018). “Pocket Wetlands” for Nutrient Removal in Tile-Drained Agriculture. | D3: https://doi.org/10.1061/9780784481400.038 | F3: 2018 | G3: 1 | H3: 0
A4: 2016IL314B | B4: Thesis/Dissertation | C4: Lewis, Q. (2018). Measuring flow and mixing at stream confluences using large-scale particle image velocimetry, in-stream techniques, and small unmanned aerial systems | D4: https://hdl.handle.net/2142/101109 | F4: 2018 | G4: 1 | H4: 0
A5: 2017IL331B | B5: Thesis/Dissertation | C5: Tillman, S. C. (2020). WETLAND MITIGATION BANKING IN THE CHICAGO AREA: AN ASSESSMENT OF ECOLOGICAL OUTCOMES AND COMPLIANCE WITH PERFORMANCE STANDARDS | D5: https://hdl.handle.net/2142/109459 | F5: 2020 | G5: 1 | H5: 0
A6: 2017IL329B | B6: Thesis/Dissertation | C6: William, R. (2019). The role of reliability in characterizing green stormwater infrastructure in urban areas | D6: https://hdl.handle.net/2142/104806 | F6: 2019 | G6: 1 | H6: 0
A7: 2015IL295B | B7: Thesis/Dissertation | C7: Peimer, A. W. (2016). Banking on offsets: a political ecological and eco-geomorphic analysis of Section 404 compensatory stream mitigation banking in Illinois and Missouri | D7: http://hdl.handle.net.proxy2.library.illinois.edu/2142/93034 | F7: 2016 | G7: 1 | H7: 0

Sheet Awards-Achievements-Grants
A1: Project ID | B1: Award, Achievement, or Grant (This may include awards and achievements for projects from the previous year to this 5-year cycle, so long as they were not already included in last year's report) | C1: Source? Identify the Organization | D1: Description of Award, Achievement, or Grant (This may include awards and achievements for projects from the previous year to this 5-year cycle, so long as they were not already included in last year's report) | E1: Award Recipient(s), Name | F1: Date (Mo/Year) | G1: Who was the recipient? | H1: Monetary Benefit of Award or Achievement (if applicable; use NA if not applicable) | I1: Additional Comments
A2: 2019IL089B | B2: Award | C2: UCOWR | D2: UCOWR Early Career Award for Applied Research | E2: Dr. Ashlynn Stillwell | F2: 2019 | G2: PI | I2: The UCOWR Early Career Award for Applied Research recognizes outstanding early contributions in applied research related to water.
A3: 2019IL089B | B3: Award | C3: UCOWR | D3: First place recipient Ph.D. Dissertation Award in the category of Water Policy and SocioEconomics | E3: Dr. Christopher Chini | F3: 2019 | G3: Student | H3: Dissertation awardees will receive a $750 cash award, reimbursement up to $1,000 for travel expenses to the annual UCOWR conference and a waived conference registration fee. Recipients will be asked to present their research during one of the concurrent sessions. This is a total award package of up to $2,300. | I3: Each year, UCOWR recognizes two outstanding Ph.D. dissertations on water issues, one in each of the following categories: (1) Water Policy and SocioEconomics, and (2) Natural Science and Engineering.
A4: 2011IL222B | B4: Achievement | C4: UCOWR | D4: Dissertation was nominated for the UCOWR Ph.D. Dissertation Award in Natural Science and Engineering, but was not selected. | E4: Dr. David Waterman | F4: 2019 | G4: Student | H4: Dissertation awardees will receive a $750 cash award, reimbursement up to $1,000 for travel expenses to the annual UCOWR conference and a waived conference registration fee. Recipients will be asked to present their research during one of the concurrent sessions. This is a total award package of up to $2,300. | I4: Each year, UCOWR recognizes two outstanding Ph.D. dissertations on water issues, one in each of the following categories: (1) Water Policy and SocioEconomics, and (2) Natural Science and Engineering.
A5: 2015IL298G | B5: Award | C5: Southern Illinois University | D5: University Level Scholar Excellence Award | E5: Dr. Michael Lydy | F5: 2017 | G5: PI | H5: The permanent title of Distinguished Scholar, a framed certificate, and a $1,000 monetary award are to be granted to the recipient of the University-Level Scholar Excellence Award. He/She will also receive recognition at the annual awards reception and May commencement ceremony. | I5: The University-Level Scholar Excellence Award is an exceptional one, given only to those who have made outstanding contributions to their discipline and have thus become widely recognized for their achievements by other scholars in the field.
A6: 2015IL298G | B6: Award | C6: Southern Illinois University | D6: Morris Doctoral Fellowship | E6: Sam Nutile | F6: 2016 | G6: Student | H6: The Morris Doctoral Fellowship is a five-year financial support package. The Graduate School provides a 12 month 50% research fellowship award for the first three years and the department provides a 12 month 50% graduate assistantship for the last two years. | I6: The Morris Doctoral Fellowship was established by Southern Illinois University to honor a distinguished former president (1949-1971) and his wife. This fellowship is for students new to Southern Illinois University who possess exceptional academic credentials and evidence of significant potential for research and publication.
A7: 2015IL298G | B7: Award | C7: Southern Illinois University | D7: REACH Award for undergraduate research | E7: Andrew Derby | F7: 42826 | G7: Student | H7: 2000 | I7: The REACH (Research-Enriched Academic Challenge) award offers the opportunity for SIU Carbondale undergraduate students to work with a faculty member on independent creative activities or research.
A8: 2015IL298G | B8: Award | C8: Southern Illinois University | D8: Master’s Fellowship Award | E8: Andrew Derby | F8: 2018 | G8: Student | H8: A fellowship covers full tuition (nine hours maximum in summer) and provides a monthly stipend.
A9: 2015IL298G | B9: Award | C9: Southern Illinois University | D9: REACH Award for undergraduate research | E9: Tristin Miller | F9: 43556 | G9: Student | H9: 2000 | I9: The REACH (Research-Enriched Academic Challenge) award offers the opportunity for SIU Carbondale undergraduate students to work with a faculty member on independent creative activities or research.
A10: 2015IL298G | B10: Award | C10: Southern Illinois University | D10: REACH Award for undergraduate research | E10: Luis Prado | F10: 43556 | G10: Student | H10: 2000 | I10: The REACH (Research-Enriched Academic Challenge) award offers the opportunity for SIU Carbondale undergraduate students to work with a faculty member on independent creative activities or research.
A11: 2015IL298G | B11: Award | C11: Southern Illinois University | D11: Dissertation Research Assistantship | E11: Federico Sinche | F11: 2016 | G11: Student | H11: A DRA award covers full tuition (nine hours maximum in summer) and provides a monthly stipend. | I11: Dissertation Research Assistantships are academic awards designed for students who are in the dissertation preparation stage of their graduate education.
A12: 2015IL298G | B12: Award | C12: Rutgers/Society of Environmental Toxicology and Chemistry | D12: SETAC/EA EngineeringJeff Black Award for top master’s student for the society | E12: Corie Fulton | F12: 2018 | G12: Student | H12: 2000
A13: 2015IL298G | B13: Award | C13: Southern Illinois University | D13: Master’s Fellowship Award | E13: Courtney Fung | F13: 2016 | G13: Student | H13: A fellowship covers full tuition (nine hours maximum in summer) and provides a monthly stipend.
A14: 2018IL338B | B14: Award | C14: University of Illinois School of Integrative Biology | D14: William H. Luckman Award for Research in Applied Entomology | E14: Allison Parker | F14: 2018 | G14: Student | H14: 1000
A15: 2018IL338B | B15: Award | C15: University of Illinois | D15: Dissertation Completion Fellowship | E15: Allison Parker | F15: 2018 | G15: Student | H15: 20000
B16: Award | C16: American Fisheries Society | D16: Award from the Illinois Chapter of the American Fisheries Society to contribute to this project | E16: Amy Schneider | G16: Student | H16: 500
B17: Award | C17: Illinois State University | D17: One of 11 research awards from the university-wide Undergraduate Research Support Program (URSP) | E17: Joe Hoberg | F17: 2021 | G17: Student | H17: 4500
B18: Achievement | C18: Illinois State University | D18: Recognition in the category of Outstanding Research Promise as the top first year graduate student (2021). | E18: Alhassan Sahad | F18: 2021 | G18: Student
A19: 2018IL342B | B19: Grant | C19: Illinois Water Resources Center | D19: 2019 Emerging Contaminants in the Environment Conference Sponsor | E19: NA | F19: 43586 | G19: Other | H19: 1500
A20: 2018IL342B | B20: Grant | C20: Illinois Water Resources Center | D20: Illinois Center for Urban Resilience and Environmental Sustainability Planning Workshop Sponsor | E20: NA | F20: 43313 | G20: Other | H20: 500
A21: 2018IL342B | B21: Grant | C21: Illinois Water Resources Center | D21: Provided support for attendance at the ArcSWAT Workshop held at Auburn University, Alabama for a master’s student researching Impacts of Climate Change on Streamflow and Water Quality in the Cahokia Creek Watershed, Madison County, Illinois | E21: Omoloa Badmus | F21: 43497 | G21: Student
A22: 2016IL315B | B22: Award | C22: University of Illinois College of Agricultural, Consumer, and Environmental Science | D22: Team Award for Excellence | E22: Illinois Water Resources Center Staff | F22: 2017 | G22: Other | H22: 6000 | I22: The Team Award for Excellence recognizes faculty members and staff who, working together as a team, have made a significant contribution in teaching, research, or extension.

Sheet social media
A1: Project ID | B1: Title/Username of Social Media | C1: Social Media Activity (Type) | D1: Estimated Audience Size | E1: Primary Audience Type | F1: If relevant, how did this activity foster Diversity, Equity, Inclusion, Accessibility, & Justice? Please elaborate | G1: Additional Comments
A2: 2018IL342B | B2: Illinois Water Resources Center | C2: facebook | D2: 300 | E2: Academic | F2: NA
A3: 2016IL315B | B3: WaterOperator.org | C3: web page | E3: Resource Managers | F3: NA | G3: The Illinois State Water Survey, in collaboration with the Illinois Water Resources Center and Rural Community Assistance Partnership and with funding from the U.S. Environmental Protection Agency, manages two national community outreach programs focused on providing theinformation and tools needed to protect drinking and source water quality in rural areas. The web-based Private Well Class offers groundwater science education and technical assistance for well owners, realtors, and others interested in well care best practices. WaterOperator.org is a mobile-friendly web portal with free, comprehensive resources tailored for small community and tribal water and wastewater operators.
A4: 2016IL315B | B4: iwrc.illinois.edu | C4: web page | E4: Other | F4: NA
A5: 2017IL334B | B5: iwrc.illinois.edu | C5: web page | E5: Other | F5: NA
A6: 2018IL342B | B6: iwrc.illinois.edu | C6: web page | E6: Other | F6: NA
A7: 2020IL212B | B7: iwrc.illinois.edu | C7: web page | E7: Other | F7: NA
A8: 2018IL342B | B8: geothermal.illinois.edu | C8: web page | E8: Other | F8: NA
A9: 2020IL212B | B9: geothermal.illinois.edu | C9: web page | E9: Other | F9: NA

Sheet Conference Presentations
A1: Project ID | B1: Presentation Title | C1: Venue | D1: Date (Mo/Year) | E1: Project PI | F1: Who was the presentor? | G1: How many students were co-authors of this presentation? | H1: How many USGS staff were co-authors of this presentation? | I1: Primary Audience Type | J1: Additional Description (if applicable)
A2: 2015IL298G | B2: Application of a bioaccessibility-based method for pyrethroid insecticides: A case study | C2: UCOWR/NIWR Annual Water Resources Conference | D2: 43617 | E2: Michael J. Lydy | F2: Other | G2: 0 | H2: 0 | I2: Academic
A3: 2015IL298G | B3: Does the use of a sediment holding time bias laboratory bioassay results? | C3: UCOWR/NIWR Annual Water Resources Conference | D3: 43618 | E3: Michael J. Lydy | F3: Other | G3: 0 | H3: 0 | I3: Academic
A4: 2015IL298G | B4: The contribution of detoxification pathways to pyrethroid resistance in Hyalella azteca | C4: SETAC North America 39th Annual Meeting | D4: 43422 | E4: Michael J. Lydy | F4: PI | G4: 2 | H4: 0 | I4: Academic
A5: 2015IL298G | B5: Overview and mechanisms of resistance in the freshwater crustacean Hyalella Azteca | C5: SETAC North America 39th Annual Meeting | D5: 43423 | E5: Michael J. Lydy | F5: Other | G5: 2 | H5: 0 | I5: Academic
A6: 2015IL298G | B6: Are pyrethroid insecticides a threat to aquatic non-target species? | C6: Illinois Sustainable Technology Center | D6: 42795 | E6: Michael J. Lydy | F6: PI | G6: 0 | H6: 0 | I6: Academic
A7: 2015IL298G | B7: Are provisional species of Hyalella azteca capable of producing viable offspring and are the resulting offspring less able to handle environmental challenges? | C7: Southern Illinois University Undergraduate Creative Avtivities and Research Forum | D7: 42826 | E7: Michael J. Lydy | F7: Student | G7: 2 | H7: 0 | I7: Public
A8: 2015IL298G | B8: Assessing dominance of pyrethroid insecticide resistance in Hyalella azteca by crossbreeding homozygous resistant (L925I) and non-resistant (wild-type) populations | C8: Southern Illinois University Undergraduate Creative Avtivities and Research Forum | D8: 42827 | E8: Michael J. Lydy | F8: Student | G8: 3 | H8: 0 | I8: Public
A9: 2015IL298G | B9: The contribution of detoxification pathways to pyrethroid resistance in Hyalella azteca | C9: Ozark Prairie SETAC | D9: 42856 | E9: Michael J. Lydy | F9: Student | G9: 2 | H9: 0 | I9: Academic
A10: 2015IL298G | B10: Assessing dominance of pyrethroid insecticide resistance in Hyalella azteca by crossbreeding homozygous resistant (L925I) and non-resistant (wild-type) populations | C10: Ozark Prairie SETAC | D10: 42857 | E10: Michael J. Lydy | F10: Student | G10: 3 | H10: 0 | I10: Academic
A11: 2018IL341B | B11: Remediation of Cr(VI)-contaminated soil from a superfund site using sunflower Helianthus annuus L. | C11: SETAC North America 39th Annual Meeting | D11: 43405 | E11: Jia Liu | F11: Student | G11: 1 | H11: 0 | I11: Academic
A12: 2018IL341B | B12: Biosolids as an alternative to conventional chemical fertilizers for sunflower (Helianthus annuus L.) in phytoremediation of Cr(VI)-contaminated soil from a superfund site. | C12: Southern Illinois University Materials Technology Center Poster Session | D12: 43436 | E12: Jia Liu | F12: Student | G12: 1 | H12: 0 | I12: Academic
A13: 2018IL341B | B13: Remediation of trichloroethylene (TCE) and tetrachloroethylene (PCE) contaminated groundwater from a Superfund site using sunflower Helianthus annuus L | C13: Southern Illinois University UN Sustainable Development Goals Event | D13: 43132 | E13: Jia Liu | F13: Student | G13: 1 | H13: 0 | I13: Academic
A14: 2017IL330B | B14: Identifying Factors Influencing Tile Drainage Nutrient Removal Efficiency in Constructed Wetlands | C14: American Society of Civil Engineers Environmental and Water Research Institute (ASCE-EWRI) 2019 World Environmental & Water Resources Congress | D14: 43586 | E14: Karl J. Rockne | F14: Student | G14: 1 | H14: 0 | I14: Academic
A15: 2017IL330B | B15: Pocket Wetlands for Nutrient Removal in Tile-Drained Agriculture | C15: American Society of Civil Engineers Environmental and Water Research Institute (ASCE-EWRI) 2019 World Environmental & Water Resources Congress | D15: 43252 | E15: Karl J. Rockne | F15: Student | G15: 1 | H15: 0 | I15: Academic | J15: Paper awarded first place in the graduate student paper competition
A16: 2017IL330B | B16: Impact of Drought Conditions on Nutrient Removal, Sediment Organic Matter, and Microbial communities in a Treatment Wetland | C16: Association of Environmental Engineering & Science Professors (AEESP | D16: 43587 | E16: Karl J. Rockne | F16: Student | G16: 1 | H16: 0 | I16: Academic
A17: 2017IL330B | B17: Impact of Drought Conditions on Nutrient Removal, Sediment Organic Matter, and Microbial communities in a Treatment Wetland | C17: American Geophysical Union Academic & Science (AGU) | D17: 43435 | E17: Karl J. Rockne | F17: Student | G17: 1 | H17: 0 | I17: Academic
A18: 2017IL330B | B18: Annual Changes in the Sediment Microbiome Structure During Development of a Constructed Wetland | C18: American Society for Microbiology (ASM) Microbe | D18: 43252 | E18: Karl J. Rockne | F18: Student | G18: 1 | H18: 0 | I18: Academic
A19: 2017IL330B | B19: Nutrient Removal Efficiency in An Engineered Wetland | C19: Christopher B. and Susan S.Burke Civil Engineering Graduate Poster Competition | D19: 43191 | E19: Karl J. Rockne | F19: Student | G19: 1 | H19: 0 | I19: Academic | J19: Poster awarded 3rd place in the competition
A20: 2017IL330B | B20: Treatment Wetlands for Meeting the Illinois Nutrient Reduction Strategy Goals | C20: Illinois Nutrient Research and Education Council, Northern Illinois Public Forum | D20: 42887 | E20: Karl J. Rockne | F20: PI | G20: 1 | H20: 0 | I20: Academic
A21: 2017IL330B | B21: Treatment Wetlands: A Key Technology for Meeting the Illinois Nutrient Reduction Strategy Goals | C21: US Army Corps of Engineers Chicago District Society of American Military Engineers (SAME) | D21: 42736 | E21: Karl J. Rockne | F21: PI | G21: 2 | H21: 0 | I21: Academic | J21: Invited speaker
A22: 2017IL330B | B22: Sediment Microbiome Dynamics in a Nutrient Treatment Wetland Sediment | C22: Battelle Contaminated Sediment Conference | D22: 42736 | E22: Karl J. Rockne | F22: Student | G22: 2 | H22: 0 | I22: Academic
A23: 2017IL330B | B23: Constructed Wetlands to Reduce Nutrients from Runoff in Croplands: The Implications for Urban Stormwater | C23: StormCon Conference | D23: 42583 | E23: Karl J. Rockne | F23: Student | G23: 1 | H23: 0 | I23: Academic
A24: 2017IL330B | B24: Demonstrating and Monitoring Nutrient Removal in a Constructed Wetland | C24: Illinois Water Conference | D24: 42644 | E24: Karl J. Rockne | F24: Student | G24: 1 | H24: 0 | I24: Academic
A25: 2017IL329B | B25: Validating runoff of the Community Earth System Model (CESM) CMIP6 simulation against surface observation and reanalysis data | C25: American Geophysical Union Fall Meeting | D25: 44166 | E25: Ashlynn S. Stillwell | F25: Student | G25: 0 | H25: 0 | I25: Academic
A26: 2016IL315B | B26: Nutrient Loss Reduction Strategy | C26: Illinois State Fair | D26: 2017 | E26: Illinois Water Resources Center | F26: PI | H26: 0 | I26: Public
A27: 2016IL315B | B27: 4-hour Environmental Health Professional Workshop trainings for Continuing Education Credits | C27: Tribal Lands and Environment Forum in Connecticut | D27: 2017 | E27: Illinois Water Resources Center | F27: PI | I27: Public
A28: 2018IL340B | B28: Drone-based Water Quality Monitoring for Harmful Algal Blooms | C28: Southern Illinois Volunteer Lake Monitoring Program | D28: 43556 | E28: Ruopu Li | F28: PI | G28: 0 | H28: 0 | I28: Public | J28: Invited speaker

Sheet Education and Outreach
A1: Project ID | B1: Education or Outreach Activity (Include Conference and Workshop Sponsorship or Assistance, Citizen Science, Water Education for Teachers (WET), Support for Local Advisory Consortiums, etc.) | C1: Estimated Audience Size | D1: Date (Mo/Year) | E1: Primary Audience Type (Select from list) | F1: Did this activity foster Diversity, Equity, Inclusion, Accessibility, & Justice? Please elaborate | G1: Additional Comments
B2: Drone-based Water Quality Monitoring for Harmful Algal Blooms. Dr. Ruopu Li. Invited talk for the local community under Southern Illinois Volunteer Lake Monitoring Program in Marion, IL | D2: 43556
B3: Treatment Wetlands for Meeting the Illinois Nutrient Reduction Strategy Goals at Nothern Illinois Public Forum | D3: 42736 | E3: Public
A4: 2018IL342B | B4: Groundwater and Geothermal Resources Seminar Series | C4: 50 | D4: 43405 | E4: Academic | F4: NA | G4: Free and open to the public
A5: 2018IL342B | B5: IWRC hosted a tour of their Center as well as the UIUC ACES Energy Farm for a group of educators from Taiwan as part of an academic enrichment program that specializes in preparing students in Asia for studies in the US. | C5: 10 | D5: 43525 | E5: Academic | F5: NA
A6: 2018IL342B | B6: Yu-Feng Lin, IWRC Director visited Southern Illinois University, Carbondale to promote IWRC’s mission and to visit IWRC funded PIs. | C6: 10 | D6: 2019 | E6: Academic | F6: NA
A7: 2016IL315B | B7: Planting for Pollinators video series | D7: 2016 | E7: Public | F7: NA
A8: 2016IL315B | B8: Private Well Class multimedia content | D8: 2016 | E8: Public | F8: NA | G8: A flagship national 10-week educational email course for private well owners. Content provided includes the Private Well Podcast, well care videos, live webinars once a month with Q & A that feature a variety of topics, social media via Facebook and Twitter, and other resources.
A9: 2016IL315B | B9: 4-hour Environmental Health Professional Workshop trainings for Continuing Education Credits in Oregon, Virginia, Massachusetts, Connecticut, Illinois, Tennessee, and online | D9: 2016
A10: 2016IL315B | B10: Stormwater/Green Infrastructure activities including a speaking engagement at Common Place Peoria | C10: 10 | D10: 42401 | E10: Other | F10: NA | G10: audience included key community decision makers and youth
A11: 2016IL315B | B11: Stormwater/Green Infrastructure activities including a speaking engagement at 4G STEM Camp | C11: 39 | D11: 42522 | E11: Students | F11: NA
A12: 2016IL315B | B12: Stormwater/Green Infrastructure activities including a speaking engagement at Greater Egypt Regional Planning Commission Stormwater Training | C12: 58 | D12: 42552 | E12: Other | F12: NA | G12: audience included key community decision makers and youth
A13: 2016IL315B | B13: Stormwater/Green Infrastructure activities including a speaking engagement at Illinois State Fair | C13: 20 | D13: 42583 | E13: Public | F13: NA
A14: 2016IL315B | B14: Stormwater/Green Infrastructure activities including a speaking engagement at CU Sunshine Rotary | C14: 40 | D14: 42614 | E14: Public | F14: NA
A15: 2016IL315B | B15: Stormwater/Green Infrastructure activities including a speaking engagement at Master Naturalist Urban Systems Training | C15: 37 | D15: 42644 | E15: Other | F15: NA | G15: audience included key community decision makers and youth

Sheet USGS Collaboration
A1: Project ID | B1: USGS Point of Contact/s (Name/s) | C1: USGS Point of Contact/s Affiliation (Work Unit/s) | D1: USGS Collaboration
A2: 2014IL292S | B2: Toshiki Iwasaki | C2: Geomorphology and Sediment Transport Laboratory, Golden, Colorado | D2: Project report first author
A3: 2014IL292S | B3: Jonathan Nelson | C3: Geomorphology and Sediment Transport Laboratory, Golden, Colorado | D3: Project report co-author
A4: 2015IL298G | B4: Patrick W. Moran | C4: Washington Water Science Center, Tacoma, Washington | D4: Co-author on "Survey of bioaccessible pyrethroid insecticides and sediment toxicity in urban streams of the northeast United States"
A5: 2015IL298G | B5: Peter C. Van Metre | C5: Texas Water Science Center, Austin, Texas | D5: Co-author on "Survey of bioaccessible pyrethroid insecticides and sediment toxicity in urban streams of the northeast United States"
A6: 2015IL298G | B6: Lisa H. Nowell | C6: California Water Science Center, Sacramento, California | D6: Co-author on "Survey of bioaccessible pyrethroid insecticides and sediment toxicity in urban streams of the northeast United States"
A7: 2015IL298G | B7: Patrick W. Moran | C7: Washington Water Science Center, Tacoma, Washington | D7: Co-author on "Effect of sample holding time on bioaccessibility and sediment ecotoxicological assessments"
A8: 2015IL298G | B8: Peter C. Van Metre | C8: Texas Water Science Center, Austin, Texas | D8: Co-author on "Effect of sample holding time on bioaccessibility and sediment ecotoxicological assessments"
A9: 2015IL298G | B9: Lisa H. Nowell | C9: California Water Science Center, Sacramento, California | D9: Co-author on "Effect of sample holding time on bioaccessibility and sediment ecotoxicological assessments"
A10: 2016IL314B | B10: Frank L. Engel | C10: Illinois Water Science Center | D10: Collaborator on 104B project
A35: =IF(('Project Overview'!A36) <> 0, 'Project Overview'!A36, "")
A36: =IF(('Project Overview'!A37) <> 0, 'Project Overview'!A37, "")
A37: =IF(('Project Overview'!A38) <> 0, 'Project Overview'!A38, "")
A38: =IF(('Project Overview'!A39) <> 0, 'Project Overview'!A39, "")
A39: =IF(('Project Overview'!A40) <> 0, 'Project Overview'!A40, "")
A40: =IF(('Project Overview'!A41) <> 0, 'Project Overview'!A41, "")
A41: =IF(('Project Overview'!A42) <> 0, 'Project Overview'!A42, "")
A42: =IF(('Project Overview'!A43) <> 0, 'Project Overview'!A43, "")
A43: =IF(('Project Overview'!A44) <> 0, 'Project Overview'!A44, "")
A44: =IF(('Project Overview'!A45) <> 0, 'Project Overview'!A45, "")
A45: =IF(('Project Overview'!A46) <> 0, 'Project Overview'!A46, "")
A46: =IF(('Project Overview'!A47) <> 0, 'Project Overview'!A47, "")
... A354: =IF(('Project Overview'!A355) <> 0, 'Project Overview'!A355, "")

Sheet Other Activity
A1: Project ID | B1: Description of Other Activity (e.g., media interviews, technology transfer activity, etc.) | C1: Web-page, Web Link, or Other Identifier (if applicable)

Sheet 2019_IL_Eval_results
A1: Result | B1: Recommendations | C1: Action | D1: Comments
A2: Pass | B2: The panel recommends using the advisory board as well as working partnerships (i.e., nutrient reduction strategy groups) to identify the most pressing research needs and coordinating the competitive grants program accordingly. | C2: The Illinois Water Resources Center (IWRC) has a transdisciplinary advisory board that helps guide IWRC's strategic plan and informs statewide research needs. | D2: Overall, the Institute provides some concrete examples of quality and relevant work, particularly the Institute’s role in developing and implementing the state’s nutrient loss reduction plan and their collaboration for better education and outreach on private wells.
B3: The panel encourages the Institute to fund more PIs in junior faculty ranks. The number of students impacted is quite satisfactory; the panel encourages the Institute to develop strategies, metrics, and documentation for significant educational impacts. | C3: During the reporting period, the Director of IWRC transferred. Since the reporting period here, IWRC has worked to develop additional metrics and strategies to increase impact around the state. | D3: The institute has a rigorous RFP process that includes institutions of higher education state-wide.
B4: The panel would like to see additional information on the scope and subsequent impacts of the information transfer program. | C4: IWRC was in transition following the reporting period and has since increased the scope of the information transfer priorities. | D4: The peer review process for selecting proposals is strong.
B5: The panel encourages the state or university to provide additional discretionary funds or salary support to the Institute | C5: IWRC has transitioned to a research institute from extension during the reporting period. This will allow more flexibility in obtaining additional, external funding. Negotiations with the univerisity have been fruitful as well, providing additional support to IWRC through 2026 after which, university support will cease.

Sheet Keyword_drop_down_options
A1: Keywords | B1: Cross-Discipline Science | C1: Cross-Discipline Landscape | D1: Science Priority
A2: ACID DEPOSITION | D2: Water Scarcity and Availability
A3: AGRICULTURE | D3: Water-Related Hazards and Climate Variability
A4: CLIMATOLOGICAL PROCESSES | D4: Water Quality
A5: CONSERVATION | D5: Water Policy, Planning, and Socioeconomics
A6: DROUGHT | D6: Water Technology and Innovation
A7: ECOLOGY | D7: Workforce Development and Water Literacy
A8: ECONOMICS | D8: Watershed and Ecosystem Function
A9: EDUCATION
A10: FLOODS
A11: GEOMORPOLOGICAL PROCESSES
A12: GEOCHEMICAL PROCESSES
A13: GROUNDWATER
A14: HYDROGEOCHEMISTRY
A15: HYDROLOGY
A16: INVASIVE SPECIES
A17: IRRIGATION
A18: LAW, INSTITUTIONS, AND POLICY
A19: MANAGEMENT AND PLANNING
A20: METHODS
... A36: WETLANDS
