Workbook

Sheet 2025 data
A1: PI | B1: Award Amount | C1: College | D1: Department | E1: Institution | F1: City | G1: State | H1: PhD | I1: MS | J1: undergrad | K1: postdocs | L1: DEA | M1: WRRI Science Priority | N1: Keyword 1 | O1: Keyword 2 | P1: Keyword 3 | S1: Product Type (Journal article, report, dataset, with Digital Object Identifier) | T1: Product Citation (Indicate Digital Object Identifier and publication year in appropriate adjoining columns. If none available, go to "Other Products" Tab, and list product type and stage of completion. Provide further details about the doi product in the Additional Comments column. This list may include citations for projects from this 5-year period and one previous year, so long as the citation was not already included in previous year's report) | U1: Digital Object Identifier (DOI) | V1: Year of Publication | W1: How many USGS staff were co-authors of this product? | X1: How many students were co-authors of this product? | Z1: Award, Achievement, or Grant (This may include awards and achievements for projects from the previous year to this 5-year cycle, so long as they were not already included in last year's report) | AA1: Source? Identify the Organization | AB1: Description of Award, Achievement, or Grant (This may include awards and achievements for projects from the previous year to this 5-year cycle, so long as they were not already included in last year's report) | AC1: Award Recipient(s), Name | AD1: Date (Mo/Year) | AE1: Who was the recipient? | AF1: Monetary Benefit of Award or Achievement (if applicable; use NA if not applicable) | AG1: Additional Comments
A2: 2015 | S2: Journal Article | T2: Favata, C. A., Maia, A., Pant, M., Nepal, V., & Colombo, R. E. (2018). Fish assemblage change following the structural restoration of a degraded stream. RIVER RESEARCH AND APPLICATIONS, 34(8), 927-936. | U2: https://doi.org/10.1002/rra.3336 | V2: 2018 | Z2: Award | AA2: Southern Illinois University | AB2: University Level Scholar Excellence Award | AC2: Dr. Michael Lydy | AD2: 2017 | AE2: PI | AF2: The permanent title of Distinguished Scholar, a framed certificate, and a $1,000 monetary award are to be granted to the recipient of the University-Level Scholar Excellence Award. He/She will also receive recognition at the annual awards reception and May commencement ceremony. | AG2: The University-Level Scholar Excellence Award is an exceptional one, given only to those who have made outstanding contributions to their discipline and have thus become widely recognized for their achievements by other scholars in the field.
A3: Maia | B3: 9977 | E3: Eastern Illinois University | M3: Watershed and Ecosystem Function | S3: Journal Article | T3: Smith, S. C. F., Colombo, R. E., Thomas, T., & Keeney, D. B. (2019). Dissimilar effects of low-head dams on the genetic structure of riverine fishes. FRESHWATER SCIENCE, 38(1), 92-102. | U3: https://doi.org/10.1086/701598 | V3: 2019 | Z3: Award | AA3: Southern Illinois University | AB3: Morris Doctoral Fellowship | AC3: Sam Nutile | AD3: 2016 | AE3: Student | AF3: The Morris Doctoral Fellowship is a five-year financial support package. The Graduate School provides a 12 month 50% research fellowship award for the first three years and the department provides a 12 month 50% graduate assistantship for the last two years. | AG3: The Morris Doctoral Fellowship was established by Southern Illinois University to honor a distinguished former president (1949-1971) and his wife. This fellowship is for students new to Southern Illinois University who possess exceptional academic credentials and evidence of significant potential for research and publication.
A4: Rhoads | B4: 5591 | C4: College of Liberal Arts & Sciences | D4: Geography and Geographic Information Science | E4: University of Illinois Urbana-Champaign | F4: Urbana-Champaign | G4: Illinois | M4: Water Quality | S4: Journal Article | T4: Pant, M., Nepal, V., West, J. L., & Colombo, R. E. (2019). Seasonal differences in diversity of macroinvertebrate and fish taxa in a Midwestern stream. RIVER RESEARCH AND APPLICATIONS, 35(6), 692-701. | U4: https://doi.org/10.1002/rra.3441 | V4: 2019 | Z4: Award | AA4: Southern Illinois University | AB4: REACH Award for undergraduate research | AC4: Andrew Derby | AD4: 42826 | AE4: Student | AF4: 2000 | AG4: The REACH (Research-Enriched Academic Challenge) award offers the opportunity for SIU Carbondale undergraduate students to work with a faculty member on independent creative activities or research.
A5: Stillwell | B5: 10000 | C5: Grainger College of Engineering | D5: Civil and Environmental Engineering | E5: University of Illinois Urbana-Champaign | F5: Urbana-Champaign | G5: Illinois | M5: Water Scarcity and Availability | S5: Thesis/Dissertation | T5: Peimer, A. W. (2016). Banking on offsets: a political ecological and eco-geomorphic analysis of Section 404 compensatory stream mitigation banking in Illinois and Missouri | U5: http://hdl.handle.net.proxy2.library.illinois.edu/2142/93034 | V5: 2016 | Z5: Award | AA5: Southern Illinois University | AB5: Master’s Fellowship Award | AC5: Andrew Derby | AD5: 2018 | AE5: Student | AF5: A fellowship covers full tuition (nine hours maximum in summer) and provides a monthly stipend.
A6: Lydy | B6: 249329 | D6: Chemical and Biomolecular Science, Zoology | E6: Southern Illinois University | H6: 2 | I6: 2 | J6: 3 | M6: Water Quality | N6: MODELS | O6: SEDIMENTS | P6: TOXIC SUBSTANCES | S6: Journal Article | T6: Barker, Z. A., & Stillwell, A. S. (2016). Implications of Transitioning from De Facto to Engineered Water Reuse for Power Plant Cooling. ENVIRONMENTAL SCIENCE & TECHNOLOGY, 50(10), 5379-5388. | U6: https://doi.org/10.1021/acs.est.5b05753 | V6: 2016 | Z6: Award | AA6: Southern Illinois University | AB6: REACH Award for undergraduate research | AC6: Tristin Miller | AD6: 43556 | AE6: Student | AF6: 2000 | AG6: The REACH (Research-Enriched Academic Challenge) award offers the opportunity for SIU Carbondale undergraduate students to work with a faculty member on independent creative activities or research.
A7: Totals | B7: =SUM(B3:B6) -> 274897 | H7: =SUM(H3:H6) -> 2 | I7: =SUM(I3:I6) -> 2 | J7: =SUM(J3:J6) -> 3 | S7: Journal Article | T7: Huff Hartz, K. E., Nutile, S. A., Fung, C. Y., Sinche, F. L., Moran, P. W., Van Metre, P. C., Nowell, L. H., & Lydy, M. J. (2019). Survey of bioaccessible pyrethroid insecticides and sediment toxicity in urban streams of the northeast United States. Environmental Pollution, 254, 112931. | U7: https://doi.org/https://doi.org/10.1016/j.envpol.2019.07.099 | V7: 2019 | Z7: Award | AA7: Southern Illinois University | AB7: REACH Award for undergraduate research | AC7: Luis Prado | AD7: 43556 | AE7: Student | AF7: 2000 | AG7: The REACH (Research-Enriched Academic Challenge) award offers the opportunity for SIU Carbondale undergraduate students to work with a faculty member on independent creative activities or research.
A8: 2016 | S8: Journal Article | T8: Huff Hartz, K. E., Sinche, F. L., Nutile, S. A., Fung, C. Y., Moran, P. W., Van Metre, P. C., Nowell, L. H., Mills, M., & Lydy, M. J. (2018). Effect of sample holding time on bioaccessibility and sediment ecotoxicological assessments. Environmental Pollution, 242, 2078-2087. | U8: https://doi.org/https://doi.org/10.1016/j.envpol.2018.06.065 | V8: 2018 | Z8: Award | AA8: Southern Illinois University | AB8: Dissertation Research Assistantship | AC8: Federico Sinche | AD8: 2016 | AE8: Student | AF8: A DRA award covers full tuition (nine hours maximum in summer) and provides a monthly stipend. | AG8: Dissertation Research Assistantships are academic awards designed for students who are in the dissertation preparation stage of their graduate education.
A9: Eichholz | B9: 1000 | D9: Zoology | E9: Southern Illinois University | H9: 1 | I9: 2 | J9: 5 | M9: Watershed and Ecosystem Function | N9: WETLANDS | O9: FLOODS | P9: ECOLOGY | S9: Journal Article | T9: Berkelhammer, M., Alsip, B., Matamala, R., Cook, D., Whelan, M. E., Joo, E., Bernacchi, C., Miller, J., & Meyers, T. (2020). Seasonal Evolution of Canopy Stomatal Conductance for a Prairie and Maize Field in the Midwestern United States from Continuous Carbonyl Sulfide Fluxes. Geophysical Research Letters, 47(6). | U9: https://doi.org/10.1029/2019gl085652 | V9: 2020 | Z9: Award | AA9: Rutgers/Society of Environmental Toxicology and Chemistry | AB9: SETAC/EA EngineeringJeff Black Award for top master’s student for the society | AC9: Corie Fulton | AD9: 2018 | AE9: Student | AF9: 2000
A10: Benjamin | B10: 9853 | D10: Earth and Environmental Science | E10: University of Illinois Chicago | H10: 0 | I10: 1 | J10: 4 | M10: Water Scarcity and Availability | N10: CLIMATOLOGICAL PROCESSES | O10: AGRICULTURE | P10: HYDROLOGY | S10: Journal Article | T10: Chabela, L. P., & Peterson, E. W. (2019). Relationship between Peak Stage, Storm Duration, and Bank Storage along a Meandering Stream. Water, 11(8). | U10: https://doi.org/10.3390/w11081688 | V10: 2019 | Z10: Award | AA10: Southern Illinois University | AB10: Master’s Fellowship Award | AC10: Courtney Fung | AD10: 2016 | AE10: Student | AF10: A fellowship covers full tuition (nine hours maximum in summer) and provides a monthly stipend.
A11: Peterson | B11: 10000 | D11: Geography, Geology, and the Environment | E11: Illinois State University | H11: 0 | I11: 2 | J11: 3 | M11: Water Quality | N11: NON POINT POLLUTION | O11: MODELS | P11: WATER QUALITY | S11: Journal Article | T11: Lewis, Q. W., Lindroth, E. M., & Rhoads, B. L. (2018). Integrating unmanned aerial systems and LSPIV for rapid, cost-effective stream gauging. JOURNAL OF HYDROLOGY, 560, 230-246. | U11: https://doi.org/10.1016/j.jhydrol.2018.03.008 | V11: 2018 | Z11: Award | AA11: University of Illinois College of Agricultural, Consumer, and Environmental Science | AB11: Team Award for Excellence | AC11: Illinois Water Resources Center Staff | AD11: 2017 | AE11: Other | AF11: 6000 | AG11: The Team Award for Excellence recognizes faculty members and staff who, working together as a team, have made a significant contribution in teaching, research, or extension.
A12: Rhoads | B12: 9915 | C12: College of Liberal Arts & Sciences | D12: Geography and Geographic Information Science | E12: University of Illinois Urbana-Champaign | F12: Urbana-Champaign | G12: Illinois | H12: 1 | I12: 0 | J12: 3 | M12: Water Quality | N12: HYDROLOGY | O12: SURFACE WATER | P12: WATER QUALITY | S12: Journal Article | T12: Lewis, Q. W., & Rhoads, B. L. (2018a). LSPIV Measurements of Two-Dimensional Flow Structure in Streams Using Small Unmanned Aerial Systems: 1. Accuracy Assessment Based on Comparison With Stationary Camera Platforms and In-Stream Velocity Measurements. WATER RESOURCES RESEARCH, 54(10), 8000-8018. | U12: https://doi.org/10.1029/2018WR022550 | V12: 2018 | Z12: Award | AA12: University of Illinois School of Integrative Biology | AB12: William H. Luckman Award for Research in Applied Entomology | AC12: Allison Parker | AD12: 2018 | AE12: Student | AF12: 1000
A13: Miller | B13: 4340273 | E13: University of Illinois Urbana-Champaign | F13: Urbana-Champaign | G13: Illinois | M13: Workforce Development and Water Literacy | S13: Journal Article | T13: Lewis, Q. W., & Rhoads, B. L. (2018b). LSPIV Measurements of Two-Dimensional Flow Structure in Streams Using Small Unmanned Aerial Systems: 2. Hydrodynamic Mapping at River Confluences. WATER RESOURCES RESEARCH, 54(10), 7981-7999. | U13: https://doi.org/10.1029/2018WR022551 | V13: 2018 | Z13: Award | AA13: University of Illinois | AB13: Dissertation Completion Fellowship | AC13: Allison Parker | AD13: 2018 | AE13: Student | AF13: 20000
A14: Totals | B14: =SUM(B9:B13) -> 4371041 | H14: =SUM(H9:H13) -> 2 | I14: =SUM(I9:I13) -> 5 | J14: =SUM(J9:J13) -> 15 | S14: Journal Article | T14: Lewis, Q., Rhoads, B., Sukhodolov, A., & Constantinescu, G. (2020). Advective Lateral Transport of Streamwise Momentum Governs Mixing at Small River Confluences. WATER RESOURCES RESEARCH, 56(9), Article e2019WR026817. | U14: https://doi.org/10.1029/2019WR026817 | V14: 2020
A15: 2017 | S15: Thesis/Dissertation | T15: Lewis, Q. (2018). Measuring flow and mixing at stream confluences using large-scale particle image velocimetry, in-stream techniques, and small unmanned aerial systems | U15: https://hdl.handle.net/2142/101109 | V15: 2018 | Z15: Award | AA15: UCOWR | AB15: UCOWR Early Career Award for Applied Research | AC15: Dr. Ashlynn Stillwell | AD15: 2019 | AE15: PI | AG15: The UCOWR Early Career Award for Applied Research recognizes outstanding early contributions in applied research related to water.
A16: Stillwell | B16: 10000 | C16: Grainger College of Engineering | D16: Civil and Environmental Engineering | E16: University of Illinois Urbana-Champaign | F16: Urbana-Champaign | G16: Illinois | H16: 1 | I16: 0 | J16: 0 | M16: Water Policy, Planning, and Socioeconomics | N16: MANAGEMENT AND PLANNING | O16: CLIMATOLOGICAL PROCESSES | P16: FLOODS | S16: Journal Article | T16: William, R., Gardoni, P., & Stillwell, A. S. (2019). Reliability-Based Approach to Investigating Long-Term Clogging in Green Stormwater Infrastructure. JOURNAL OF SUSTAINABLE WATER IN THE BUILT ENVIRONMENT, 5(1), Article 04018015. | U16: https://doi.org/10.1061/JSWBAY.0000875 | V16: 2019 | Z16: Award | AA16: UCOWR | AB16: First place recipient Ph.D. Dissertation Award in the category of Water Policy and SocioEconomics | AC16: Dr. Christopher Chini | AD16: 2019 | AE16: Student | AF16: Dissertation awardees will receive a $750 cash award, reimbursement up to $1,000 for travel expenses to the annual UCOWR conference and a waived conference registration fee. Recipients will be asked to present their research during one of the concurrent sessions. This is a total award package of up to $2,300. | AG16: Each year, UCOWR recognizes two outstanding Ph.D. dissertations on water issues, one in each of the following categories: (1) Water Policy and SocioEconomics, and (2) Natural Science and Engineering.
A17: Rockne | B17: 10000 | D17: Civil, Materials, and Environmental Engineering | E17: University of Illinois Chicago | H17: 1 | I17: 0 | J17: 0 | M17: Watershed and Ecosystem Function | N17: AGRICULTURE | O17: NUTRIENTS | P17: WETLANDS | S17: Thesis/Dissertation | T17: William, R. (2019). The role of reliability in characterizing green stormwater infrastructure in urban areas | U17: https://hdl.handle.net/2142/104806 | V17: 2019 | Z17: Award | AA17: Illinois State University | AB17: One of 11 research awards from the university-wide Undergraduate Research Support Program (URSP) | AC17: Joe Hoberg | AD17: 2021 | AE17: Student | AF17: 4500
A18: Matthews | B18: 4668 | D18: Natural Resources and Environmental Science | E18: University of Illinois Urbana-Champaign | F18: Urbana-Champaign | G18: Illinois | H18: 0 | I18: 1 | J18: 0 | M18: Watershed and Ecosystem Function | N18: WETLANDS | O18: SURFACE WATER | P18: CONSERVATION | S18: Conference Proceedings Paper (not abstract) | T18: Izadmehr, M., & Rockne, K. (2018). “Pocket Wetlands” for Nutrient Removal in Tile-Drained Agriculture. | U18: https://doi.org/10.1061/9780784481400.038 | V18: 2018 | Z18: Achievement | AA18: Illinois State University | AB18: Recognition in the category of Outstanding Research Promise as the top first year graduate student (2021). | AC18: Alhassan Sahad | AD18: 2021 | AE18: Student
A19: Packman | B19: 10000 | D19: Civil and Environmental Engineering, Mechanical Engineering, Chemical and Biological Engineering | E19: Northwestern University | H19: 2 | I19: 1 | J19: 2 | M19: Water Quality | N19: CLIMATOLOGICAL PROCESSES | O19: WATER QUALITY | P19: NON POINT POLLUTION | S19: Thesis/Dissertation | T19: Cohen, D. B. (2018). MICROBIAL COMMUNITY ASSEMBLY AND HYDROLOGIC VARIABILITY AS CONTROLS ON POTENTIAL DENITRIFICATION RATES IN RESTORED FRESHWATER WETLANDS | U19: https://hdl.handle.net/2142/101669 | V19: 2018 | Z19: Award | AA19: American Fisheries Society | AB19: Award from the Illinois Chapter of the American Fisheries Society to contribute to this project | AC19: Amy Schneider | AE19: Student | AF19: 500
A20: Peterson | B20: 10000 | D20: Geography, Geology, and the Environment | E20: Illinois State University | H20: 0 | I20: 1 | J20: 1 | M20: Water Quality | N20: AGRICULTURE | O20: NON POINT POLLUTION | P20: NUTRIENTS | S20: Thesis/Dissertation | T20: Tillman, S. C. (2020). WETLAND MITIGATION BANKING IN THE CHICAGO AREA: AN ASSESSMENT OF ECOLOGICAL OUTCOMES AND COMPLIANCE WITH PERFORMANCE STANDARDS | U20: https://hdl.handle.net/2142/109459 | V20: 2020 | Z20: Award | AA20: Illinois Muskie Tournament Trail Fishery Scholarship | AB20: Awarded to undergraduate or graduate students studying fisheries | AC20: Amy Schneider | AD20: 44531 | AE20: Student | AF20: 1000
A21: Lydy | B21: 18915 | D21: Chemical and Biomolecular Science, Zoology | E21: Southern Illinois University | H21: 1 | I21: 0 | J21: 0 | M21: Water Technology and Innovation | N21: SEDIMENTS | O21: METHODS | S21: Journal Article | T21: Gonzalez, L. M. H., Rivera, V. A., Phillips, C. B., Haug, L. A., Hatch, S. L., Yeager, L. E., Chang, H. B., Alvarez, J., Gnaedinger, K. J., Miller, W. M., & Packman, A. I. (2019). Characterization of soil profiles and elemental concentrations reveals deposition of heavy metals and phosphorus in a Chicago-area nature preserve, Gensburg Markham Prairie. JOURNAL OF SOILS AND SEDIMENTS, 19(11), 3817-3831. | U21: https://doi.org/10.1007/s11368-019-02315-5 | V21: 2019 | Z21: Grant | AA21: Illinois AFS | AB21: Larimore Student Research Grant | AC21: Amy Schneider | AD21: 44531 | AE21: Student | AF21: 500 | AG21: For graduate students attending an Illinois college or university to promote research in Illinois fisheries
A22: Angel | B22: 59881 | E22: University of Illinois Urbana-Champaign? James Angel | M22: Water-Related Hazards and Climate Variability | S22: Journal Article | T22: Griffin, J. S., Haug, L. A., Rivera, V. A., Gonzalez, L. M. H., Kelly, J. J., Miller, W. M., Wells, G. F., & Packman, A. I. (2020). Soil hydrology drives ecological niche differentiation in a native prairie microbiome. FEMS MICROBIOLOGY ECOLOGY, 96(1), Article fiz163. | U22: https://doi.org/10.1093/femsec/fiz163 | V22: 2020 | Z22: Grant | AA22: UIUC Department of Natural Resources and Environmental Sciences | AB22: NRES Graduate Research Improvement Grant | AC22: Amy Schneider | AD22: 44652 | AE22: Student | AF22: 4965 | AG22: For outstanding UIUC NRES graduate students conducting research in the department
A23: Totals | B23: =SUM(B16:B22) -> 123464 | H23: =SUM(H16:H22) -> 5 | I23: =SUM(I16:I22) -> 3 | J23: =SUM(J16:J22) -> 3 | S23: Journal Article | T23: Hernandez Gonzalez, L. M., Rivera, V. A., Phillips, C. B., Haug, L. A., Hatch, S. L., Yeager, L. E., Chang, H., Alvarez, J., Gnaedinger, K. J., Miller, W. M., & Packman, A. I. (2019). Characterization of soil profiles and elemental concentrations reveals deposition of heavy metals and phosphorus in a Chicago-area nature preserve, Gensburg Markham Prairie. JOURNAL OF SOILS AND SEDIMENTS, 19(11), 3817-3831. | U23: https://doi.org/10.1007/s11368-019-02315-5 | V23: 2019
A24: 2018 | S24: Journal Article | T24: Kimm, H., Guan, K. Y., Gentine, P., Wu, J., Bernacchi, C. J., Sulman, B. N., Griffis, T. J., & Lin, C. J. (2020). Redefining droughts for the US Corn Belt: The dominant role of atmospheric vapor pressure deficit over soil moisture in regulating stomatal behavior of Maize and Soybean. AGRICULTURAL AND FOREST METEOROLOGY, 287, Article 107930. | U24: https://doi.org/10.1016/j.agrformet.2020.107930 | V24: 2020 | Z24: Grant | AA24: Illinois AFS | AB24: Illinois AFS Travel Grant | AC24: Amy Schneider | AD24: 44958 | AE24: Student | AF24: 500 | AG24: For graduate students attending an Illinois college or university to help provide travel to the Illinois AFS conference
A25: Guan | B25: 10000 | D25: Natural Resources and Environmental Science | E25: University of Illinois | H25: 1 | I25: 0 | J25: 0 | M25: Water Scarcity and Availability | N25: AGRICULTURE | O25: DROUGHT | P25: WATER SUPPLY | S25: Journal Article | T25: Wu, D., Li, R. P., Zhang, F. Y., & Liu, J. (2019). A review on drone-based harmful algae blooms monitoring. ENVIRONMENTAL MONITORING AND ASSESSMENT, 191(4), Article 211. | U25: https://doi.org/10.1007/s10661-019-7365-8 | V25: 2019 | Z25: Award | AA25: University of Illinois Urbana-Champaign Department of Natural Resources and Environmental Sciences | AB25: Graduate student award for research excellence | AC25: Amy Schneider | AD25: 45383 | AE25: Student | AF25: 250 | AG25: Amy is a graduate student solely supported through this 104(g) award.
A26: Li | B26: 9982 | D26: Geography and Environmental Resources | E26: Southern Illinois University | H26: 0 | I26: 0 | J26: 1 | M26: Water Quality | N26: INVASIVE SPECIES | O26: MANAGEMENT AND PLANNING | P26: SURFACE WATER | S26: Journal Article | T26: Candeago, R., Kim, K., Vapnik, H., Cotty, S., Aubin, M., Berensmeier, S., Kushima, A., & Su, X. (2020). Semiconducting Polymer Interfaces for Electrochemically Assisted Mercury Remediation. ACS APPLIED MATERIALS & INTERFACES, 12(44), 49713-49722. | U26: https://doi.org/10.1021/acsami.0c15570 | V26: 2020 | Z26: Award | AB26: Best Student Poster Presentation | AC26: Amy Schneider | AD26: 45323 | AE26: Student | AG26: Award for presentation of research related to this 104(g) project
A27: Liu | B27: 9937 | D27: Civil and Environmental Engineering | E27: Southern Illinois University | H27: 1 | I27: 0 | J27: 0 | M27: Water Quality | N27: GROUNDWATER | O27: AGRICULTURE | P27: TOXIC SUBSTANCES | S27: Journal Article | T27: Kim, K., Medina, P. B., Elbert, J., Kayiwa, E., Cusick, R. D., Men, Y. J., & Su, X. (2020). Molecular Tuning of Redox-Copolymers for Selective Electrochemical Remediation. ADVANCED FUNCTIONAL MATERIALS, 30(52), Article 2004635. | U27: https://doi.org/10.1002/adfm.202004635 | V27: 2020 | Z27: Award | AA27: American Academy for the Advancement of Science | AB27: Elected Fellow recognizing excellence in research with an emphasis on barriers controlling the spread of invasive species | AC27: Cory Suski | AD27: 2024 | AE27: PI
A28: Allen | B28: 10000 | D28: Integrative Biology | E28: University of Illinois Urbana-Champaign | H28: 1 | I28: 0 | J28: 9 | M28: Workforce Development and Water Literacy | N28: WATER SUPPLY | O28: CONSERVATION | S28: Journal Article | T28: Amy E. Schneider, A. J. Esbaugh, Aaron R. Cupp, and C. D. Suski. Silver carp experience metabolic and behavioral changes when exposed to water from the Chicago Area Waterway. Scientific Reports, 14 (2024), 24689. | U28: DOI:10.1038/S41598-024-71442-Y | V28: 2024 | W28: 1 | X28: 1 | Z28: Additional USGS 104g grant ($250,000, expected December 2022) that follows on this research | AA28: David Lampert | AB28: 250000 | AC28: PFAS transport from contaminated areas to surface waters
A29: Totals | B29: =SUM(B25:B28) -> 39919 | H29: =SUM(H25:H28) -> 3 | I29: =SUM(I25:I28) -> 0 | J29: =SUM(J25:J28) -> 10 | S29: Dataset | T29: Schneider, Amy, and Suski, Cory. Dataset: Molecular and physical disturbance of silver carp along the Illinois River gradient. University of Illinois at Urbana-Champaign. | U29: https://doi.org/10.13012/B2IDB-2785696_V1 | V29: 2024 | X29: 1
A30: 2019 | S30: Dataset | T30: Schneider, Amy, and Suski, Cory. Dataset: Acute exposure to water from the Chicago Area Waterway System induces molecular indices of stress and disturbance in silver carp: Implications for deterrence to range expansion. University of Illinois at Urbana-Champaign. | U30: https://doi.org/10.13012/B2IDB-0347483_V1 | V30: 2024 | X30: 1 | Z30: Additional USEPA P3 grants ($100,000 awarded 10/2022) that follow on this research | AA30: David Lampert | AB30: 100000
A31: Stillwell | B31: 10000 | D31: Civil and Environmental Engineering | E31: University of Illinois | H31: 0 | I31: 1 | J31: 0 | M31: Water Technology and Innovation | N31: WATER SUPPLY | O31: MANAGEMENT AND PLANNING | S31: Dataset | T31: Schneider, Amy, Suski, Cory, and Esbaugh, Andrew. Dataset: Silver carp experience metabolic and behavioral changes when exposed to water from the Chicago Area Waterway: Implications for upstream movement. University of Illinois at Urbana-Champaign. | U31: https://doi.org/10.13012/B2IDB-0037727_V1 | V31: 2023 | X31: 1 | Z31: Award | AA31: National Science Foundation | AB31: Competitive Research Experience for Undergraduates Award | AC31: Anne Cooke | AD31: 45017 | AE31: Student | AF31: 6000 | AG31: Undergraduate student assisted with field work over the summer in part to try to accomplish project goals in absence of the PhD student whose research was supposed to be supported by project funds
A32: Su | B32: 10000 | D32: Chemical and Biomolecular Engineering | E32: University of Illinois | H32: 1 | I32: 0 | J32: 0 | M32: Water Technology and Innovation | N32: AGRICULTURE | O32: TREATMENT | P32: NUTRIENTS | S32: Journal Article | T32: You, H., and Tinoco, R. O. Turbulent coherent flow structures to predict the behavior of particles with low to intermediate Stokes number between submerged obstacles in streams. Water Resources Research, 59 (2023), e2022WR032439. | U32: https://doi.org/10.1029/2022WR032439 | V32: 2023 | W32: 0 | X32: 1 | Z32: Award | AA32: American Chemical Society | AB32: The Satinder Ahuja Award for Young Investigators in Separation Science | AC32: Xiao Su | AD32: 45474 | AE32: CO-PI
A33: Christianson | B33: 9968 | D33: Crop Science | E33: University of Illinois | H33: 2 | I33: 0 | J33: 0 | M33: Water Technology and Innovation | N33: AGRICULTURE | O33: NUTRIENTS | S33: Journal Article | T33: You, H., & Tinoco, R. O. (2022). Prediction model to compute the capture of drifting particles through in-stream obstacles. | V33: 2022
A34: Peterson | B34: 9998 | D34: Geography, Geology, and the Environment | E34: Illinois State University | H34: 0 | I34: 2 | J34: 0 | M34: Water Quality | N34: NITRATE CONTAMINATION | O34: METHODS | P34: SURFACE WATER | S34: Conference Proceedings Paper (not abstract) | T34: You, H., and Tinoco, R. O. Transport and capture of neutrally buoyant particles in streams: Investigating the effect of obstacle configuration. In Proceedings of 39th IAHR World Congress, Granada, Spain, 2022. | U34: https://doi.org/10.3850/IAHR-39WC252171192022349 | V34: 2022 | W34: 0 | X34: 1 | AF34: =SUM(AF4,AF6:AF7,AF9,AF11:AF13,AF17,AF19:AF25,AF31) -> 53215
A35: Totals | B35: =SUM(B31:B34) -> 39966 | H35: =SUM(H31:H34) -> 3 | I35: =SUM(I31:I34) -> 3 | J35: =SUM(J31:J34) -> 0 | S35: Thesis/Dissertation | T35: Hastie, Allisa G. (2022). Opportunities for Non-Potable Water Reuse in the United States based on a Supply-Demand Assessment and Review of State Policies. M.S. thesis, University of Illinois Urbana-Champaign. | U35: Not yet available. | V35: 2022
A36: 2020 | S36: Journal Article | T36: Zhenhui Jin, Fujunzhu Zhao, Yanlin Lei, Yi-Cheng Wang, Hydrogel-based triboelectric devices for energy-harvesting and wearable sensing applications, Nano Energy, 95, 2022, 106988. | U36: https://doi.org/10.1016/j.nanoen.2022.106988 | V36: 2022
A37: Peterson | B37: 9887 | C37: College of Liberal Arts & Sciences | D37: Department of Geography, Geology, and the Environment | E37: Illinois State University | F37: Normal | G37: Illinois | H37: 1 | I37: 0 | J37: 0 | M37: Water Quality | N37: WATER QUALITY | O37: NITRATE CONTAMINATION | P37: GROUNDWATER | S37: Journal Article | T37: Davendra Ramkumar, Aileen Marty, Japhia Ramkumar, Holly Rosencranz, Radhika Vedantham, Modan Goldman, Erin Meyer, Jasia Steinmetz, Amy Weckle, Kelly Bloedorn, and Carl Rosier. Food for thought: Making the case for food produced via regenerative agriculture in the battle against non-communicable chronic diseases (NCDs). One Health, 18 (2024), 100734. | U37: https://doi.org/10.1016/j.onehlt.2024.100734 | V37: 2024 | W37: 0 | X37: 2
A38: Lei Zhao | B38: 10000 | C38: Grainger College of Engineering | D38: Civil and Environmental Engineering | E38: University of Illinois Urbana-Champaign | F38: Urbana-Champaign | G38: Illinois | H38: 0 | I38: 0 | J38: 2 | M38: Water Technology and Innovation | N38: CLIMATOLOGICAL PROCESSES | O38: HYDROLOGY | P38: FLOODS | S38: Thesis/Dissertation | T38: Manwatkar, Prashik. Per- and Polyfluoroalkyl Substances Fate and Transport in Sediments, Sand, and Adsorbent Media, Thesis, Illinois Institute of Technology. | U38: https://repository.iit.edu/islandora/object/islandora%3A1024904 | V38: 2022 | W38: 0 | X38: 1
A39: Deal | B39: 10000 | C39: College of Fine & Applied Arts | D39: Landscape Architecture | E39: University of Illinois Urbana-Champaign | F39: Urbana-Champaign | G39: Illinois | H39: 1 | I39: 0 | J39: 0 | M39: Water Policy, Planning, and Socioeconomics | N39: CLIMATOLOGICAL PROCESSES | O39: MODELS | P39: HYDROLOGY | S39: Tool | T39: MODFLOW 6: USGS Modular Hydrologic Model (Version 6.5.0). | U39: https://www.usgs.gov/software/modflow-6-usgs-modular-hydrologic-model | V39: 2024 | W39: 4 | X39: 1
A40: Guan | B40: 10000 | C40: College of Agricultural, Consumer and Environmental Sciences | D40: Natural Resources & Environmental Sciences | E40: University of Illinois Urbana-Champaign | F40: Urbana-Champaign | G40: Illinois | H40: 1 | I40: 0 | J40: 0 | M40: Water Scarcity and Availability | N40: CLIMATOLOGICAL PROCESSES | O40: AGRICULTURE | P40: MODELS | S40: Journal Article | T40: Zonga, Y., Heb, Q.-Z., & Tartakovsky, A. M. (2023). Improved training of physics-informed neural networks for parabolic differential equations with sharply perturbed initial conditions. Computer Methods in Applied Mechanics and Engineering 414 (2023), 116125. | U40: https://doi.org/10.1016/j.cma.2023.116125 | V40: 2023 | W40: 0 | X40: 1
A41: Linduo Zhao | B41: 9988 | C41: Prairie Research Institute | D41: Illinois Sustainable Technology Center | E41: University of Illinois Urbana-Champaign | F41: Urbana-Champaign | G41: Illinois | H41: 0 | I41: 1 | J41: 0 | M41: Water Technology and Innovation | N41: GROUNDWATER | O41: WATER QUALITY | S41: Journal Article | T41: Yeung, Y.-H., Barajas-Solano, D. A., & Tartakovsky, A. M. (2023). Gaussian process regression and conditional Karhunen-Loéve models for data assimilation in inverse problems. Journal of Computational Physics. | U41: https://arxiv.org/abs/2301.11279 | V41: 2023
A42: Suski | B42: 240624 | C42: College of Agricultural, Consumer and Environmental Sciences | D42: Natural Resources & Environmental Sciences | E42: University of Illinois Urbana-Champaign | F42: Urbana-Champaign | G42: Illinois | H42: 0 | I42: 1 | J42: 2 | K42: 0 | L42: 0 | M42: Watershed and Ecosystem Function | N42: AQUATIC INVASIVE SPECIES | O42: WASTEWATER | P42: ECOLOGY | S42: Journal Article | T42: Tartakovsky, A., Wang, Y., McCreight, J., Hughes, J., Fienen, M. Karhunen-Loeve–Deep Neural Network surrogate models for forward modeling and parameter estimation in groundwater models. | V42: 2023
A43: Totals | B43: =SUM(B37:B42) -> 290499 | H43: =SUM(H37:H42) -> 3 | I43: =SUM(I37:I42) -> 2 | J43: =SUM(J37:J42) -> 4 | K43: =SUM(K37:K42) -> 0 | L43: =SUM(L37:L42) -> 0 | S43: Tool | T43: Physics-informed neural network (PINN) code for parameter estimation in groundwater models using pressure and tracer concentration measurements. | U43: https://doi.org/10.1016/j.cma.2023.116125 | V43: 2023
A44: 2021 | S44: Tool | T44: CKLEMAP code for parameter estimation in large-scale groundwater models based on the reduced-order conditional Karhunen-Loeve representation of parameter. | U44: https://arxiv.org/abs/2301.11279 | V44: 2023
A45: Stillwell | B45: 10000 | C45: Grainger College of Engineering | D45: Civil and Environmental Engineering | E45: University of Illinois Urbana-Champaign | F45: Urbana-Champaign | G45: Illinois | H45: 0 | I45: 1 | J45: 1 | M45: Water Scarcity and Availability | N45: WATER SUPPLY | O45: LAW, INSTITUTIONS, AND POLICY | P45: MANAGEMENT AND PLANNING | S45: Tool | T45: KL-DNN code for surrogate modeling and parameter estimation in groundwater models based on the reduced-order Karhunen-Loeve representation of parameter and hydraulic head fields and a deep neural network map between the reduced spaces of parameters (e.g., conductivity) and hydraulic head. | U45: This code is described in the “Karhunen-Loeve–Deep Neural Network surrogate models for forward modeling and parameter estimation in groundwater models.” | V45: 2023
A46: Kim | B46: 10000 | C46: Prairie Research Institute | D46: Illinois Sustainable Technology Center | E46: University of Illinois Urbana-Champaign | F46: Urbana-Champaign | G46: Illinois | H46: 0 | I46: 1 | J46: 0 | M46: Water Technology and innovation | N46: TOXIC SUBSTANCES | O46: TREATMENT | P46: WATER QUALITY | S46: Tool | T46: KL-DNN code for surrogate modeling and parameter estimation in groundwater models based on the reduced-order Karhunen-Loeve representation of parameter and hydraulic head fields and a deep neural network map between the reduced spaces of parameters (e.g., conductivity) and hydraulic head. | U46: This code is described in the “Karhunen-Loeve–Deep Neural Network surrogate models for forward modeling and parameter estimation in groundwater models.” | V46: 2023
A47: Rhoads | B47: 9500 | C47: College of Liberal Arts & Sciences | D47: Geography and Geographic Information Science | E47: University of Illinois Urbana-Champaign | F47: Urbana-Champaign | G47: Illinois | H47: 1 | I47: 0 | J47: 0 | M47: Water-Related Hazards and Climate Variability | N47: GEOMORPOLOGICAL PROCESSES | O47: FLOODS | P47: HYDROLOGY | S47: Journal Article | T47: Yu-Hong Yeung, David A. Barajas-Solano, and Alexandre M. Tartakovsky. Gaussian process regression and conditional Karhunen-Loève models for data assimilation in inverse problems. Journal of Computational Physics, 502 (2024), 112788. | U47: https://www.sciencedirect.com/science/article/pii/S0021999124000378 | V47: 2024 | W47: 0 | X47: 0
A48: Stumpf | B48: 27622 | C48: Prairie Research Institute | D48: Illinois State Geological Survey | E48: University of Illinois Urbana-Champaign | F48: Urbana-Champaign | G48: Illinois | M48: Water Technology and Innovation | S48: Journal Article | T48: Yuanzhe Wang, Yifei Zong, James L. McCreight, Joseph D. Hughes, and Alexandre M. Tartakovsky. Bayesian reduced-order deep learning surrogate model for dynamic systems described by partial differential equations. Computer Methods in Applied Mechanics and Engineering, 429 (2024), 117147. | U48: https://doi.org/10.1016/j.cma.2024.117147 | V48: 2024 | W48: 3 | X48: 1
A49: Wang | B49: 9999 | C49: College of Agricultural, Consumer and Environmental Sciences | D49: Food Science & Human Nutrition | E49: University of Illinois Urbana-Champaign | F49: Urbana-Champaign | G49: Illinois | H49: 1 | I49: 2 | J49: 0 | M49: Water Quality | N49: WATER QUALITY | S49: Tool | T49: Software tool: KL-DNN code for surrogate modeling and parameter estimation in groundwater models, based on the reduced-order Karhunen–Loève representation of parameter and hydraulic head fields and a deep neural network map between the reduced spaces of parameters (e.g., conductivity) and hydraulic head | U49: This code is described in the paper “Karhunen–Loève deep neural network surrogate models for forward modeling and parameter estimation in groundwater models,” which is currently in preparation. | V49: 2023, complet but no weblink | W49: 3 | X49: 1
A50: Meyer | B50: 5000 | C50: Non-Profit | D50: Basil's Harvest | E50: Not for profit | F50: Chicago | G50: Illinois | H50: 0 | I50: 0 | J50: 0 | M50: Water-Related Hazards and Climate Variability | N50: AGRICULTURE | O50: EDUCATION | P50: METHODS | S50: Journal Article | T50: N. Kim, A. Aguda, C. Kim, and X. Su, Integrating redox-electrodialysis and electrosorption for the removal of ultra-short- to long-chain PFAS, Nature Communications, 15 (2024), 8321. | U50: https://doi.org/10.1038/s41467-024-52630-w | V50: 2024 | W50: 0 | X50: 2
A51: Lampert | B51: 10000 | C51: Armour College of Engineering | D51: Civil, Architectural, and Environmental Engineering | E51: Illinois Institute of Technology | F51: Chicago | G51: Illinois | H51: 1 | I51: 1 | J51: 0 | M51: Water Quality | N51: SURFACE WATER | O51: WASTEWATER | P51: PHOSPHORUS
A52: Tinoco | B52: 238013 | C52: Grainger College of Engineering | D52: Civil and Environmental Engineering | E52: University of Illinois Urbana-Champaign | F52: Urbana-Champaign | G52: Illinois | H52: 4 | I52: 0 | J52: 0 | M52: Watershed and Ecosystem Function | N52: AQUATIC INVASIVE SPECIES | O52: CONSERVATION | P52: ECOLOGY
A53: Totals | B53: =SUM(B45:B52) -> 320134 | H53: =SUM(H45:H52) -> 7 | I53: =SUM(I45:I52) -> 5 | J53: =SUM(J45:J52) -> 1 | K53: =SUM(K45:K52) -> 0 | L53: =SUM(L45:L52) -> 0
A54: 2022
A55: Lampert | B55: 20000 | C55: Armour College of Engineering | D55: Civil, Architectural, and Environmental Engineering | E55: Illinois Institute of Technology | H55: 2 | I55: 0 | J55: 1 | M55: Water Quality | N55: SURFACE WATER | O55: WASTEWATER | P55: PHOSPHORUS
A56: Rhoads | B56: 9700 | C56: College of Liberal Arts & Sciences | D56: Geography and Geographic Information Science | E56: University of Illinois Urbana-Champaign | F56: Urbana-Champaign | G56: Illinois | H56: 2 | I56: 0 | J56: 1 | M56: Water Quality | N56: SEDIMENTS | O56: SURFACE WATER | P56: GEOCHEMICAL PROCESSES
A57: Sankaran | B57: 9999 | C57: Grainger College of Engineering | D57: Nuclear, Plasma & Radiological Engineering | E57: University of Illinois Urbana-Champaign | F57: Urbana-Champaign | G57: Illinois | H57: 1 | I57: 0 | J57: 1 | M57: Water Technology and innovation | N57: AGRICULTURE | O57: ATMOSPHERIC DEPOSITION | P57: CONSERVATION
A58: Caceres | B58: 10000 | C58: College of Liberal Arts & Sciences | D58: School of Integrative Biology | E58: University of Illinois Urbana-Champaign | F58: Urbana-Champaign | G58: Illinois | H58: 1 | I58: 0 | J58: 0 | M58: Water Quality | N58: NONPOINT POLLUTION | O58: ECOLOGY | P58: SURFACE WATER
A59: Parkos | B59: 122318 | C59: Prairie Research Institute | D59: Illinois Natural History Survey | E59: University of Illinois Urbana-Champaign | F59: Urbana-Champaign | G59: Illinois | H59: 0 | I59: 1 | J59: 0 | L59: 1 | M59: Watershed and Ecosystem Function | N59: AQUATIC INVASIVE SPECIES | O59: HYDROLOGY | P59: ECOLOGY
A60: Lampert | B60: 250000 | C60: Armour College of Engineering | D60: Civil, Architectural, and Environmental Engineering | E60: Illinois Institute of Technology | F60: Chicago | G60: Illinois | H60: 2 | I60: 0 | J60: 1 | K60: 0 | L60: 3 | M60: Water Quality | N60: PFAS | O60: SEDIMENTS | P60: MODELS
A61: Lin | B61: 200000 | C61: Prairie Research Institute | D61: Illinois State Geological Survey | E61: University of Illinois Urbana-Champaign | F61: Urbana-Champaign | G61: Illinois | H61: 1 | I61: 0 | J61: 0 | K61: 0 | L61: 1 | M61: Water Technology and innovation | N61: MODELS | O61: GROUNDWATER | P61: METHODS
A62: Corush | B62: 300000 | C62: Prairie Research Institute | D62: Illinois Natural History Survey | E62: University of Illinois Urbana-Champaign | F62: Urbana-Champaign | G62: Illinois | H62: 1 | I62: 0 | J62: 7 | K62: 1 | L62: 8 | M62: Watershed and Ecosystem Function | N62: AQUATIC INVASIVE SPECIES | O62: CONSERVATION | P62: ECOLOGY
A63: Tartakovsky | B63: 200000 | C63: Grainger College of Engineering | D63: Civil and Environmental Engineering | E63: University of Illinois Urbana-Champaign | F63: Urbana-Champaign | G63: Illinois | H63: 2 | I63: 0 | J63: 0 | K63: 0 | L63: 2 | M63: Water Scarcity and Availability | N63: GROUNDWATER | O63: METHODS | P63: MODELS
A64: Totals | B64: =SUM(B55:B63) -> 1122017 | H64: =SUM(H55:H63) -> 12 | I64: =SUM(I55:I63) -> 1 | J64: =SUM(J55:J63) -> 11 | K64: =SUM(K55:K63) -> 1 | L64: =SUM(L55:L63) -> 15
A65: 2023
A66: Taylor | B66: 15141 | C66: Prairie Research Institute | D66: Illinois Natural History Survey | E66: University of Illinois Urbana-Champaign | F66: Urbana-Champaign | G66: Illinois | H66: 1 | I66: 2 | J66: 0 | K66: 0 | M66: Watershed and Ecosystem Function | N66: AQUATIC INVASIVE SPECIES | O66: CONSERVATION | P66: ECOLOGY
A67: Su | B67: 15000 | C67: College of Liberal Arts & Sciences | D67: Chemical and Biomolecular Engineering | E67: University of Illinois Urbana-Champaign | F67: Urbana-Champaign | G67: Illinois | H67: 1 | I67: 0 | J67: 0 | K67: 0 | L67: 3 | M67: Water Quality | N67: PFAS | O67: SURFACE WATER | P67: PFAS
A68: Prada | B68: 14998 | C68: Prairie Research Institute | D68: Illinois Sustainable Technology Center | E68: University of Illinois Urbana-Champaign | F68: Urbana-Champaign | G68: Illinois | H68: 0 | I68: 0 | J68: 2 | K68: 0 | L68: 2 | M68: Water Quality | N68: PFAS | O68: TREATMENT | P68: TOXIC SUBSTANCES
A69: Li | B69: 15000 | C69: College of Agricultural, Life, and Physical Sciences | D69: School of Earth Systems and Sustainability | E69: Southern Illinois University Carbondale | F69: Carbondale | G69: Illinois | H69: 0 | I69: 1 | J69: 0 | K69: 0 | L69: 1 | M69: Water Scarcity and Availability | N69: WATER SUPPLY | O69: HYDROLOGY | P69: SURFACE WATER
A70: Totals | B70: =SUM(B66:B69) -> 60139 | H70: =SUM(H66:H69) -> 2 | I70: =SUM(I66:I69) -> 3 | J70: =SUM(J66:J69) -> 2 | K70: =SUM(K66:K69) -> 0 | L70: =SUM(L66:L69) -> 6
A71: 2024
A72: Stillwell | B72: 15000 | C72: Grainger College of Engineering | D72: Civil and Environmental Engineering | E72: University of Illinois Urbana-Champaign | F72: Urbana-Champaign | G72: Illinois | M72: Water-Related Hazards and Climate Variability
A73: Park | B73: 15000 | C73: Prairie Research Institute | D73: Illinois Sustainable Technology Center | E73: University of Illinois Urbana-Champaign | F73: Urbana-Champaign | G73: Illinois | M73: Water Quality
A74: Sloan | B74: 15000 | C74: National Great Rivers Research and Education Center | D74: National Great Rivers Research and Education Center | E74: Lewis and Clark Community College | F74: East Alton | G74: Illinois | M74: Water Quality
A75: Li | B75: 15000 | C75: College of Agricultural, Life, and Physical Sciences | D75: School of Earth Systems and Sustainability | E75: Southern Illinois University Carbondale | F75: Carbondale | G75: Illinois | M75: Watershed and Ecosystem Function
A76: Totals | B76: =SUM(B72:B75) -> 60000 | H76: =SUM(H72:H75) -> 0 | I76: =SUM(I72:I75) -> 0 | J76: =SUM(J72:J75) -> 0

Sheet 2025 Calculations
B1: 2015-2024 | C1: Since 2016 | D1: Since 2017 | E1: Since 2018 | F1: Since 2019 | G1: Since 2020 | H1: Since 2021 | I1: Since 2022
A2: Amount of funds managed | B2: =SUM('2025 data'!B7,'2025 data'!B14,'2025 data'!B23,'2025 data'!B29,'2025 data'!B35,'2025 data'!B43,'2025 data'!B53,'2025 data'!B64,'2025 data'!B70,'2025 data'!B76) -> 6702076 | C2: =B2-'2025 data'!B7 -> 6427179 | D2: =C2-'2025 data'!B14 -> 2056138 | E2: =D2-'2025 data'!B23 -> 1932674 | F2: =E2-'2025 data'!B29 -> 1892755 | G2: =F2-'2025 data'!B35 -> 1852789 | H2: =G2-'2025 data'!B43 -> 1562290 | I2: =H2-'2025 data'!B53 -> 1242156
A3: Total funds managed | B3: 55 | C3: 51 | D3: 46 | E3: 39 | F3: 35 | G3: 31 | H3: 25 | I3: 17
A4: Average amount per award | B4: =B2/B3 -> 121855.93 | C4: =C2/C3 -> 126023.12 | D4: =D2/D3 -> 44698.652 | E4: =E2/E3 -> 49555.744 | F4: =F2/F3 -> 54078.714 | G4: =G2/G3 -> 59767.387 | H4: =H2/H3 -> 62491.6 | I4: =I2/I3 -> 73068
A5: Number of PhD students supported | B5: =SUM('2025 data'!H7,'2025 data'!H14,'2025 data'!H23,'2025 data'!H29,'2025 data'!H35,'2025 data'!H43,'2025 data'!H53,'2025 data'!H64,'2025 data'!H70,'2025 data'!H76) -> 39 | C5: =B5-'2025 data'!H7 -> 37 | D5: =C5-'2025 data'!H14 -> 35 | E5: =D5-'2025 data'!H23 -> 30 | F5: =E5-'2025 data'!H29 -> 27 | G5: =F5-'2025 data'!H35 -> 24 | H5: =G5-'2025 data'!H43 -> 21 | I5: =H5-'2025 data'!H53 -> 14
A6: Number of MS students supported | B6: =SUM('2025 data'!I7,'2025 data'!I14,'2025 data'!I23,'2025 data'!I29,'2025 data'!I35,'2025 data'!I43,'2025 data'!I53,'2025 data'!I64,'2025 data'!I70,'2025 data'!I76) -> 24 | C6: =B6-'2025 data'!I7 -> 22 | D6: =C6-'2025 data'!I14 -> 17 | E6: =D6-'2025 data'!I23 -> 14 | F6: =E6-'2025 data'!I29 -> 14 | G6: =F6-'2025 data'!I35 -> 11 | H6: =G6-'2025 data'!I43 -> 9 | I6: ='2025 Calculations'!H6-'2025 data'!I53 -> 4
A7: Number of Undergrads supported | B7: =SUM('2025 data'!J7,'2025 data'!J14,'2025 data'!J23,'2025 data'!J29,'2025 data'!J35,'2025 data'!J43,'2025 data'!J53,'2025 data'!J64,'2025 data'!J70,'2025 data'!J76) -> 49 | C7: =B7-'2025 data'!J7 -> 46 | D7: =C7-'2025 data'!J14 -> 31 | E7: =D7-'2025 data'!J23 -> 28 | F7: =E7-'2025 data'!J29 -> 18 | G7: =F7-'2025 data'!J35 -> 18 | H7: =G7-'2025 data'!J43 -> 14 | I7: =H7-'2025 data'!J53 -> 13
A8: Number of Postdocs supported | B8: no data | C8: no data | D8: no data | E8: no data | F8: no data | G8: no data | H8: no data | I8: =SUM('2025 data'!K64,'2025 data'!K70) -> 1
A9: Diversity, Equity, Inclusion and Justice students served | B9: no data | C9: no data | D9: no data | E9: no data | F9: no data | G9: no data | H9: no data | I9: =SUM('2025 data'!L64,'2025 data'!L70) -> 21
A10: Journal Articles | B10: 31 | C10: 31 | D10: 30 | E10: 30 | F10: 25 | G10: 17 | H10: 11 | I10: 11
A11: Conference Proceedings Paper (not abstract) | B11: 2 | C11: 2 | D11: 2 | E11: 2 | F11: 1 | G11: 1 | H11: 1 | I11: 1
A12: Thesis/Dissertations | B12: 7 | C12: 7 | D12: 7 | E12: 6 | F12: 4 | G12: 3 | H12: 2 | I12: 2
A13: Datasets | B13: no data | C13: no data | D13: no data | E13: no data | F13: no data | G13: no data | H13: no data | I13: 3
A14: Tools | B14: no data | C14: no data | D14: no data | E14: no data | F14: no data | G14: no data | H14: no data | I14: 6
B17: 2015 | C17: 2016 | D17: 2017 | E17: 2018 | F17: 2019 | G17: 2020 | H17: 2021 | I17: 2022 | J17: 2023 | K17: 2024
A18: Amount of new awards managed by year | B18: ='2025 data'!B7 -> 274897 | C18: ='2025 data'!B14 -> 4371041 | D18: ='2025 data'!B23 -> 123464 | E18: ='2025 data'!B29 -> 39919 | F18: ='2025 data'!B35 -> 39966 | G18: ='2025 data'!B43 -> 290499 | H18: ='2025 data'!B53 -> 320134 | I18: ='2025 data'!B64 -> 1122017 | J18: ='2025 data'!B70 -> 60139 | K18: ='2025 data'!B76 -> 60000
A19: Average funding 2015-2024 | B19: =AVERAGE(B18:K18) -> 670207.6
A20: Average funding 2016-2024 | B20: =AVERAGE(C18:K18) -> 714131
A21: Average funding 2017-2024 | B21: =AVERAGE(D18:K18) -> 257017.25
A22: Average funding 2018-2024 | B22: =AVERAGE(E18:K18) -> 276096.29
A23: Average funding 2019-2024 | B23: =AVERAGE(F18:K18) -> 315459.17
A24: Average funding 2020-2024 | B24: =AVERAGE(G18:K18) -> 370557.8
A25: Average funding 2021-2024 | B25: =AVERAGE(H18:K18) -> 390572.5
A26: Average funding 2022-2024 | B26: =AVERAGE(I18:K18) -> 414052
A35: WRRI Science Priorities | B35: Since 2015 | C35: Since 2016 | D35: Since 2017 | E35: Since 2018 | F35: Since 2019 | G35: Since 2020 | H35: Since 2021 | I35: Since 2022
A36: Water Quality | B36: 20 | C36: 18 | D36: 16 | E36: 14 | F36: 12 | G36: 11 | H36: 10 | I36: 8
A37: Watershed and Ecosystem Function | B37: 10 | C37: 9 | D37: 8 | E37: 6 | F37: 6 | G37: 6 | H37: 5 | I37: 4
A38: Water Scarcity and Availability | G38: 4
A39: Water Policy, Planning, and Socioeconomics | B39: 2 | C39: 2 | D39: 2 | E39: 1 | F39: 1 | G39: 1 | H39: 0 | I39: 0
A40: Water Technology and Innovation | B40: 10 | C40: 10 | D40: 10 | E40: 9 | F40: 9 | G40: 6 | H40: 4 | I40: 2
A41: Workforce Development and Water Literacy | B41: 2 | C41: 2 | D41: 1 | E41: 1 | F41: 0 | G41: 0 | H41: 0 | I41: 0
A42: Water-Related Hazards and Climate Variability | G42: 3
B43: =SUM(B36:B42) -> 44 | C43: =SUM(C36:C42) -> 41 | D43: =SUM(D36:D42) -> 37 | E43: =SUM(E36:E42) -> 31 | F43: =SUM(F36:F42) -> 28 | G43: =SUM(G36:G42) -> 31 | H43: =SUM(H36:H42) -> 19 | I43: =SUM(I36:I42) -> 14
B49: MODELS
B50: WETLANDS
B51: CLIMATOLOGICAL PROCESSES
B52: NON POINT POLLUTION
B53: HYDROLOGY
B54: MANAGEMENT AND PLANNING
B55: AGRICULTURE
B56: WETLANDS
B57: CLIMATOLOGICAL PROCESSES
B58: AGRICULTURE
B59: SEDIMENTS
B60: AGRICULTURE
... B176: SURFACE WATER

Sheet Sheet1
C1: 2020 | D1: Institution | E1: City | F1: State
A2: 9987 | B2: College of Liberal Arts & Sciences | C2: Department of Geography, Geology, and the Environment | D2: Illinois State University | E2: Normal | F2: Illinois | AF2: Award Amount | AG2: College
A3: 10000 | B3: Grainger College of Engineering | C3: Civil and Environmental Engineering | D3: University of Illinois Urbana-Champaign | E3: Urbana-Champaign | F3: Illinois | M3: Illinois State University | N3: 1 | O3: 0.04 | P3: nutrient | Q3: =1/N24 -> 0.038461538 | R3: Illinois State University | W3: Department of Geography, Geology, and the Environment | X3: 2 | Y3: agricultural | Z3: University of Illinois Urbana-Champaign | AA3: Natural Resources & Environmental Sciences | AC3: term | AD3: dept | AF3: 10000 | AG3: Armour College of Engineering | AH3: Illinois Institute of Technology | AI3: =SUM(AF3:AF5) -> 280000 | AJ3: =AI3/$AF$34 -> 0.15112352 | AO3: Armour College of Engineering | AP3: 280000 | AQ3: =AP3/$AF$34 -> 0.15112352
A4: 10000 | B4: College of Fine & Applied Arts | C4: Landscape Architecture | D4: University of Illinois Urbana-Champaign | E4: Urbana-Champaign | F4: Illinois | M4: University of Illinois Urbana-Champaign | N4: 20 | O4: 0.08 | P4: agricultural | Q4: 0.04 | R4: University of Illinois Urbana-Champaign | W4: Natural Resources & Environmental Sciences | AA4: Geography and Geographic Information Science | AC4: mississippi | AD4: Civil and Environmental Engineering | AF4: 20000 | AG4: Armour College of Engineering | AO4: College of Agricultural, Consumer and Environmental Sciences | AP4: 260623 | AQ4: =AP4/$AF$34 -> 0.14066523
A5: 10000 | B5: College of Agricultural, Consumer and Environmental Sciences | C5: Natural Resources & Environmental Sciences | D5: University of Illinois Urbana-Champaign | E5: Urbana-Champaign | F5: Illinois | M5: University of Illinois Urbana-Champaign | N5: 20 | P5: agricultural | Q5: 0.04 | R5: University of Illinois Urbana-Champaign | W5: Geography and Geographic Information Science | X5: 1 | Y5: agricultural | Z5: Not for profit | AA5: Basil's Harvest | AC5: modeling | AD5: Civil and Environmental Engineering | AF5: 250000 | AG5: Armour College of Engineering | AO5: College of Agricultural, Life, and Physical Sciences | AP5: 30000 | AQ5: =AP5/$AF$34 -> 0.016191806
A6: 9988 | B6: Prairie Research Institute | C6: Illinois Sustainable Technology Center | D6: University of Illinois Urbana-Champaign | E6: Urbana-Champaign | F6: Illinois | M6: University of Illinois Urbana-Champaign | N6: 20 | O6: 0.08 | P6: energy | Q6: 0.04 | R6: University of Illinois Urbana-Champaign | W6: Food Science & Human Nutrition | X6: 2 | Y6: energy | Z6: University of Illinois Urbana-Champaign | AA6: Food Science & Human Nutrition | AC6: modeling | AD6: Civil and Environmental Engineering | AF6: 10000 | AG6: College of Agricultural, Consumer and Environmental Sciences | AH6: University of Illinois Urbana-Champaign | AI6: =SUM(AF6:AF8) -> 260623 | AJ6: =AI6/$AF$34 -> 0.14066523 | AO6: College of Fine & Applied Arts | AP6: 10000 | AQ6: =AP6/$AF$34 -> 0.0053972687
A7: 240624 | B7: College of Agricultural, Consumer and Environmental Sciences | C7: Natural Resources & Environmental Sciences | D7: University of Illinois Urbana-Champaign | E7: Urbana-Champaign | F7: Illinois | G7: =1/26 -> 0.038461538 | H7: Illinois State University | M7: University of Illinois Urbana-Champaign | N7: 20 | P7: energy | Q7: 0.04 | R7: University of Illinois Urbana-Champaign | W7: Illinois State Geological Survey | AA7: Illinois State Geological Survey | AC7: stormwater | AD7: Civil and Environmental Engineering | AF7: 240624 | AG7: College of Agricultural, Consumer and Environmental Sciences | AO7: College of Liberal Arts & Sciences | AP7: 54087 | AQ7: =AP7/$AF$34 -> 0.029192207
G8: =16/20 -> 0.8 | H8: University of Illinois Urbana-Champaign | M8: University of Illinois Urbana-Champaign | N8: 20 | O8: 0.08 | P8: groundwater | Q8: 0.04 | R8: University of Illinois Urbana-Champaign | W8: Illinois Sustainable Technology Center | X8: 2 | Y8: groundwater | Z8: University of Illinois Urbana-Champaign | AA8: Illinois Sustainable Technology Center | AC8: energy | AD8: Food Science & Human Nutrition | AF8: 9999 | AG8: College of Agricultural, Consumer and Environmental Sciences | AO8: Grainger College of Engineering | AP8: 483012 | AQ8: =AP8/$AF$34 -> 0.26069455
C9: 2021 | G9: 0.04 | H9: Basil's Harvest | M9: University of Illinois Urbana-Champaign | N9: 20 | P9: groundwater | Q9: 0.04 | R9: University of Illinois Urbana-Champaign | W9: Illinois State Geological Survey | AA9: Illinois State Geological Survey | AC9: agricultural | AD9: Geography and Geographic Information Science | AF9: 15000 | AG9: College of Agricultural, Life, and Physical Sciences | AH9: Southern Illinois University | AI9: =SUM(AF9:AF10) -> 30000 | AJ9: =AI9/$AF$34 -> 0.016191806 | AO9: Non-Profit Organization | AP9: 5000 | AQ9: =AP9/$AF$34 -> 0.0026986343
A10: 10000 | B10: Grainger College of Engineering | C10: Civil and Environmental Engineering | D10: University of Illinois Urbana-Champaign | E10: Urbana-Champaign | F10: Illinois | G10: =2/26 -> 0.076923077 | H10: Illinois Institute of Technology | M10: University of Illinois Urbana-Champaign | N10: 20 | O10: 0.12 | P10: hydrology | Q10: 0.04 | R10: University of Illinois Urbana-Champaign | W10: Geography and Geographic Information Science | X10: 3 | Y10: hydrology | Z10: University of Illinois Urbana-Champaign | AA10: Geography and Geographic Information Science | AC10: hydrology | AD10: Geography and Geographic Information Science | AF10: 15000 | AG10: College of Agricultural, Life, and Physical Sciences | AO10: Prairie Research Institute | AP10: 850067 | AQ10: =AP10/$AF$34 -> 0.458804
A11: 10000 | B11: Prairie Research Institute | C11: Illinois Sustainable Technology Center | D11: University of Illinois Urbana-Champaign | E11: Urbana-Champaign | F11: Illinois | G11: 0.04 | H11: Southern Illinois University Carbondale | M11: University of Illinois Urbana-Champaign | N11: 20 | P11: hydrology | Q11: 0.04 | R11: University of Illinois Urbana-Champaign | W11: School of Integrative Biology | AA11: School of Integrative Biology | AC11: hydrology | AD11: Illinois Natural History Survey | AF11: 10000 | AG11: College of Fine & Applied Arts | AH11: University of Illinois Urbana-Champaign | AI11: =SUM(AF11) -> 10000 | AJ11: =AI11/$AF$34 -> 0.0053972687 | AQ11: =SUM(AQ3:AQ10) -> 1.0647672
A12: 9500 | B12: College of Liberal Arts & Sciences | C12: Geography and Geographic Information Science | D12: University of Illinois Urbana-Champaign | E12: Urbana-Champaign | F12: Illinois | M12: University of Illinois Urbana-Champaign | N12: 20 | P12: hydrology | Q12: 0.04 | R12: University of Illinois Urbana-Champaign | W12: Illinois Natural History Survey | AA12: Illinois Natural History Survey | AC12: invasive | AD12: Illinois Natural History Survey | AF12: 9887 | AG12: College of Liberal Arts & Sciences | AH12: University of Illinois Urbana-Champaign | AI12: =SUM(AF12:AF16) -> 54087 | AJ12: =AI12/$AF$34 -> 0.029192207
A13: 27622 | B13: Prairie Research Institute | C13: Illinois State Geological Survey | D13: University of Illinois Urbana-Champaign | E13: Urbana-Champaign | F13: Illinois | M13: University of Illinois Urbana-Champaign | N13: 20 | O13: 0.12 | P13: invasive | Q13: 0.04 | R13: University of Illinois Urbana-Champaign | W13: Natural Resources & Environmental Sciences | X13: 3 | Y13: invasive | Z13: University of Illinois Urbana-Champaign | AA13: Natural Resources & Environmental Sciences | AC13: energy | AD13: Illinois State Geological Survey | AF13: 9500 | AG13: College of Liberal Arts & Sciences | AO13: Engineering | AP13: =SUM(AF3:AF5,AF17:AF22) -> 763012 | AQ13: =AP13/$AP$18 -> 0.41181808
A14: 9999 | B14: College of Agricultural, Consumer and Environmental Sciences | C14: Food Science & Human Nutrition | D14: University of Illinois Urbana-Champaign | E14: Urbana-Champaign | F14: Illinois | M14: University of Illinois Urbana-Champaign | N14: 20 | P14: invasive | Q14: 0.08 | R14: University of Illinois Urbana-Champaign | W14: Illinois Natural History Survey | AA14: Illinois Natural History Survey | AC14: groundwater | AD14: Illinois State Geological Survey | AF14: 9700 | AG14: College of Liberal Arts & Sciences | AO14: Agricultural, Consumer and Environmental Sciences | AP14: =SUM(AF6:AF10) -> 290623 | AQ14: =AP14/$AP$18 -> 0.15685704
A15: 5000 | B15: Non-Profit | C15: Basil's Harvest | D15: Not for profit | E15: Chicago | F15: Illinois | G15: 0.04 | H15: nutrient | I15: Illinois State University | M15: University of Illinois Urbana-Champaign | N15: 20 | O15: 0.04 | P15: mississippi | Q15: =1/$N$24 -> 0.038461538 | R15: University of Illinois Urbana-Champaign | W15: Civil and Environmental Engineering | X15: 1 | Y15: mississippi | Z15: University of Illinois Urbana-Champaign | AA15: Civil and Environmental Engineering | AC15: groundwater | AD15: Illinois Sustainable Technology Center | AF15: 10000 | AG15: College of Liberal Arts & Sciences | AO15: Arts & Sciences | AP15: =SUM(AF11:AF16) -> 64087 | AQ15: =AP15/$AP$18 -> 0.034589476
A16: 10000 | B16: Armour College of Engineering | C16: Civil, Architectural, and Environmental Engineering | D16: Illinois Institute of Technology | E16: Chicago | F16: Illinois | G16: 0.08 | H16: agricultural | I16: University of Illinois Urbana-Champaign | M16: University of Illinois Urbana-Champaign | N16: 20 | O16: 0.16 | P16: modeling | Q16: 0.04 | R16: University of Illinois Urbana-Champaign | W16: Landscape Architecture | X16: 4 | Y16: modeling | Z16: University of Illinois Urbana-Champaign | AA16: Landscape Architecture | AC16: modeling | AD16: Landscape Architecture | AF16: 15000 | AG16: College of Liberal Arts & Sciences | AO16: Prairie Research Institute | AP16: =SUM(AF23,AF25:AF33) -> 730067 | AQ16: =AP16/$AP$18 -> 0.39403677
A17: 238013 | B17: Grainger College of Engineering | C17: Civil and Environmental Engineering | D17: University of Illinois Urbana-Champaign | E17: Urbana-Champaign | F17: Illinois | G17: 0.08 | H17: energy | I17: University of Illinois Urbana-Champaign | M17: University of Illinois Urbana-Champaign | N17: 20 | P17: modeling | Q17: 0.08 | R17: University of Illinois Urbana-Champaign | W17: Civil and Environmental Engineering | AA17: Civil and Environmental Engineering | AC17: agricultural | AD17: Natural Resources & Environmental Sciences | AF17: 10000 | AG17: Grainger College of Engineering | AH17: University of Illinois Urbana-Champaign | AI17: =SUM(AF17:AF22) -> 483012 | AJ17: =AI17/$AF$34 -> 0.26069455 | AL17: University of Illinois Urbana-Champaign | AM17: =SUM(AI6,AI11:AI12,AI17,AI25) -> 1522789 | AN17: =AM17/$AM$22 -> 0.82189013 | AO17: Non-profit organization | AP17: =AF24 -> 5000 | AQ17: =AP17/$AP$18 -> 0.0026986343
C18: 2022 | G18: 0.08 | H18: groundwater | I18: University of Illinois Urbana-Champaign | M18: University of Illinois Urbana-Champaign | N18: 20 | P18: modeling | Q18: 0.04 | R18: University of Illinois Urbana-Champaign | W18: Nuclear, Plasma & Radiological Engineering | AA18: Nuclear, Plasma & Radiological Engineering | AC18: invasive | AD18: Natural Resources & Environmental Sciences | AF18: 10000 | AG18: Grainger College of Engineering | AL18: Illinois Institute of Technology | AM18: =SUM(AI3) -> 280000 | AN18: =AM18/$AM$22 -> 0.15112352 | AP18: =SUM(AP13:AP17) -> 1852789 | AQ18: =SUM(AQ13:AQ17) -> 1
A19: 20000 | B19: Armour College of Engineering | C19: Civil, Architectural, and Environmental Engineering | D19: Illinois Institute of Technology | G19: 0.12 | H19: hydrology | I19: University of Illinois Urbana-Champaign | M19: University of Illinois Urbana-Champaign | N19: 20 | O19: 0.04 | P19: stormwater | Q19: =1/$N$24 -> 0.038461538 | R19: University of Illinois Urbana-Champaign | W19: Civil and Environmental Engineering | AA19: Civil and Environmental Engineering | AC19: modeling | AD19: Nuclear, Plasma & Radiological Engineering | AF19: 238013 | AG19: Grainger College of Engineering | AL19: Southern Illinois University | AM19: =SUM(AI9) -> 30000 | AN19: =AM19/$AM$22 -> 0.016191806
A20: 9700 | B20: College of Liberal Arts & Sciences | C20: Geography and Geographic Information Science | D20: University of Illinois Urbana-Champaign | E20: Urbana-Champaign | F20: Illinois | G20: 0.12 | H20: invasive | I20: University of Illinois Urbana-Champaign | M20: Basil's Harvest | N20: 1 | O20: 0.04 | P20: agricultural | Q20: =1/$N$24 -> 0.038461538 | R20: Basil's Harvest | W20: Not for profit | X20: 1 | Y20: modeling | Z20: Southern Illinois University Carbondale | AA20: School of Earth Systems and Sustainability | AC20: hydrology | AD20: School of Integrative Biology | AF20: 9999 | AG20: Grainger College of Engineering | AL20: Lewis and Clark Community College | AM20: =AF23 -> 15000 | AN20: =AM20/$AM$22 -> 0.008095903
A21: 9999 | B21: Grainger College of Engineering | C21: Nuclear, Plasma & Radiological Engineering | D21: University of Illinois Urbana-Champaign | E21: Urbana-Champaign | F21: Illinois | G21: 0.04 | H21: mississippi | I21: University of Illinois Urbana-Champaign | M21: Illinois Institute of Technology | N21: 3 | O21: 0.04 | P21: nutrient | Q21: =1/$N$24 -> 0.038461538 | R21: Illinois Institute of Technology | W21: Civil, Architectural, and Environmental Engineering | X21: 1 | Y21: nutrient | Z21: Illinois State University | AA21: Department of Geography, Geology, and the Environment | AF21: 200000 | AG21: Grainger College of Engineering | AL21: Basil's Harvest | AM21: =AF24 -> 5000 | AN21: =AM21/$AM$22 -> 0.0026986343
A22: 10000 | B22: College of Liberal Arts & Sciences | C22: School of Integrative Biology | D22: University of Illinois Urbana-Champaign | E22: Urbana-Champaign | F22: Illinois | G22: 0.16 | H22: modeling | I22: University of Illinois Urbana-Champaign | M22: Illinois Institute of Technology | O22: 0.08 | P22: pfas | Q22: =2/N24 -> 0.076923077 | R22: Illinois Institute of Technology | W22: Civil, Architectural, and Environmental Engineering | X22: 1 | Y22: nutrient | Z22: Illinois Institute of Technology | AA22: Civil, Architectural, and Environmental Engineering | AF22: 15000 | AG22: Grainger College of Engineering | AM22: =SUM(AM17:AM21) -> 1852789
A23: 122318 | B23: Prairie Research Institute | C23: Illinois Natural History Survey | D23: University of Illinois Urbana-Champaign | E23: Urbana-Champaign | F23: Illinois | G23: 0.04 | H23: stormwater | I23: University of Illinois Urbana-Champaign | M23: Southern Illinois University Carbondale | N23: 1 | O23: 0.04 | P23: modeling | Q23: =1/$N$24 -> 0.038461538 | R23: Southern Illinois University Carbondale | W23: School of Earth Systems and Sustainability | X23: 3 | Y23: pfas | Z23: University of Illinois Urbana-Champaign | AA23: Illinois Sustainable Technology Center | AF23: 15000 | AG23: National Great Rivers Research and Education Center | AH23: Lewis and Clark Community College
A24: 250000 | B24: Armour College of Engineering | C24: Civil, Architectural, and Environmental Engineering | D24: Illinois Institute of Technology | E24: Chicago | F24: Illinois | G24: 0.04 | H24: agricultural | I24: Basil's Harvest | N24: 26 | Q24: =SUM(Q3:Q23) -> 0.94769231 | AA24: Chemical and Biomolecular Engineering | AF24: 5000 | AG24: Non-Profit Organization | AH24: Basil's Harvest | AI24: =SUM(AF24) -> 5000 | AJ24: =AI24/$AF$34 -> 0.0026986343
A25: 200000 | B25: Prairie Research Institute | C25: Illinois State Geological Survey | D25: University of Illinois Urbana-Champaign | E25: Urbana-Champaign | F25: Illinois | G25: 0.04 | H25: nutrient | I25: Illinois Institute of Technology | M25: Illinois State University | N25: Department of Geography, Geology, and the Environment | AA25: Illinois Sustainable Technology Center | AF25: 9988 | AG25: Prairie Research Institute | AH25: University of Illinois Urbana-Champaign | AI25: =SUM(AF25:AF33) -> 715067 | AJ25: =AI25/$AF$34 -> 0.38594087
A26: 300000 | B26: Prairie Research Institute | C26: Illinois Natural History Survey | D26: University of Illinois Urbana-Champaign | E26: Urbana-Champaign | F26: Illinois | G26: 0.08 | H26: pfas | I26: Illinois Institute of Technology | M26: University of Illinois Urbana-Champaign | N26: Civil and Environmental Engineering | X26: 2 | Y26: pfas | Z26: Illinois Institute of Technology | AA26: Civil, Architectural, and Environmental Engineering | AF26: 10000 | AG26: Prairie Research Institute | AJ26: =SUM(AJ3:AJ25) -> 0.9919041
A27: 200000 | B27: Grainger College of Engineering | C27: Civil and Environmental Engineering | D27: University of Illinois Urbana-Champaign | E27: Urbana-Champaign | F27: Illinois | G27: 0.04 | H27: modeling | I27: Southern Illinois University Carbondale | M27: University of Illinois Urbana-Champaign | N27: Landscape Architecture | X27: 1 | Y27: stormwater | Z27: University of Illinois Urbana-Champaign | AA27: Civil and Environmental Engineering | AF27: 27622 | AG27: Prairie Research Institute
C28: 2023 | M28: University of Illinois Urbana-Champaign | N28: Natural Resources & Environmental Sciences | AF28: 122318 | AG28: Prairie Research Institute
A29: 15141 | B29: Prairie Research Institute | C29: Illinois Natural History Survey | D29: University of Illinois Urbana-Champaign | E29: Urbana-Champaign | F29: Illinois | M29: University of Illinois Urbana-Champaign | N29: Illinois Sustainable Technology Center | AF29: 200000 | AG29: Prairie Research Institute
A30: 15000 | B30: College of Liberal Arts & Sciences | C30: Chemical and Biomolecular Engineering | D30: University of Illinois Urbana-Champaign | E30: Urbana-Champaign | F30: Illinois | M30: University of Illinois Urbana-Champaign | N30: Natural Resources & Environmental Sciences | R30: Institution | S30: Total Institutional Funding | T30: Department | U30: Funding by Department | AF30: 300000 | AG30: Prairie Research Institute | BF30: 0.16 | BG30: Modeling
A31: 14998 | B31: Prairie Research Institute | C31: Illinois Sustainable Technology Center | D31: University of Illinois Urbana-Champaign | E31: Urbana-Champaign | F31: Illinois | R31: Illinois Institute of Technology | S31: 280000 | AF31: 15141 | AG31: Prairie Research Institute | BF31: 0.08 | BG31: Energy | BM31: 0.16 | BN31: Modeling
A32: 15000 | B32: College of Agricultural, Life, and Physical Sciences | C32: School of Earth Systems and Sustainability | D32: Southern Illinois University Carbondale | E32: Carbondale | F32: Illinois | AF32: 14998 | AG32: Prairie Research Institute | CB32: Funding Support Provided by IWRC since 2020
C33: 2024 | M33: University of Illinois Urbana-Champaign | N33: Civil and Environmental Engineering | T33: Civil, Architectural, and Environmental Engineering | U33: =SUM(A16,A19,A24) -> 280000 | AF33: 15000 | AG33: Prairie Research Institute | BV33: 0.16 | BW33: Modeling | BX33: 235000
A34: 15000 | B34: Grainger College of Engineering | C34: Civil and Environmental Engineering | D34: University of Illinois Urbana-Champaign | E34: Urbana-Champaign | F34: Illinois | M34: University of Illinois Urbana-Champaign | N34: Illinois Sustainable Technology Center | R34: Illinois State University | S34: 9987 | T34: Geography, Geology, and the Environment | U34: =A2 -> 9987 | AF34: =SUM(AF3:AF33) -> 1852789 | BV34: 0.08 | BW34: Energy | BX34: 209999 | CA34: Stormwater | CB34: 10000
A35: 15000 | B35: Prairie Research Institute | C35: Illinois Sustainable Technology Center | D35: University of Illinois Urbana-Champaign | E35: Urbana-Champaign | F35: Illinois | M35: University of Illinois Urbana-Champaign | N35: Geography and Geographic Information Science | R35: University of Illinois Urbana-Champaign | S35: =SUM(U35:U45) -> 1512902 | T35: Civil and Environmental Engineering | U35: =SUM(A3,A17,A27,A10,A34) -> 473013 | BV35: 0.08 | BW35: Groundwater | BX35: 23988 | CA35: Agriculture | CB35: 15700
A36: 15000 | B36: National Great Rivers Research and Education Center | C36: National Great Rivers Research and Education Center | D36: Lewis and Clark Community College | E36: East Alton | F36: Illinois | M36: University of Illinois Urbana-Champaign | N36: Illinois State Geological Survey | T36: Illinois Natural History Survey | U36: =SUM(A23,A26,A29) -> 437459 | BV36: 0.12 | BW36: Hydrology | BX36: 120141 | CA36: Groundwater | CB36: 23988
A37: 15000 | B37: College of Agricultural, Life, and Physical Sciences | C37: School of Earth Systems and Sustainability | D37: Southern Illinois University Carbondale | E37: Carbondale | F37: Illinois | M37: University of Illinois Urbana-Champaign | N37: Food Science & Human Nutrition | T37: Natural Resources & Environmental Sciences | U37: =SUM(A5,A7) -> 250624 | BV37: 0.12 | BW37: Invasive species | BX37: 662942 | CA37: Nutrients | CB37: 44987
M38: Not for profit | N38: Basil's Harvest | T38: Illinois State Geological Survey | U38: =+SUM(A13,A25) -> 227622 | BV38: 0.04 | BW38: Mississippi River | BX38: 238013 | CA38: Hydrology | CB38: 135141
M39: Illinois Institute of Technology | N39: Civil, Architectural, and Environmental Engineering | T39: Illinois Sustainable Technology Center | U39: =SUM(A6,A11,A31,A35) -> 49986 | BV39: 0.04 | BW39: Stormwater | BX39: 10000 | CA39: Energy | CB39: 209999
M40: University of Illinois Urbana-Champaign | N40: Civil and Environmental Engineering | T40: Geography and Geographic Information Science | U40: =SUM(A12,A20) -> 19200 | BV40: 0.08 | BW40: Nutrients | BX40: 29987 | CA40: Mississippi River | CB40: 238013
T41: Chemical and Biomolecular Engineering | U41: =A30 -> 15000 | BV41: 0.08 | BW41: PFAs | BX41: 299998 | CA41: Modeling | CB41: 250000
M42: Illinois Institute of Technology | N42: Civil, Architectural, and Environmental Engineering | T42: Landscape Architecture | U42: =A4 -> 10000 | BV42: 0.12 | BW42: Agriculture | BX42: 15700 | CA42: PFAS | CB42: 314998
M43: University of Illinois Urbana-Champaign | N43: Geography and Geographic Information Science | T43: School of Integrative Biology | U43: =A22 -> 10000 | BF43: 0.08 | BG43: Groundwater | BM43: 0.08 | BN43: Energy | BX43: =SUM(BX33:BX42) -> 1845768 | CA43: Invasive Species | CB43: 662942
M44: University of Illinois Urbana-Champaign | N44: Nuclear, Plasma & Radiological Engineering | T44: Food Science & Human Nutrition | U44: =A14 -> 9999 | BF44: 0.12 | BG44: Hydrology | BM44: 0.08 | BN44: Groundwater
M45: University of Illinois Urbana-Champaign | N45: School of Integrative Biology | T45: Nuclear, Plasma & Radiological Engineering | U45: =A21 -> 9999 | BF45: 0.12 | BG45: Invasive species | BM45: 0.12 | BN45: Hydrology
M46: University of Illinois Urbana-Champaign | N46: Illinois Natural History Survey | R46: Southern Illinois University Carbondale | S46: 15000 | T46: School of Earth Systems and Sustainability | U46: =SUM(A32,A37) -> 30000 | BF46: 0.04 | BG46: Mississippi River | BM46: 0.12 | BN46: Invasive species
M47: Illinois Institute of Technology | N47: Civil, Architectural, and Environmental Engineering | BF47: 0.04 | BG47: Stormwater | BM47: 0.04 | BN47: Mississippi River
M48: University of Illinois Urbana-Champaign | N48: Illinois State Geological Survey | BF48: 0.08 | BG48: Nutrients | BM48: 0.04 | BN48: Stormwater
M49: University of Illinois Urbana-Champaign | N49: Illinois Natural History Survey | BF49: 0.08 | BG49: PFAs | BM49: 0.08 | BN49: Nutrients
C50: 7 | D50: illinois | M50: University of Illinois Urbana-Champaign | N50: Civil and Environmental Engineering | BF50: 0.12 | BG50: Agriculture | BM50: 0.08 | BN50: PFAs
C51: 7 | D51: water | BM51: 0.12 | BN51: Agriculture
C52: 4 | D52: surface | M52: University of Illinois Urbana-Champaign | N52: Illinois Natural History Survey
C53: 4 | D53: pfas | I53: Colleges | M53: University of Illinois Urbana-Champaign | N53: Chemical and Biomolecular Engineering
C54: 3 | D54: transport | E54: pfas | F54: nutrient | G54: Illinois State University | H54: Department of Geography, Geology, and the Environment | I54: College of Liberal Arts & Sciences | M54: University of Illinois Urbana-Champaign | N54: Illinois Sustainable Technology Center | AD54: BASIL’S HARVEST
C55: 3 | D55: urban | E55: urban | F55: stormwater | G55: University of Illinois Urbana-Champaign | H55: Civil and Environmental Engineering | I55: Grainger College of Engineering | M55: Southern Illinois University Carbondale | N55: School of Earth Systems and Sustainability | AD55: ILLINOIS INSTITUTE OF TECHNOLOGY
C56: 3 | D56: groundwater | E56: groundwater | F56: modeling | G56: University of Illinois Urbana-Champaign | H56: Landscape Architecture | I56: College of Fine & Applied Arts | M56: Geography and Geographic Information Science | N56: 2 | AD56: ILLINOIS STATE UNIVERSITY
C57: 3 | D57: energy | E57: energy | F57: agricultural | G57: University of Illinois Urbana-Champaign | H57: Natural Resources & Environmental Sciences | I57: College of Agricultural, Consumer and Environmental Sciences | M57: Illinois Natural History Survey | N57: 3 | AD57: UNIVERSITY OF ILLINOIS URBANA-CHAMPAIGN
C58: 3 | D58: sensing | E58: modeling | F58: groundwater | G58: University of Illinois Urbana-Champaign | H58: Illinois Sustainable Technology Center | I58: Prairie Research Institute | M58: Illinois State Geological Survey | N58: 2 | AD58: SOUTHERN ILLINOIS UNIVERSITY CARBONDALE
C59: 3 | D59: river | E59: stormwater | F59: invasive | G59: University of Illinois Urbana-Champaign | H59: Natural Resources & Environmental Sciences | I59: College of Agricultural, Consumer and Environmental Sciences | M59: Illinois Sustainable Technology Center | N59: 3 | AD59: Source: GISGeography.com
C60: 2 | D60: modeling | E60: hydrology | M60: Landscape Architecture | N60: 1
C61: 2 | D61: effects | E61: agricultural | M61: Natural Resources & Environmental Sciences | N61: 2
C62: 2 | D62: stormwater | E62: invasive | F62: modeling | G62: University of Illinois Urbana-Champaign | H62: Civil and Environmental Engineering | I62: Grainger College of Engineering | M62: Nuclear, Plasma & Radiological Engineering | N62: 1
C63: 2 | D63: hydrology | E63: mississippi | F63: pfas | G63: University of Illinois Urbana-Champaign | H63: Illinois Sustainable Technology Center | I63: Prairie Research Institute | M63: School of Earth Systems and Sustainability | N63: 1
C64: 2 | D64: simulation | E64: climate | F64: hydrology | G64: University of Illinois Urbana-Champaign | H64: Geography and Geographic Information Science | I64: College of Liberal Arts & Sciences | M64: School of Integrative Biology | N64: 1
C65: 2 | D65: model | E65: nutrient | F65: groundwater | G65: University of Illinois Urbana-Champaign | H65: Illinois State Geological Survey | I65: Prairie Research Institute
C66: 2 | D66: implications | F66: energy | G66: University of Illinois Urbana-Champaign | H66: Food Science & Human Nutrition | I66: College of Agricultural, Consumer and Environmental Sciences
C67: 2 | D67: agricultural | F67: agricultural | G67: Not for profit | H67: Basil's Harvest | I67: Non-Profit
C68: 2 | D68: assessment | F68: pfas | G68: Illinois Institute of Technology | H68: Civil, Architectural, and Environmental Engineering | I68: Armour College of Engineering
C69: 2 | D69: land | F69: mississippi | G69: University of Illinois Urbana-Champaign | H69: Civil and Environmental Engineering | I69: Grainger College of Engineering
C70: 2 | D70: low-cost
C71: 2 | D71: contamination | F71: nutrient | G71: Illinois Institute of Technology | H71: Civil, Architectural, and Environmental Engineering | I71: Armour College of Engineering
C72: 2 | D72: quality | F72: agricultural | G72: University of Illinois Urbana-Champaign | H72: Geography and Geographic Information Science | I72: College of Liberal Arts & Sciences
C73: 2 | D73: invasive | F73: modeling | G73: University of Illinois Urbana-Champaign | H73: Nuclear, Plasma & Radiological Engineering | I73: Grainger College of Engineering
C74: 2 | D74: upper | F74: hydrology | G74: University of Illinois Urbana-Champaign | H74: School of Integrative Biology | I74: College of Liberal Arts & Sciences
C75: 2 | D75: mississippi | F75: invasive | G75: University of Illinois Urbana-Champaign | H75: Illinois Natural History Survey | I75: Prairie Research Institute
C76: 2 | D76: basin | F76: pfas | G76: Illinois Institute of Technology | H76: Civil, Architectural, and Environmental Engineering | I76: Armour College of Engineering
C77: 2 | D77: assessing | F77: energy | G77: University of Illinois Urbana-Champaign | H77: Illinois State Geological Survey | I77: Prairie Research Institute
C78: 2 | D78: harmful | F78: invasive | G78: University of Illinois Urbana-Champaign | H78: Illinois Natural History Survey | I78: Prairie Research Institute
C79: 2 | D79: aqueous | F79: modeling | G79: University of Illinois Urbana-Champaign | H79: Civil and Environmental Engineering | I79: Grainger College of Engineering
C80: 2 | D80: floodplain
C81: 2 | D81: thermal | F81: hydrology | G81: University of Illinois Urbana-Champaign | H81: Illinois Natural History Survey | I81: Prairie Research Institute
C82: 2 | D82: interactions | F82: pfas | G82: University of Illinois Urbana-Champaign | H82: Chemical and Biomolecular Engineering | I82: College of Liberal Arts & Sciences
C83: 2 | D83: climate | F83: pfas | G83: University of Illinois Urbana-Champaign | H83: Illinois Sustainable Technology Center | I83: Prairie Research Institute
C84: 2 | D84: enemy | F84: modeling | G84: Southern Illinois University Carbondale | H84: School of Earth Systems and Sustainability | I84: College of Agricultural, Life, and Physical Sciences
C85: 2 | D85: nutrient
C86: 2 | D86: sources
C87: 2 | D87: use
C88: 2 | D88: removal
C89: 2 | D89: machine
C90: 2 | D90: learning
C91: 2 | D91: development
C92: 2 | D92: systems

Sheet Sheet3
A1: term | B1: institution | C1: Department
A2: agricultural | B2: University of Illinois Urbana-Champaign | C2: Natural Resources & Environmental Sciences
A3: agricultural | B3: Not for profit | C3: Basil's Harvest
A4: agricultural | B4: University of Illinois Urbana-Champaign | C4: Geography and Geographic Information Science
A5: energy | B5: University of Illinois Urbana-Champaign | C5: Food Science & Human Nutrition
A6: energy | B6: University of Illinois Urbana-Champaign | C6: Illinois State Geological Survey
A7: groundwater | B7: University of Illinois Urbana-Champaign | C7: Illinois Sustainable Technology Center
A8: groundwater | B8: University of Illinois Urbana-Champaign | C8: Illinois State Geological Survey
A9: hydrology | B9: University of Illinois Urbana-Champaign | C9: Geography and Geographic Information Science
A10: hydrology | B10: University of Illinois Urbana-Champaign | C10: School of Integrative Biology
A11: hydrology | B11: University of Illinois Urbana-Champaign | C11: Illinois Natural History Survey
A12: invasive | B12: University of Illinois Urbana-Champaign | C12: Natural Resources & Environmental Sciences
... A28: stormwater | B28: University of Illinois Urbana-Champaign | C28: Civil and Environmental Engineering

Sheet Sheet2
A1: 7 | B1: illinois | G1: term | H1: institution | K1: Scientific Topic | L1: Institution | M1: Departments | N1: Scientific Topic
A2: 7 | B2: water | G2: agricultural | H2: University of Illinois Urbana-Champaign | J2: 2 | K2: agricultural | L2: University of Illinois Urbana-Champaign | M2: Natural Resources & Environmental Sciences | N2: agricultural | Q2: agricultural | R2: University of Illinois Urbana-Champaign | S2: Natural Resources & Environmental Sciences
A3: 4 | B3: surface | E3: agricultural | G3: agricultural | H3: Not for profit | M3: Geography and Geographic Information Science | Q3: agricultural | R3: Not for profit | S3: Basil's Harvest
A4: 4 | B4: pfas | E4: agricultural | G4: agricultural | H4: University of Illinois Urbana-Champaign | J4: 1 | K4: agricultural | L4: Not for profit | M4: Basil's Harvest | N4: agricultural | Q4: agricultural | R4: University of Illinois Urbana-Champaign | S4: Geography and Geographic Information Science
A5: 3 | B5: transport | E5: agricultural | G5: energy | H5: University of Illinois Urbana-Champaign | J5: 2 | K5: energy | L5: University of Illinois Urbana-Champaign | M5: Food Science & Human Nutrition | N5: energy | Q5: energy | R5: University of Illinois Urbana-Champaign | S5: Food Science & Human Nutrition
A6: 3 | B6: urban | E6: energy | G6: energy | H6: University of Illinois Urbana-Champaign | M6: Illinois State Geological Survey | Q6: energy | R6: University of Illinois Urbana-Champaign | S6: Illinois State Geological Survey
A7: 3 | B7: groundwater | E7: energy | G7: groundwater | H7: University of Illinois Urbana-Champaign | J7: 2 | K7: groundwater | L7: University of Illinois Urbana-Champaign | M7: Illinois Sustainable Technology Center | N7: groundwater | Q7: groundwater | R7: University of Illinois Urbana-Champaign | S7: Illinois Sustainable Technology Center
A8: 3 | B8: energy | E8: groundwater | G8: groundwater | H8: University of Illinois Urbana-Champaign | M8: Illinois State Geological Survey | Q8: groundwater | R8: University of Illinois Urbana-Champaign | S8: Illinois State Geological Survey
A9: 3 | B9: sensing | E9: groundwater | G9: hydrology | H9: University of Illinois Urbana-Champaign | J9: 3 | K9: hydrology | L9: University of Illinois Urbana-Champaign | M9: Geography and Geographic Information Science | N9: hydrology | Q9: hydrology | R9: University of Illinois Urbana-Champaign | S9: Geography and Geographic Information Science
A10: 3 | B10: river | E10: hydrology | G10: hydrology | H10: University of Illinois Urbana-Champaign | M10: School of Integrative Biology | Q10: hydrology | R10: University of Illinois Urbana-Champaign | S10: School of Integrative Biology
A11: 2 | B11: modeling | E11: hydrology | G11: hydrology | H11: University of Illinois Urbana-Champaign | M11: Illinois Natural History Survey | Q11: hydrology | R11: University of Illinois Urbana-Champaign | S11: Illinois Natural History Survey
A12: 2 | B12: effects | E12: hydrology | G12: invasive | H12: University of Illinois Urbana-Champaign | J12: 3 | K12: invasive | L12: University of Illinois Urbana-Champaign | M12: Natural Resources & Environmental Sciences | N12: invasive | Q12: invasive | R12: University of Illinois Urbana-Champaign | S12: Natural Resources & Environmental Sciences
A13: 2 | B13: stormwater | E13: invasive | G13: invasive | H13: University of Illinois Urbana-Champaign | M13: Illinois Natural History Survey | Q13: invasive | R13: University of Illinois Urbana-Champaign | S13: Illinois Natural History Survey
A14: 2 | B14: hydrology | E14: invasive | G14: invasive | H14: University of Illinois Urbana-Champaign | J14: 1 | K14: mississippi | L14: University of Illinois Urbana-Champaign | M14: Civil and Environmental Engineering | N14: mississippi | Q14: invasive | R14: University of Illinois Urbana-Champaign | S14: Illinois Natural History Survey
A15: 2 | B15: simulation | E15: invasive | G15: mississippi | H15: University of Illinois Urbana-Champaign | J15: 4 | K15: modeling | L15: University of Illinois Urbana-Champaign | M15: Landscape Architecture | N15: modeling | Q15: mississippi | R15: University of Illinois Urbana-Champaign | S15: Civil and Environmental Engineering
A16: 2 | B16: model | E16: mississippi | G16: modeling | H16: University of Illinois Urbana-Champaign | M16: Civil and Environmental Engineering | Q16: modeling | R16: University of Illinois Urbana-Champaign | S16: Landscape Architecture
A17: 2 | B17: implications | E17: modeling | G17: modeling | H17: University of Illinois Urbana-Champaign | M17: Nuclear, Plasma & Radiological Engineering | Q17: modeling | R17: University of Illinois Urbana-Champaign | S17: Civil and Environmental Engineering
A18: 2 | B18: agricultural | E18: modeling | G18: modeling | H18: University of Illinois Urbana-Champaign | M18: Civil and Environmental Engineering | Q18: modeling | R18: University of Illinois Urbana-Champaign | S18: Nuclear, Plasma & Radiological Engineering
A19: 2 | B19: assessment | E19: modeling | G19: modeling | H19: University of Illinois Urbana-Champaign | J19: 1 | K19: modeling | L19: Southern Illinois University Carbondale | M19: School of Earth Systems and Sustainability | N19: modeling | Q19: modeling | R19: University of Illinois Urbana-Champaign | S19: Civil and Environmental Engineering
A20: 2 | B20: land | E20: modeling | G20: modeling | H20: Southern Illinois University Carbondale | J20: 1 | K20: nutrient | L20: Illinois State University | M20: Department of Geography, Geology, and the Environment | N20: nutrient | Q20: modeling | R20: Southern Illinois University Carbondale | S20: School of Earth Systems and Sustainability
A21: 2 | B21: low-cost | E21: nutrient | G21: nutrient | H21: Illinois State University | J21: 1 | K21: nutrient | L21: Illinois Institute of Technology | M21: Civil, Architectural, and Environmental Engineering | N21: nutrient | Q21: nutrient | R21: Illinois State University | S21: Department of Geography, Geology, and the Environment
A22: 2 | B22: contamination | E22: nutrient | G22: nutrient | H22: Illinois Institute of Technology | J22: 3 | K22: pfas | L22: University of Illinois Urbana-Champaign | M22: Illinois Sustainable Technology Center | N22: pfas | Q22: nutrient | R22: Illinois Institute of Technology | S22: Civil, Architectural, and Environmental Engineering
A23: 2 | B23: quality | E23: pfas | G23: pfas | H23: University of Illinois Urbana-Champaign | M23: Chemical and Biomolecular Engineering | Q23: pfas | R23: University of Illinois Urbana-Champaign | S23: Illinois Sustainable Technology Center
A24: 2 | B24: invasive | E24: pfas | G24: pfas | H24: Illinois Institute of Technology | M24: Illinois Sustainable Technology Center | Q24: pfas | R24: Illinois Institute of Technology | S24: Civil, Architectural, and Environmental Engineering
A25: 2 | B25: upper | E25: pfas | G25: pfas | H25: Illinois Institute of Technology | J25: 2 | K25: pfas | L25: Illinois Institute of Technology | M25: Civil, Architectural, and Environmental Engineering | N25: pfas | Q25: pfas | R25: Illinois Institute of Technology | S25: Civil, Architectural, and Environmental Engineering
A26: 2 | B26: mississippi | E26: pfas | G26: pfas | H26: University of Illinois Urbana-Champaign | J26: 1 | K26: stormwater | L26: University of Illinois Urbana-Champaign | M26: Civil and Environmental Engineering | N26: stormwater | Q26: pfas | R26: University of Illinois Urbana-Champaign | S26: Chemical and Biomolecular Engineering
A27: 2 | B27: basin | E27: stormwater | G27: pfas | H27: University of Illinois Urbana-Champaign | Q27: pfas | R27: University of Illinois Urbana-Champaign | S27: Illinois Sustainable Technology Center
A28: 2 | B28: assessing | G28: stormwater | H28: University of Illinois Urbana-Champaign | Q28: stormwater | R28: University of Illinois Urbana-Champaign | S28: Civil and Environmental Engineering
A29: 2 | B29: harmful
A30: 2 | B30: aqueous
A31: 2 | B31: floodplain
A32: 2 | B32: thermal
A33: 2 | B33: interactions
A34: 2 | B34: climate
A35: 2 | B35: enemy
A36: 2 | B36: nutrient
A37: 2 | B37: sources
A38: 2 | B38: use
A39: 2 | B39: removal
A40: 2 | B40: machine
... A218: 1 | B218: approach

Sheet Sheet4
A2: 11illinois 11 water 8 thermal 6 concentrations 5 test 5 urban 5 surface 5 river 5 subsurface 5 system 5 chlorine 4 tracer 4 nitrate 4 groundwater 4 pfas 4 energy 4 sensing 4 watershed 4 drainage 4 systems 4 tile 4 travel 4 higher 4 outlet 4 uas 3 transport 3 saturated 3 modeling 3 heat 3 model 3 land 3 quality 3 nutrient 3 use 3 removal 3 associated 3 waters 3 discharge 3 time 3 reduction 3 wetland 3 whereas 3 response 3 lspiv 3 mean 3 growth 3 trt 3 dtrt 2 buffer 2 effects 2 stormwater 2 hydrology 2 spatial 2 simulation 2 implications 2 design 2 chicago 2 toward 2 better 2 agricultural 2 assessment 2 management 2 understanding 2 plant 2 low-cost 2 contamination 2 movement 2 invasive 2 upper 2 mississippi 2 basin 2 assessing 2 harmful 2 aqueous 2 floodplain 2 interactions 2 climate 2 enemy 2 sources 2 production 2 using 2 machine 2 learning 2 sediment 2 streams 2 state 2 area 2 contaminated 2 areas 2 development 2 approach 2 sbzs 2 prior 2 times 2 distances 2 sbz 2 materials 2 initial 2 conducted 2 approximately 2 days 2 wells 2 gradient 2 data 2 along 2 used 2 help 2 additionally 2 research 2 organic 2 matter 2 inlet 2 decreased 2 locations 2 known 2 concentration 2 spikes 2 precipitation 2 events 2 infiltration 2 application 2 provided 2 flow 2 impacted 2 downstream 2 measurements 2 two 2 camera 2 velocities 2 obtaining 2 finally 2 potential 2 floating 2 improve 2 investigated 2 soil 2 applied 2 source 2 distributed 2 homogeneous 2 properties 2 fo-dts 2 layer 2 conditions 2 fungal 2 mycelia 2 fly 2 ash11water8thermal7showed6results6concentrations5test5urban5surface5river5subsurface5system5cl4tracer4nitrate4within4groundwater4pfas4energy4sensing4watershed4drainage4systems4tile4travel4higher4outlet4uas3transport3saturated3modeling3heat3model3land3quality3nutrient3use3removal3associated3waters3discharge3time3reduction3wetland3whereas3response3lspiv3mean3growth3trt3dtrt2buffer2effects2stormwater2hydrology2spatial2simulation2implications2design2chicago2toward2better2agricultural2assessment2management2understanding2plant2low-cost2contamination2movement2invasive2upper2mississippi2basin2assessing2harmful2aqueous2floodplain2interactions2climate2enemy2sources2production2using2machine2learning2sediment2streams2state2area2contaminated2areas2development2approach2sbzs2prior2times2distances2sbz2materials2initial2conducted2approximately2days2wells2gradient2data2along2used2help2additionally2research2organic2matter2inlet2decreased2locations2known2concentration2spikes2precipitation2events2infiltration2application2provided2flow2impacted2downstream2measurements2two2camera2velocities2obtaining2finally2potential2floating2improve2investigated2soil2applied2source2distributed2homogeneous2properties2fo-dts2layer2conditions2fungal2mycelia2fly2ash1utilizing1calculate1fate1zone1green1infrastructure1implementation1islands1coupled1runoff1physical1case1drought1irrigation1improving1stress1crops1noah1mp1mycelial1stabilization1coal1combustion1products1reduce1arsenic1selenium1deterrent1fishes1waterway1feasibility1nonpotable1reuse1efficacious1recyclable1inorganic1adsorbent1remove1matrices1morphology1inundation1riparian1ecology1context1changing1rivers1installation1underground1battery1triboelectric1devices1water-motion1harvesting1regenerative1agriculture1human1health1nexus1age1change1containment1per1polyfluoroalkyl1substances1protect1ecohydraulic1multiple1species1analyzing1algal1blooms1long1lake1reducing1wastewater1evaluating1fine1headwater1intensively1managed1landscapes1hybrid1plasma-electrocatalyst1activated1process1synthesis1ammonia1air1measuring1effect1flood1pulses1ecosystem1function1lakes1created1mining1kickapoo1recreation1habitat1selection1juvenile1black1carp1predatory1native1nonnative1bivalves1testing1package1modflow1connecting1models1causes1consequences1mollusk1invasions1throughout1physics-informed1parameter1estimation1surrogate1impacts1environmental1aquatic1biodiversity1vermillion1next-generation1electrochemical1short-chain1remediation1fast1energy-efficient1destruction1compounds1piezoelectric1formulations1sorbents1feed-pfas1vulnerability1public1droughts1integrated1remote1social1zones1considered1possible1best1practice1intercept1however1needed1effective1documented1quantified1situated1glacial1calculations1suggested1injection1down-gradient1reached1peak1result1anticipated1hydraulic1despite1shorter1introduced1removed1path1observation1different1diversion1linear1relationship1distance1traveled1develop1provide1optimal1given1limitations1available1achieve1targets1combat1hypoxia1gulf1mexico1caused1lack1denitrification1treatment1wetlands1bureau1county1highest1nearest1half1consistently1labile1abundance1denitrifying1bacteria1resulting1efficiency1captured1moved1seasonal1trends1identified1chloride1deicing1agents1elevated1winter1periodic1summer1followed1appeared1stored1aquifer1released1continued1road1salts1continue1elevate1cease1fully1recover1years1residual1remain1numerical1evaluation1incorporating1transient1revealed1around1setting1dilution1occurred1discharging1agriculturally1derived1comparison1performance1tripod-mounted1large-scale1particle1image1velocimeter1unmanned1aerial1relation1methods1nearly1identical1tripod1extended1high1enough1view1entire1channel1width1oscillated1wind1although1completely1steady1seconds1generally1unaffected1even1situations1flexible1option1velocity1thus1greatly1increased1capability1large1relatively1easy1obtain1gardens1stream1nitrogen1lower1flowing1past1garden1biofuels1crab1orchard1national1wildlife1refuge1grade1biosolids1amendment1nutrients1sunflowers1helianthus1annuus1found1low-nitrogen1fertilizer1terms1addition1low1hexavalent1chromium1cr1vi1remediated1biodiesel1obtained1seeds1making1renewable1fuel1farm1university1urbana-champaign1meter-deep1borehole1analyze1versus1heterogenous1separately1couples1fiber-optic1temperature1allowing1analysis1simulations1indicated1resolution1property1predictions1assuming1solid1work1evaluate1working1efficacy1balance1ground1pumps1ongoing1installed1vertically1attached1pvc1pipe1adjacent1boreholes1cased1sealed1sidewall1bentonite1grout1profiles1measured1year1period1transfer1unsaturated1numerically1evaluated1heterogeneities1thermo-geology1construction1natural1geothermal1shallow1water-impermeable1biological1barriers1assessed1presence1inhibit1fungi1produced1massive1effectively1prevent1impoundment1offering1innovative1sustainable1cost-effective1route1manage1legacy1sites
